Workbook

Sheet 01 Control
A1: PAPA PASTA | MENU & SUPPLIER COSTING MODEL
A2: Master control panel. Every yellow cell is an input you own. Everything else is a formula - do not overtype it.
B4: GLOBAL ASSUMPTIONS - edit the yellow cells only
B5: Assumption | C5: Value | D5: Unit | E5: Why it matters / where it is used
B6: VAT rate | C6: 0.15 | D6: % | E6: Converts excl-VAT costing into menu board prices.
B7: Default waste / over-portion allowance | C7: 0.05 | D7: % | E7: Added to every BOM line unless the line overrides it.
B8: Standard DRIED pasta portion | C8: 111 | D8: g | E8: Dried weight into the basket. Set to hold DRY MATTER constant against the old 140 g fresh portion (140 x 70% = 98 g solids; 111 x 88% = 97.7 g), so the plate the customer eats does not change.
B9: Cooked yield multiplier | C9: 2.2 | D9: x dry | E9: Dried pasta absorbs water on the boil. Portion x this = the weight of pasta that actually lands in the bowl. 111 g dried gives about 244 g cooked.
B10: Flour as-received moisture | C10: 0.12 | D10: % | E10: Bulk flour carries ~12% water. Subtracted to get true dry solids - this is what the yield is built on.
B11: Finished DRIED pasta moisture | C11: 0.12 | D11: % | E11: Shelf-stable dried pasta finishes at or below 12%. Solids / (1 - this) = dried pasta output. This is the number that changed when dried replaced fresh-daily.
B12: Pasta process loss (mix to portioned) | C12: 0.05 | D12: % | E12: Dough lost to mixing, extrusion, trim and trays. Applied AFTER the moisture mass balance.
B13: Central Kitchen labour & energy | C13: 6.5 | D13: R / kg | E13: Cost to cook, chill/freeze and pack one kg of sauce. PLACEHOLDER - replace with real CK numbers.
B14: Central Kitchen overhead & distribution | C14: 4 | D14: R / kg | E14: Rent, plant depreciation, QA and cold-chain delivery per kg. PLACEHOLDER.
B15: Central Kitchen margin to franchisee | C15: 0.25 | D15: % | E15: The mark-up the CK earns selling frozen sauce to franchisees.
B16: Store labour allowance | C16: 0.12 | D16: % | E16: Percentage of food cost carried as store labour, for the fully-loaded view.
B17: Target GP% - Core menu | C17: 0.7 | D17: % | E17: Drives the recommended sell price on Tier 1 dishes.
... B31: Price point C | C31: 135 | D31: R incl | E31: High anchor.
B33: HOW THIS WORKBOOK WORKS
B34: Tab | C34: What it does
B35: 03 Suppliers | C35: Your supplier list. Add every business you approach here first, then use the name in the price tabs.
B36: 04 SKU Master | C36: THE ENGINE - and the tab your team types into. One row per ingredient, five supplier price slots side by side. Columns AK-AQ automatically pick the CHEAPEST price, name the supplier who gave it, and divide by yield to get the usable cost. This is the only ingredient price the rest of the model ever reads.
B37: 05 Packaging Master | C37: Identical five-supplier structure for packaging - store, central kitchen and retail.
B38: 06 Pasta Dough BOM | C38: The four Golden Balance formulas the franchisee makes in-store. Baker's % -> 10 kg batch -> cost per 140 g serving.
B39: 07 Sauce BOM (CK) | C39: The nine core sauces the Central Kitchen makes. Batch cost -> cost per kg -> + CK labour, overhead and pouch -> + CK margin = the transfer price the franchisee pays.
B40: 09 Cost Index | C40: Auto-built bridge. Turns each dough and sauce into a single cost-per-gram the menu tabs can look up.
B41: 10 Core Menu BOM | C41: Tier 1 - the nine signature dishes, three salads and the add-ons, line by line.
B42: 11 Seasonal Menu BOM | C42: Tier 2 - all 36 seasonal drops across the 3-year rotation, line by line.
B43: 11 Final Menu | C43: The answer sheet. Every dish, its cost, its GP and its selling price. Read this one.
B44: 17 Quote Log | C44: The paper trail. Every quote you are ever given, dated, with the reference. Slot 6 and beyond live here, and it is where MOQ, lead time and the quote reference are recorded.
B45: 18 Production Capacity | C45: THE EQUIPMENT TAB. The 9-pot cooker, the sauce warmers, the wok cookers, the extruder and the drying racks as variables - covers per hour by station, the binding bottleneck, and whether the store can dry enough pasta overnight to serve what it can sell tomorrow. Also the sauce station loadout: which sauce sits in a warmer and which is finished to order.
... B47: 20 Quote Coverage | C47: READ ME - which SKUs still need supplier quotes; turns green as quotes land on 04/05.
B49: COLOUR LEGEND
B50: Yellow fill, blue text | C50: You type here. An input you own.
B51: White / grey, black text | C51: Formula. Do not overtype - it will break the chain.
B52: Green fill | C52: A final answer the rest of the model reads.
B53: Red text | C53: A flag that needs your decision.
B56: LOCKED - settled decisions. Everything below is closed; do not reopen it in the model.
C57: What is now fixed | E57: Detail
B58: DRIED IN STORE, SERVED FRESH. (Ricardo, 6 Sep 2026 - closes the fresh-vs-dried conflict) | E58: Extrude on the GUSGT108, dry on fan-assisted mesh racks, re-bag into sealed ambient bins, portion DRIED into the basket, boil 90-180 s, finish in the wok. The Kitchen Workflow OPS pack was right about the process; the brand position stays 'fresh' - made in this store, this morning, in front of the customer. Portion is 111 g dried, set to hold DRY MATTER constant against the old 140 g fresh portion (140 x 70% = 98 g solids; 111 x 88% = 97.7 g). That is deliberate: the plate the customer eats, the servings per batch and every Aug-2026 cost benchmark are all unchanged.
B59: Ambient pasta storage. No pasta fridge in store. | E59: Dried pasta goes into sealed bins at room temperature with roughly a 30-day life, not 5-7 chilled days. This is what resolves the OPS pack's missing refrigerated pasta storage - there was never meant to be any. The undercounter fridges stay for sauces, mise en place and toppings.
B60: The line is a 9-pot cooker, sauce warmers and 3-4 automatic wok cookers. (Ricardo, 6 Sep 2026) | E60: This supersedes the OPS pack's 2-basket boiler, 3 lidded vessels and 2-plate hob. Every one of these is a variable on 18 Production Capacity, which works out covers per hour by station and names the binding bottleneck.
B61: Sauce service method is a TASTE rule, not a capacity rule. | E61: A sauce is held in a warmer only where four hours at 63 C makes it the same or better - the tomato bases, the two braises and the two stabilised creams. Carbonara, Quattro Formaggi and Aglio e Olio are finished to order in the wok because holding them ruins them; pesto and chermoula are never heated at all. The wok cookers are what make that affordable. Full allocation on 18 Production Capacity.
B62: Board prices: SET B (Menu Concepts pack) is the print set. (Ricardo, 6 Sep 2026 - 'fix it') | E62: Set B is adopted and pre-loaded into Approved Sell on 12 Final Menu. It is the only set that carries the whole menu - beverages, Build Your Own and the add-on ladder - and its lower entry price (R65 Napoletana, R85 Bolognese) suits a volume-driven QSR. Set A survives on 16 Menu Price Reference as the pre-agreed step-up if landed costs come in high.
B63: Four formulas, one machine, one backbone. | E63: Bokgat Base, Protein+ Pro, Farmhouse, Chickpea Power Pro. Baker's percentages unchanged from the spec. Ingredient ceilings are carried on the SKU notes: lupin 20%, lion's mane 5%, microgreens 3%, chickpea 25%, inulin ~12%.
B64: Yield is a mass balance, not the manual's 70. | E64: Dry blend x (1 - flour moisture) + salt = dry solids; solids / (1 - finished pasta moisture) = fresh output; then process loss. That gives 87-88 servings planning and 91-93 ceiling per 10 kg batch. The manual's 70 would need 143 g of dry blend per 140 g portion, which is not physically possible - it is carried as a worst-case reference line only.
B65: No in-store drying cabinet. | E65: Fan-assisted mesh drying racks replace it - 6 racks x 10 trays x 2 kg wet is the planning figure on 18 Production Capacity, and rack space is a real constraint on a dried process. The TBD dryer line comes out of the capex model.
B66: Machine: Gustotek GT Line GUSGT108. | E66: 16-20 kg/h, Culinary Equipment Co., Lanseria, 011 701 2200. A locally stocked SA SKU - no freight, no FX, no import lead time on the extruder.
B67: The Aug-2026 per-serving costs are sound. | E67: They were already computed on the ~98 g dry-matter basis, not on the 70-serving divisor. They are carried on tab 06 as a benchmark band so live quotes can be checked against them the moment they land.
B69: OPEN DECISIONS - these change the numbers, so they need your call
B70: # | C70: Decision | E70: Why it matters
B71: 1 | C71: CONFLICT: the OPS pack says sauces arrive CHILLED at 5 C or below, not frozen. | E71: It reads 'chilled sauces: probe and log - must read <=5 C', 'reheat ONCE to >=75 C core, then hold >=63 C', with a 4-hour hot window. You told me frozen for overnight defrost, and this model prices freeze-grade pouches on that basis. Chilled is a different pouch, a different cold chain and a shorter delivery cycle. Gap G10 in that pack already flags the delivery temperature as an assumption.
B72: 2 | C72: Run one witnessed 10 kg batch and weigh the output off the racks. | E72: This is the single biggest unknown left in the pasta line. It collapses the 87-vs-91 servings band AND the drying-rack density estimate in one morning's work. Until it happens every batch-planning figure carries a range.
B73: 3 | C73: Four commissary pre-blends, or four in-store formulas? | E73: This one restructures the model. Pre-blends keep the 'franchisee never blends flour' moat: the dough becomes a Central Kitchen product with a transfer price, exactly like the sauces on 07 and 08, and tab 06 gets rebuilt as a CK tab. In-store formulas leave it as it is now - a franchise raw-material build off 04 SKU Master. Say which and I will restructure it.
B74: 4 | C74: Extruder in every store, or central production with refrigerated distribution? | E74: Central production solves the drying-space problem and the consistency problem at once - but it takes the extruder out of the store, and the in-store Pasta Theatre with it. That is a brand call, not an operations one.
B75: 5 | C75: Sauce warmer wells: 6 is the model's assumption. Confirm the actual well count. | E75: The core menu needs 5 wells held at once (Napoletana, Bolognese, Alfredo, Arrabbiata, Boscaiola) and the live seasonal drop needs 1-2 more. Six is the minimum that runs the full menu; eight gives you a spare well for a second seasonal and for changeover. Below six, a core sauce has to come off the line. Set the real number on 18 Production Capacity and the check on 14 Model Health will tell you if the menu still fits.
B76: 6 | C76: Wok cookers: 3 or 4? The model says 4. | E76: Every bowl passes through a wok. Three woks give about 135 covers/hour and the woks become the binding station; four give about 180, which pushes the binding station up to the 9-pot cooker at about 162. So the fourth wok buys roughly 27 covers/hour and moves the constraint onto a machine you have already bought. The OPS pack's peak planning figure was 60-80 covers/hour, so even three clears it on paper - but with three, the wok station is the only one with no headroom and the cooker upstream sits idle. Take the fourth.
B77: 7 | C77: Slushee machine bowls: 6 flavours are now specced, 4 bowls are assumed. | E77: Rooibos, Naartjie, Granadilla, Strawberry, Blue Bubblegum, Ginger-Lime and Papa's Red plus cream soda and lemonade is nine possible flavours against four live bowls. Rooibos and Blue Bubblegum should be permanent (the SA hero and the kids anchor); the other two bowls rotate. Confirm the machine's bowl count.
B78: 8 | C78: Quote baobab first. | E78: It is the largest single cost swing in three of the four formulas. Every dough cost on tab 06 stays blank until it and the other flours are priced.
B79: 9 | C79: Farmhouse total dry blend: 10.20 kg here, 10.00 kg in the spec sheet. | E79: The spec's own baker's percentages for Farmhouse sum to 102%, which is 10.20 kg on a 10 kg batch - so its stated 10.00 kg total does not match its own recipe. This model uses the actual line quantities (10.20 kg), which puts Farmhouse at 88 planning servings rather than 87. Confirm which is right.
B80: 10 | C80: Pork and chicken SKUs from the starter sheet have been removed. | E80: The concept doc sets a brand-wide halaal standard: 100% pork-free, beef the only meat. Pork chunks and chicken strips were live SKUs in the old sheet. Confirm they are gone for good.
B81: 11 | C81: Boscaiola is costed on Fusilli, not Rigatoni. | E81: The old sheet used PP-PASTA-RIG-BOSC. The concept doc assigns Boscaiola to Fusilli. This model follows the doc - the SKU is now PP-PASTA-FUS-BOSC.
B82: 12 | C82: Four supplier quotes look like pack prices, not per-kg prices. | E82: Peas R348.50/kg, Asparagus R439.50/kg, Carrots R148.00/kg and Radish microgreens R19.06/kg are out of line with the rest of the Ferreira Fresh and TLF lists. Re-confirm the unit before these hit a menu price.
... B85: 15 | C85: Sauce pouches are sized at 2 kg (1 kg for pesto, the Aglio kit, chakalaka and chermoula). | E85: Thawed shelf life is one trading day, so a pouch should be one day-part of demand. Seasonal bases run 13-week windows, so their pouch sizing matters more - an oversized pouch on a slow drop is straight waste. Confirm against forecast covers per store.
B87: OPERATING FACTS TAKEN FROM THE DRIVE - Kitchen Workflow OPS pack v1.0, 1 Sep 2026
B88: Central kitchen sized for | C88: 4-10 outlets (this model now defaults to 6)
B89: Peak store capacity | C89: OPS pack planning estimate was 60-80 covers/hour with 3-4 crew. The 9-pot / 4-wok line modelled on 18 Production Capacity is well above that - see the bottleneck line
B90: Crew modes | C90: 2 quiet / 3 standard / 4 peak
B91: Order to collect target | C91: 5 minutes at peak; 90-180 s boil plus about 60 s finish
B92: Sauce holding on the line | C92: SUPERSEDED. Now sauce warmer wells (6 assumed) at 63 C or above for 4 hours, then chill or discard. Only the sauces that taste the same or better held go in them
B93: Pasta theatre | C93: Real production, watched. Extrude in the window, dry overnight on the racks, cook tomorrow. The dried batch sits in sealed ambient bins by the cooker
B94: Line equipment (Ricardo, 6 Sep) | C94: 9-pot pasta cooker, sauce warmers, 3-4 automatic wok cookers finishing pasta and sauce together. All variables on 18 Production Capacity
B95: Menu price status | C95: Set B (Menu Concepts) adopted 6 Sep and pre-loaded into Approved Sell on 12 Final Menu. Still to be re-tested against landed costs the moment quotes arrive - see 16 Menu Price Reference
B97: Built 2026-09-06. Pasta: Papa Pasta Dough & Yield Specification v1.0 (5 Sep 2026), which supersedes Coda 02.03. Menu, sauces and seasonal rotation: the Papa Pasta Concept Build doc (02.01 Core Menu, 02.01.2 The Nine Core Sauces, 02.02.1 Seasonal Drops). Plus the existing WorkDrive starter sheet. Sauce and dish quantities are engineering estimates for costing - confirm on a production run. No price has been invented: every cost cell is blank until a real supplier quote is entered.

Sheet 02 Lists
A1: LISTS & UNIT CONVERSIONS
A2: The conversion table turns a pack price into a cost per gram, millilitre or unit. Add a row if you buy in a unit that is not listed. The lists on the right feed every dropdown in the workbook.
A4: Pack Unit | B4: Base Units | C4: Meaning | E4: Base Unit | F4: Component Type | G4: VAT Basis | H4: RFQ Status | I4: Team Member
A5: g | B5: 1 | C5: gram | E5: g | F5: Pasta | G5: Excl VAT | H5: Not started | I5: PPP1
A6: kg | B6: 1000 | C6: kilogram | E6: ml | F6: Sauce | G6: Incl VAT | H6: Requested | I6: PPP2
A7: mg | B7: 0.001 | C7: milligram | E7: ea | F7: Protein | H7: Chasing | I7: Ricardo
A8: ml | B8: 1 | C8: millilitre | F8: Ingredient | H8: Quoted
A9: L | B9: 1000 | C9: litre | F9: Finish | H9: Declined
A10: ea | B10: 1 | C10: each / unit | F10: Packaging | H10: On hold
A11: pack | B11: 1 | C11: pack treated as 1 unit
A12: case | B12: 1 | C12: case treated as 1 unit - enter total units in Pack Qty
A13: doz | B13: 12 | C13: dozen | E13: Team Member: two people collect quotes (PPP1, PPP2) and Ricardo is the third. Overtype the placeholders with real names here and every Assigned To dropdown on 15 RFQ Tracker and every Relationship Owner on 03 Suppliers picks up the change. Names already chosen on those tabs keep the old text, so rename before you allocate.
A14: punnet | B14: 1 | C14: punnet as 1 unit
A15: tray | B15: 1 | C15: tray as 1 unit
A16: box | B16: 1 | C16: box as 1 unit
A17: sleeve | B17: 1 | C17: sleeve as 1 unit
A18: roll | B18: 1 | C18: roll as 1 unit

Sheet 03 Suppliers
A1: SUPPLIER REGISTER
A2: Every supplier you approach goes here first. Use the exact Supplier Name in the price tabs so the cheapest-price formula can name them back to you. QUOTES ARE is important: if a supplier quotes you INCLUDING VAT, set it here and the model strips the VAT for you automatically. Getting this wrong makes every cost from that supplier 15% too high.
A4: Supplier Code | B4: Supplier Name | C4: Categories Supplied | D4: Contact Person | E4: Phone | F4: Email | G4: Status | H4: Payment Terms | I4: Lead Time (days) | J4: MOQ | K4: Delivery Days | L4: Halaal Certified | M4: Notes | N4: Quotes Are | O4: Relationship Owner
A5: SUP-001 | B5: Ferreira Fresh | C5: Fresh produce | G5: Quoting | M5: Existing quotes 16-17 Aug 2026 | N5: Excl VAT | Q5: ='02 Lists'!$G$5&"" | R5: ='02 Lists'!$I$5&""
A6: SUP-002 | B6: The Local Farmer | C6: Mushrooms & microgreens | G6: Quoting | M6: TLF - also the Farmhouse powder supply chain | N6: Excl VAT | Q6: ='02 Lists'!$G$6&"" | R6: ='02 Lists'!$I$6&""
A7: SUP-003 | G7: To approach | N7: Excl VAT | R7: ='02 Lists'!$I$7&""
A8: SUP-004 | G8: To approach | N8: Excl VAT
A9: SUP-005 | G9: To approach | N9: Excl VAT
A10: SUP-006 | G10: To approach | N10: Excl VAT
A11: SUP-007 | G11: To approach | N11: Excl VAT
A12: SUP-008 | G12: To approach | N12: Excl VAT
N13: Excl VAT
N14: Excl VAT
N15: Excl VAT
N16: Excl VAT
N17: Excl VAT
N18: Excl VAT
N19: Excl VAT
N20: Excl VAT
N21: Excl VAT
N22: Excl VAT
N23: Excl VAT
N24: Excl VAT
... N34: Excl VAT

Sheet 04 SKU Master
A1: INGREDIENT SKU MASTER - 5 SUPPLIER PRICE SLOTS
A2: Type each supplier's pack price into their slot. Columns AK-AQ pick the cheapest automatically. USABLE Cost per Base Unit (column AM) is the single number every recipe in this workbook reads.
A3: THE ITEM | G3: SUPPLIER 1 | M3: SUPPLIER 2 | S3: SUPPLIER 3 | Y3: SUPPLIER 4 | AE3: SUPPLIER 5 | AK3: LOWEST PRICE - CALCULATED, DO NOT TYPE HERE
A4: Ingredient SKU | B4: Category | C4: Item Description | D4: Base Unit | E4: Yield % | F4: Spec / Notes | G4: Supplier Name | H4: Pack Qty | I4: Pack Unit | J4: Pack Cost (as quoted) | K4: Quote Date | L4: Cost per Base Unit | M4: Supplier Name | N4: Pack Qty | O4: Pack Unit | P4: Pack Cost (as quoted) | Q4: Quote Date | R4: Cost per Base Unit | S4: Supplier Name | T4: Pack Qty | U4: Pack Unit | V4: Pack Cost (as quoted) | W4: Quote Date | X4: Cost per Base Unit | Y4: Supplier Name | Z4: Pack Qty | AA4: Pack Unit | AB4: Pack Cost (as quoted) | AC4: Quote Date | AD4: Cost per Base Unit | AE4: Supplier Name | AF4: Pack Qty | AG4: Pack Unit | AH4: Pack Cost (as quoted) | AI4: Quote Date | AJ4: Cost per Base Unit | AK4: LOWEST Cost per Base Unit | AL4: CHEAPEST Supplier | AM4: USABLE Cost per Base Unit (after yield) | AN4: Quotes Held | AO4: Highest Cost per Base Unit | AP4: Price Spread | AQ4: Best Quote Date
A5: PP-WHEAT-SA | B5: Flour / Dough | C5: SA stone-milled whole wheat flour | D5: g | E5: 1 | F5: Strong bread wheat, protein >=13% | L5: =IF(OR($J5="",$H5="",$H5=0),"",$J5/(1+IF(IFERROR(INDEX('03 Suppliers'!$N$5:$N$34,MATCH($G5,'03 Suppliers'!$B$5:$B$34,0)),"Excl VAT")="Incl VAT",'01 Control'!$C$6,0))/($H5*IFERROR(VLOOKUP($I5,'02 Lists'!$A$5:$B$18,2,FALSE()),1))) | R5: =IF(OR($P5="",$N5="",$N5=0),"",$P5/(1+IF(IFERROR(INDEX('03 Suppliers'!$N$5:$N$34,MATCH($M5,'03 Suppliers'!$B$5:$B$34,0)),"Excl VAT")="Incl VAT",'01 Control'!$C$6,0))/($N5*IFERROR(VLOOKUP($O5,'02 Lists'!$A$5:$B$18,2,FALSE()),1))) | X5: =IF(OR($V5="",$T5="",$T5=0),"",$V5/(1+IF(IFERROR(INDEX('03 Suppliers'!$N$5:$N$34,MATCH($S5,'03 Suppliers'!$B$5:$B$34,0)),"Excl VAT")="Incl VAT",'01 Control'!$C$6,0))/($T5*IFERROR(VLOOKUP($U5,'02 Lists'!$A$5:$B$18,2,FALSE()),1))) | AD5: =IF(OR($AB5="",$Z5="",$Z5=0),"",$AB5/(1+IF(IFERROR(INDEX('03 Suppliers'!$N$5:$N$34,MATCH($Y5,'03 Suppliers'!$B$5:$B$34,0)),"Excl VAT")="Incl VAT",'01 Control'!$C$6,0))/($Z5*IFERROR(VLOOKUP($AA5,'02 Lists'!$A$5:$B$18,2,FALSE()),1))) | AJ5: =IF(OR($AH5="",$AF5="",$AF5=0),"",$AH5/(1+IF(IFERROR(INDEX('03 Suppliers'!$N$5:$N$34,MATCH($AE5,'03 Suppliers'!$B$5:$B$34,0)),"Excl VAT")="Incl VAT",'01 Control'!$C$6,0))/($AF5*IFERROR(VLOOKUP($AG5,'02 Lists'!$A$5:$B$18,2,FALSE()),1))) | AK5: =IF(COUNT(L5,R5,X5,AD5,AJ5)=0,"",MIN(L5,R5,X5,AD5,AJ5)) | AL5: =IF($AK5="","",IF(L5=$AK5,$G5,IF(R5=$AK5,$M5,IF(X5=$AK5,$S5,IF(AD5=$AK5,$Y5,IF(AJ5=$AK5,$AE5,"")))))) | AM5: =IF($AK5="","",$AK5/IF($E5="",1,$E5)) | AN5: =COUNT(L5,R5,X5,AD5,AJ5) | AO5: =IF(COUNT(L5,R5,X5,AD5,AJ5)=0,"",MAX(L5,R5,X5,AD5,AJ5)) | AP5: =IF(OR($AK5="",$AO5="",$AO5=0),"",($AO5-$AK5)/$AO5) | AQ5: =IF($AK5="","",IF(L5=$AK5,$K5,IF(R5=$AK5,$Q5,IF(X5=$AK5,$W5,IF(AD5=$AK5,$AC5,IF(AJ5=$AK5,$AI5,"")))))) | AS5: ='02 Lists'!$A$5&"" | AT5: ='03 Suppliers'!$B$5&""
A6: PP-DURUM-WHOLE | B6: Flour / Dough | C6: Whole durum wheat flour | D6: g | E6: 1 | F6: Stone-milled, protein >=13-14%; Protein+ prefers >=14% | L6: =IF(OR($J6="",$H6="",$H6=0),"",$J6/(1+IF(IFERROR(INDEX('03 Suppliers'!$N$5:$N$34,MATCH($G6,'03 Suppliers'!$B$5:$B$34,0)),"Excl VAT")="Incl VAT",'01 Control'!$C$6,0))/($H6*IFERROR(VLOOKUP($I6,'02 Lists'!$A$5:$B$18,2,FALSE()),1))) | R6: =IF(OR($P6="",$N6="",$N6=0),"",$P6/(1+IF(IFERROR(INDEX('03 Suppliers'!$N$5:$N$34,MATCH($M6,'03 Suppliers'!$B$5:$B$34,0)),"Excl VAT")="Incl VAT",'01 Control'!$C$6,0))/($N6*IFERROR(VLOOKUP($O6,'02 Lists'!$A$5:$B$18,2,FALSE()),1))) | X6: =IF(OR($V6="",$T6="",$T6=0),"",$V6/(1+IF(IFERROR(INDEX('03 Suppliers'!$N$5:$N$34,MATCH($S6,'03 Suppliers'!$B$5:$B$34,0)),"Excl VAT")="Incl VAT",'01 Control'!$C$6,0))/($T6*IFERROR(VLOOKUP($U6,'02 Lists'!$A$5:$B$18,2,FALSE()),1))) | AD6: =IF(OR($AB6="",$Z6="",$Z6=0),"",$AB6/(1+IF(IFERROR(INDEX('03 Suppliers'!$N$5:$N$34,MATCH($Y6,'03 Suppliers'!$B$5:$B$34,0)),"Excl VAT")="Incl VAT",'01 Control'!$C$6,0))/($Z6*IFERROR(VLOOKUP($AA6,'02 Lists'!$A$5:$B$18,2,FALSE()),1))) | AJ6: =IF(OR($AH6="",$AF6="",$AF6=0),"",$AH6/(1+IF(IFERROR(INDEX('03 Suppliers'!$N$5:$N$34,MATCH($AE6,'03 Suppliers'!$B$5:$B$34,0)),"Excl VAT")="Incl VAT",'01 Control'!$C$6,0))/($AF6*IFERROR(VLOOKUP($AG6,'02 Lists'!$A$5:$B$18,2,FALSE()),1))) | AK6: =IF(COUNT(L6,R6,X6,AD6,AJ6)=0,"",MIN(L6,R6,X6,AD6,AJ6)) | AL6: =IF($AK6="","",IF(L6=$AK6,$G6,IF(R6=$AK6,$M6,IF(X6=$AK6,$S6,IF(AD6=$AK6,$Y6,IF(AJ6=$AK6,$AE6,"")))))) | AM6: =IF($AK6="","",$AK6/IF($E6="",1,$E6)) | AN6: =COUNT(L6,R6,X6,AD6,AJ6) | AO6: =IF(COUNT(L6,R6,X6,AD6,AJ6)=0,"",MAX(L6,R6,X6,AD6,AJ6)) | AP6: =IF(OR($AK6="",$AO6="",$AO6=0),"",($AO6-$AK6)/$AO6) | AQ6: =IF($AK6="","",IF(L6=$AK6,$K6,IF(R6=$AK6,$Q6,IF(X6=$AK6,$W6,IF(AD6=$AK6,$AC6,IF(AJ6=$AK6,$AI6,"")))))) | AS6: ='02 Lists'!$A$6&"" | AT6: ='03 Suppliers'!$B$6&""
A7: PP-SORGHUM-WHITE | B7: Flour / Dough | C7: SA white sorghum flour | D7: g | E7: 1 | F7: Dehulled, fine mill <=200 um | L7: =IF(OR($J7="",$H7="",$H7=0),"",$J7/(1+IF(IFERROR(INDEX('03 Suppliers'!$N$5:$N$34,MATCH($G7,'03 Suppliers'!$B$5:$B$34,0)),"Excl VAT")="Incl VAT",'01 Control'!$C$6,0))/($H7*IFERROR(VLOOKUP($I7,'02 Lists'!$A$5:$B$18,2,FALSE()),1))) | R7: =IF(OR($P7="",$N7="",$N7=0),"",$P7/(1+IF(IFERROR(INDEX('03 Suppliers'!$N$5:$N$34,MATCH($M7,'03 Suppliers'!$B$5:$B$34,0)),"Excl VAT")="Incl VAT",'01 Control'!$C$6,0))/($N7*IFERROR(VLOOKUP($O7,'02 Lists'!$A$5:$B$18,2,FALSE()),1))) | X7: =IF(OR($V7="",$T7="",$T7=0),"",$V7/(1+IF(IFERROR(INDEX('03 Suppliers'!$N$5:$N$34,MATCH($S7,'03 Suppliers'!$B$5:$B$34,0)),"Excl VAT")="Incl VAT",'01 Control'!$C$6,0))/($T7*IFERROR(VLOOKUP($U7,'02 Lists'!$A$5:$B$18,2,FALSE()),1))) | AD7: =IF(OR($AB7="",$Z7="",$Z7=0),"",$AB7/(1+IF(IFERROR(INDEX('03 Suppliers'!$N$5:$N$34,MATCH($Y7,'03 Suppliers'!$B$5:$B$34,0)),"Excl VAT")="Incl VAT",'01 Control'!$C$6,0))/($Z7*IFERROR(VLOOKUP($AA7,'02 Lists'!$A$5:$B$18,2,FALSE()),1))) | AJ7: =IF(OR($AH7="",$AF7="",$AF7=0),"",$AH7/(1+IF(IFERROR(INDEX('03 Suppliers'!$N$5:$N$34,MATCH($AE7,'03 Suppliers'!$B$5:$B$34,0)),"Excl VAT")="Incl VAT",'01 Control'!$C$6,0))/($AF7*IFERROR(VLOOKUP($AG7,'02 Lists'!$A$5:$B$18,2,FALSE()),1))) | AK7: =IF(COUNT(L7,R7,X7,AD7,AJ7)=0,"",MIN(L7,R7,X7,AD7,AJ7)) | AL7: =IF($AK7="","",IF(L7=$AK7,$G7,IF(R7=$AK7,$M7,IF(X7=$AK7,$S7,IF(AD7=$AK7,$Y7,IF(AJ7=$AK7,$AE7,"")))))) | AM7: =IF($AK7="","",$AK7/IF($E7="",1,$E7)) | AN7: =COUNT(L7,R7,X7,AD7,AJ7) | AO7: =IF(COUNT(L7,R7,X7,AD7,AJ7)=0,"",MAX(L7,R7,X7,AD7,AJ7)) | AP7: =IF(OR($AK7="",$AO7="",$AO7=0),"",($AO7-$AK7)/$AO7) | AQ7: =IF($AK7="","",IF(L7=$AK7,$K7,IF(R7=$AK7,$Q7,IF(X7=$AK7,$W7,IF(AD7=$AK7,$AC7,IF(AJ7=$AK7,$AI7,"")))))) | AS7: ='02 Lists'!$A$7&"" | AT7: ='03 Suppliers'!$B$7&""
A8: PP-BAOBAB | B8: Flour / Dough | C8: SA baobab fruit powder | D8: g | E8: 1 | F8: Soluble fibre + vitamin C. LARGEST SINGLE COST SWING in 3 of 4 formulas - quote this first | L8: =IF(OR($J8="",$H8="",$H8=0),"",$J8/(1+IF(IFERROR(INDEX('03 Suppliers'!$N$5:$N$34,MATCH($G8,'03 Suppliers'!$B$5:$B$34,0)),"Excl VAT")="Incl VAT",'01 Control'!$C$6,0))/($H8*IFERROR(VLOOKUP($I8,'02 Lists'!$A$5:$B$18,2,FALSE()),1))) | R8: =IF(OR($P8="",$N8="",$N8=0),"",$P8/(1+IF(IFERROR(INDEX('03 Suppliers'!$N$5:$N$34,MATCH($M8,'03 Suppliers'!$B$5:$B$34,0)),"Excl VAT")="Incl VAT",'01 Control'!$C$6,0))/($N8*IFERROR(VLOOKUP($O8,'02 Lists'!$A$5:$B$18,2,FALSE()),1))) | X8: =IF(OR($V8="",$T8="",$T8=0),"",$V8/(1+IF(IFERROR(INDEX('03 Suppliers'!$N$5:$N$34,MATCH($S8,'03 Suppliers'!$B$5:$B$34,0)),"Excl VAT")="Incl VAT",'01 Control'!$C$6,0))/($T8*IFERROR(VLOOKUP($U8,'02 Lists'!$A$5:$B$18,2,FALSE()),1))) | AD8: =IF(OR($AB8="",$Z8="",$Z8=0),"",$AB8/(1+IF(IFERROR(INDEX('03 Suppliers'!$N$5:$N$34,MATCH($Y8,'03 Suppliers'!$B$5:$B$34,0)),"Excl VAT")="Incl VAT",'01 Control'!$C$6,0))/($Z8*IFERROR(VLOOKUP($AA8,'02 Lists'!$A$5:$B$18,2,FALSE()),1))) | AJ8: =IF(OR($AH8="",$AF8="",$AF8=0),"",$AH8/(1+IF(IFERROR(INDEX('03 Suppliers'!$N$5:$N$34,MATCH($AE8,'03 Suppliers'!$B$5:$B$34,0)),"Excl VAT")="Incl VAT",'01 Control'!$C$6,0))/($AF8*IFERROR(VLOOKUP($AG8,'02 Lists'!$A$5:$B$18,2,FALSE()),1))) | AK8: =IF(COUNT(L8,R8,X8,AD8,AJ8)=0,"",MIN(L8,R8,X8,AD8,AJ8)) | AL8: =IF($AK8="","",IF(L8=$AK8,$G8,IF(R8=$AK8,$M8,IF(X8=$AK8,$S8,IF(AD8=$AK8,$Y8,IF(AJ8=$AK8,$AE8,"")))))) | AM8: =IF($AK8="","",$AK8/IF($E8="",1,$E8)) | AN8: =COUNT(L8,R8,X8,AD8,AJ8) | AO8: =IF(COUNT(L8,R8,X8,AD8,AJ8)=0,"",MAX(L8,R8,X8,AD8,AJ8)) | AP8: =IF(OR($AK8="",$AO8="",$AO8=0),"",($AO8-$AK8)/$AO8) | AQ8: =IF($AK8="","",IF(L8=$AK8,$K8,IF(R8=$AK8,$Q8,IF(X8=$AK8,$W8,IF(AD8=$AK8,$AC8,IF(AJ8=$AK8,$AI8,"")))))) | AS8: ='02 Lists'!$A$8&"" | AT8: ='03 Suppliers'!$B$8&""
A9: PP-FLAX-GOLDEN | B9: Flour / Dough | C9: Golden flaxseed, cold-milled | D9: g | E9: 1 | F9: Fresh-milled, refrigerated (oxidation control) | L9: =IF(OR($J9="",$H9="",$H9=0),"",$J9/(1+IF(IFERROR(INDEX('03 Suppliers'!$N$5:$N$34,MATCH($G9,'03 Suppliers'!$B$5:$B$34,0)),"Excl VAT")="Incl VAT",'01 Control'!$C$6,0))/($H9*IFERROR(VLOOKUP($I9,'02 Lists'!$A$5:$B$18,2,FALSE()),1))) | R9: =IF(OR($P9="",$N9="",$N9=0),"",$P9/(1+IF(IFERROR(INDEX('03 Suppliers'!$N$5:$N$34,MATCH($M9,'03 Suppliers'!$B$5:$B$34,0)),"Excl VAT")="Incl VAT",'01 Control'!$C$6,0))/($N9*IFERROR(VLOOKUP($O9,'02 Lists'!$A$5:$B$18,2,FALSE()),1))) | X9: =IF(OR($V9="",$T9="",$T9=0),"",$V9/(1+IF(IFERROR(INDEX('03 Suppliers'!$N$5:$N$34,MATCH($S9,'03 Suppliers'!$B$5:$B$34,0)),"Excl VAT")="Incl VAT",'01 Control'!$C$6,0))/($T9*IFERROR(VLOOKUP($U9,'02 Lists'!$A$5:$B$18,2,FALSE()),1))) | AD9: =IF(OR($AB9="",$Z9="",$Z9=0),"",$AB9/(1+IF(IFERROR(INDEX('03 Suppliers'!$N$5:$N$34,MATCH($Y9,'03 Suppliers'!$B$5:$B$34,0)),"Excl VAT")="Incl VAT",'01 Control'!$C$6,0))/($Z9*IFERROR(VLOOKUP($AA9,'02 Lists'!$A$5:$B$18,2,FALSE()),1))) | AJ9: =IF(OR($AH9="",$AF9="",$AF9=0),"",$AH9/(1+IF(IFERROR(INDEX('03 Suppliers'!$N$5:$N$34,MATCH($AE9,'03 Suppliers'!$B$5:$B$34,0)),"Excl VAT")="Incl VAT",'01 Control'!$C$6,0))/($AF9*IFERROR(VLOOKUP($AG9,'02 Lists'!$A$5:$B$18,2,FALSE()),1))) | AK9: =IF(COUNT(L9,R9,X9,AD9,AJ9)=0,"",MIN(L9,R9,X9,AD9,AJ9)) | AL9: =IF($AK9="","",IF(L9=$AK9,$G9,IF(R9=$AK9,$M9,IF(X9=$AK9,$S9,IF(AD9=$AK9,$Y9,IF(AJ9=$AK9,$AE9,"")))))) | AM9: =IF($AK9="","",$AK9/IF($E9="",1,$E9)) | AN9: =COUNT(L9,R9,X9,AD9,AJ9) | AO9: =IF(COUNT(L9,R9,X9,AD9,AJ9)=0,"",MAX(L9,R9,X9,AD9,AJ9)) | AP9: =IF(OR($AK9="",$AO9="",$AO9=0),"",($AO9-$AK9)/$AO9) | AQ9: =IF($AK9="","",IF(L9=$AK9,$K9,IF(R9=$AK9,$Q9,IF(X9=$AK9,$W9,IF(AD9=$AK9,$AC9,IF(AJ9=$AK9,$AI9,"")))))) | AS9: ='02 Lists'!$A$9&"" | AT9: ='03 Suppliers'!$B$9&""
A10: PP-LUPIN-SWEET | B10: Flour / Dough | C10: SA sweet lupin flour, fermented | D10: g | E10: 1 | F10: LUPIN ALLERGEN - declare CONTAINS LUPIN; dedicated line or full deep-clean. CEILING 20% | L10: =IF(OR($J10="",$H10="",$H10=0),"",$J10/(1+IF(IFERROR(INDEX('03 Suppliers'!$N$5:$N$34,MATCH($G10,'03 Suppliers'!$B$5:$B$34,0)),"Excl VAT")="Incl VAT",'01 Control'!$C$6,0))/($H10*IFERROR(VLOOKUP($I10,'02 Lists'!$A$5:$B$18,2,FALSE()),1))) | R10: =IF(OR($P10="",$N10="",$N10=0),"",$P10/(1+IF(IFERROR(INDEX('03 Suppliers'!$N$5:$N$34,MATCH($M10,'03 Suppliers'!$B$5:$B$34,0)),"Excl VAT")="Incl VAT",'01 Control'!$C$6,0))/($N10*IFERROR(VLOOKUP($O10,'02 Lists'!$A$5:$B$18,2,FALSE()),1))) | X10: =IF(OR($V10="",$T10="",$T10=0),"",$V10/(1+IF(IFERROR(INDEX('03 Suppliers'!$N$5:$N$34,MATCH($S10,'03 Suppliers'!$B$5:$B$34,0)),"Excl VAT")="Incl VAT",'01 Control'!$C$6,0))/($T10*IFERROR(VLOOKUP($U10,'02 Lists'!$A$5:$B$18,2,FALSE()),1))) | AD10: =IF(OR($AB10="",$Z10="",$Z10=0),"",$AB10/(1+IF(IFERROR(INDEX('03 Suppliers'!$N$5:$N$34,MATCH($Y10,'03 Suppliers'!$B$5:$B$34,0)),"Excl VAT")="Incl VAT",'01 Control'!$C$6,0))/($Z10*IFERROR(VLOOKUP($AA10,'02 Lists'!$A$5:$B$18,2,FALSE()),1))) | AJ10: =IF(OR($AH10="",$AF10="",$AF10=0),"",$AH10/(1+IF(IFERROR(INDEX('03 Suppliers'!$N$5:$N$34,MATCH($AE10,'03 Suppliers'!$B$5:$B$34,0)),"Excl VAT")="Incl VAT",'01 Control'!$C$6,0))/($AF10*IFERROR(VLOOKUP($AG10,'02 Lists'!$A$5:$B$18,2,FALSE()),1))) | AK10: =IF(COUNT(L10,R10,X10,AD10,AJ10)=0,"",MIN(L10,R10,X10,AD10,AJ10)) | AL10: =IF($AK10="","",IF(L10=$AK10,$G10,IF(R10=$AK10,$M10,IF(X10=$AK10,$S10,IF(AD10=$AK10,$Y10,IF(AJ10=$AK10,$AE10,"")))))) | AM10: =IF($AK10="","",$AK10/IF($E10="",1,$E10)) | AN10: =COUNT(L10,R10,X10,AD10,AJ10) | AO10: =IF(COUNT(L10,R10,X10,AD10,AJ10)=0,"",MAX(L10,R10,X10,AD10,AJ10)) | AP10: =IF(OR($AK10="",$AO10="",$AO10=0),"",($AO10-$AK10)/$AO10) | AQ10: =IF($AK10="","",IF(L10=$AK10,$K10,IF(R10=$AK10,$Q10,IF(X10=$AK10,$W10,IF(AD10=$AK10,$AC10,IF(AJ10=$AK10,$AI10,"")))))) | AS10: ='02 Lists'!$A$10&"" | AT10: ='03 Suppliers'!$B$10&""
A11: PP-INULIN-HP | B11: Flour / Dough | C11: Inulin HP (DP >=23) | D11: g | E11: 1 | F11: Long-chain, soluble fibre >=90%; 1:1 swap with baobab. CEILING ~12% | L11: =IF(OR($J11="",$H11="",$H11=0),"",$J11/(1+IF(IFERROR(INDEX('03 Suppliers'!$N$5:$N$34,MATCH($G11,'03 Suppliers'!$B$5:$B$34,0)),"Excl VAT")="Incl VAT",'01 Control'!$C$6,0))/($H11*IFERROR(VLOOKUP($I11,'02 Lists'!$A$5:$B$18,2,FALSE()),1))) | R11: =IF(OR($P11="",$N11="",$N11=0),"",$P11/(1+IF(IFERROR(INDEX('03 Suppliers'!$N$5:$N$34,MATCH($M11,'03 Suppliers'!$B$5:$B$34,0)),"Excl VAT")="Incl VAT",'01 Control'!$C$6,0))/($N11*IFERROR(VLOOKUP($O11,'02 Lists'!$A$5:$B$18,2,FALSE()),1))) | X11: =IF(OR($V11="",$T11="",$T11=0),"",$V11/(1+IF(IFERROR(INDEX('03 Suppliers'!$N$5:$N$34,MATCH($S11,'03 Suppliers'!$B$5:$B$34,0)),"Excl VAT")="Incl VAT",'01 Control'!$C$6,0))/($T11*IFERROR(VLOOKUP($U11,'02 Lists'!$A$5:$B$18,2,FALSE()),1))) | AD11: =IF(OR($AB11="",$Z11="",$Z11=0),"",$AB11/(1+IF(IFERROR(INDEX('03 Suppliers'!$N$5:$N$34,MATCH($Y11,'03 Suppliers'!$B$5:$B$34,0)),"Excl VAT")="Incl VAT",'01 Control'!$C$6,0))/($Z11*IFERROR(VLOOKUP($AA11,'02 Lists'!$A$5:$B$18,2,FALSE()),1))) | AJ11: =IF(OR($AH11="",$AF11="",$AF11=0),"",$AH11/(1+IF(IFERROR(INDEX('03 Suppliers'!$N$5:$N$34,MATCH($AE11,'03 Suppliers'!$B$5:$B$34,0)),"Excl VAT")="Incl VAT",'01 Control'!$C$6,0))/($AF11*IFERROR(VLOOKUP($AG11,'02 Lists'!$A$5:$B$18,2,FALSE()),1))) | AK11: =IF(COUNT(L11,R11,X11,AD11,AJ11)=0,"",MIN(L11,R11,X11,AD11,AJ11)) | AL11: =IF($AK11="","",IF(L11=$AK11,$G11,IF(R11=$AK11,$M11,IF(X11=$AK11,$S11,IF(AD11=$AK11,$Y11,IF(AJ11=$AK11,$AE11,"")))))) | AM11: =IF($AK11="","",$AK11/IF($E11="",1,$E11)) | AN11: =COUNT(L11,R11,X11,AD11,AJ11) | AO11: =IF(COUNT(L11,R11,X11,AD11,AJ11)=0,"",MAX(L11,R11,X11,AD11,AJ11)) | AP11: =IF(OR($AK11="",$AO11="",$AO11=0),"",($AO11-$AK11)/$AO11) | AQ11: =IF($AK11="","",IF(L11=$AK11,$K11,IF(R11=$AK11,$Q11,IF(X11=$AK11,$W11,IF(AD11=$AK11,$AC11,IF(AJ11=$AK11,$AI11,"")))))) | AS11: ='02 Lists'!$A$11&"" | AT11: ='03 Suppliers'!$B$11&""
A12: PP-CHICKPEA-KABULI | B12: Flour / Dough | C12: Kabuli chickpea flour, roasted + fermented | D12: g | E12: 1 | F12: Roast/de-hull then ferment. CEILING 25%. Declare voluntarily (not an SA declared allergen) | L12: =IF(OR($J12="",$H12="",$H12=0),"",$J12/(1+IF(IFERROR(INDEX('03 Suppliers'!$N$5:$N$34,MATCH($G12,'03 Suppliers'!$B$5:$B$34,0)),"Excl VAT")="Incl VAT",'01 Control'!$C$6,0))/($H12*IFERROR(VLOOKUP($I12,'02 Lists'!$A$5:$B$18,2,FALSE()),1))) | R12: =IF(OR($P12="",$N12="",$N12=0),"",$P12/(1+IF(IFERROR(INDEX('03 Suppliers'!$N$5:$N$34,MATCH($M12,'03 Suppliers'!$B$5:$B$34,0)),"Excl VAT")="Incl VAT",'01 Control'!$C$6,0))/($N12*IFERROR(VLOOKUP($O12,'02 Lists'!$A$5:$B$18,2,FALSE()),1))) | X12: =IF(OR($V12="",$T12="",$T12=0),"",$V12/(1+IF(IFERROR(INDEX('03 Suppliers'!$N$5:$N$34,MATCH($S12,'03 Suppliers'!$B$5:$B$34,0)),"Excl VAT")="Incl VAT",'01 Control'!$C$6,0))/($T12*IFERROR(VLOOKUP($U12,'02 Lists'!$A$5:$B$18,2,FALSE()),1))) | AD12: =IF(OR($AB12="",$Z12="",$Z12=0),"",$AB12/(1+IF(IFERROR(INDEX('03 Suppliers'!$N$5:$N$34,MATCH($Y12,'03 Suppliers'!$B$5:$B$34,0)),"Excl VAT")="Incl VAT",'01 Control'!$C$6,0))/($Z12*IFERROR(VLOOKUP($AA12,'02 Lists'!$A$5:$B$18,2,FALSE()),1))) | AJ12: =IF(OR($AH12="",$AF12="",$AF12=0),"",$AH12/(1+IF(IFERROR(INDEX('03 Suppliers'!$N$5:$N$34,MATCH($AE12,'03 Suppliers'!$B$5:$B$34,0)),"Excl VAT")="Incl VAT",'01 Control'!$C$6,0))/($AF12*IFERROR(VLOOKUP($AG12,'02 Lists'!$A$5:$B$18,2,FALSE()),1))) | AK12: =IF(COUNT(L12,R12,X12,AD12,AJ12)=0,"",MIN(L12,R12,X12,AD12,AJ12)) | AL12: =IF($AK12="","",IF(L12=$AK12,$G12,IF(R12=$AK12,$M12,IF(X12=$AK12,$S12,IF(AD12=$AK12,$Y12,IF(AJ12=$AK12,$AE12,"")))))) | AM12: =IF($AK12="","",$AK12/IF($E12="",1,$E12)) | AN12: =COUNT(L12,R12,X12,AD12,AJ12) | AO12: =IF(COUNT(L12,R12,X12,AD12,AJ12)=0,"",MAX(L12,R12,X12,AD12,AJ12)) | AP12: =IF(OR($AK12="",$AO12="",$AO12=0),"",($AO12-$AK12)/$AO12) | AQ12: =IF($AK12="","",IF(L12=$AK12,$K12,IF(R12=$AK12,$Q12,IF(X12=$AK12,$W12,IF(AD12=$AK12,$AC12,IF(AJ12=$AK12,$AI12,"")))))) | AS12: ='02 Lists'!$A$12&"" | AT12: ='03 Suppliers'!$B$12&""
A13: PP-MUSHROOM-LIGHT | B13: Flour / Dough | C13: Light mushroom powder (umami layer) | D13: g | E13: 1 | F13: Light-coloured; savoury depth | L13: =IF(OR($J13="",$H13="",$H13=0),"",$J13/(1+IF(IFERROR(INDEX('03 Suppliers'!$N$5:$N$34,MATCH($G13,'03 Suppliers'!$B$5:$B$34,0)),"Excl VAT")="Incl VAT",'01 Control'!$C$6,0))/($H13*IFERROR(VLOOKUP($I13,'02 Lists'!$A$5:$B$18,2,FALSE()),1))) | R13: =IF(OR($P13="",$N13="",$N13=0),"",$P13/(1+IF(IFERROR(INDEX('03 Suppliers'!$N$5:$N$34,MATCH($M13,'03 Suppliers'!$B$5:$B$34,0)),"Excl VAT")="Incl VAT",'01 Control'!$C$6,0))/($N13*IFERROR(VLOOKUP($O13,'02 Lists'!$A$5:$B$18,2,FALSE()),1))) | X13: =IF(OR($V13="",$T13="",$T13=0),"",$V13/(1+IF(IFERROR(INDEX('03 Suppliers'!$N$5:$N$34,MATCH($S13,'03 Suppliers'!$B$5:$B$34,0)),"Excl VAT")="Incl VAT",'01 Control'!$C$6,0))/($T13*IFERROR(VLOOKUP($U13,'02 Lists'!$A$5:$B$18,2,FALSE()),1))) | AD13: =IF(OR($AB13="",$Z13="",$Z13=0),"",$AB13/(1+IF(IFERROR(INDEX('03 Suppliers'!$N$5:$N$34,MATCH($Y13,'03 Suppliers'!$B$5:$B$34,0)),"Excl VAT")="Incl VAT",'01 Control'!$C$6,0))/($Z13*IFERROR(VLOOKUP($AA13,'02 Lists'!$A$5:$B$18,2,FALSE()),1))) | AJ13: =IF(OR($AH13="",$AF13="",$AF13=0),"",$AH13/(1+IF(IFERROR(INDEX('03 Suppliers'!$N$5:$N$34,MATCH($AE13,'03 Suppliers'!$B$5:$B$34,0)),"Excl VAT")="Incl VAT",'01 Control'!$C$6,0))/($AF13*IFERROR(VLOOKUP($AG13,'02 Lists'!$A$5:$B$18,2,FALSE()),1))) | AK13: =IF(COUNT(L13,R13,X13,AD13,AJ13)=0,"",MIN(L13,R13,X13,AD13,AJ13)) | AL13: =IF($AK13="","",IF(L13=$AK13,$G13,IF(R13=$AK13,$M13,IF(X13=$AK13,$S13,IF(AD13=$AK13,$Y13,IF(AJ13=$AK13,$AE13,"")))))) | AM13: =IF($AK13="","",$AK13/IF($E13="",1,$E13)) | AN13: =COUNT(L13,R13,X13,AD13,AJ13) | AO13: =IF(COUNT(L13,R13,X13,AD13,AJ13)=0,"",MAX(L13,R13,X13,AD13,AJ13)) | AP13: =IF(OR($AK13="",$AO13="",$AO13=0),"",($AO13-$AK13)/$AO13) | AQ13: =IF($AK13="","",IF(L13=$AK13,$K13,IF(R13=$AK13,$Q13,IF(X13=$AK13,$W13,IF(AD13=$AK13,$AC13,IF(AJ13=$AK13,$AI13,"")))))) | AS13: ='02 Lists'!$A$13&"" | AT13: ='03 Suppliers'!$B$13&""
A14: PP-OYSTER-POWDER | B14: Flour / Dough | C14: Oyster mushroom powder (The Local Farmer) | D14: g | E14: 1 | F14: Freeze-dried preferred; fine mill <=200 um | L14: =IF(OR($J14="",$H14="",$H14=0),"",$J14/(1+IF(IFERROR(INDEX('03 Suppliers'!$N$5:$N$34,MATCH($G14,'03 Suppliers'!$B$5:$B$34,0)),"Excl VAT")="Incl VAT",'01 Control'!$C$6,0))/($H14*IFERROR(VLOOKUP($I14,'02 Lists'!$A$5:$B$18,2,FALSE()),1))) | R14: =IF(OR($P14="",$N14="",$N14=0),"",$P14/(1+IF(IFERROR(INDEX('03 Suppliers'!$N$5:$N$34,MATCH($M14,'03 Suppliers'!$B$5:$B$34,0)),"Excl VAT")="Incl VAT",'01 Control'!$C$6,0))/($N14*IFERROR(VLOOKUP($O14,'02 Lists'!$A$5:$B$18,2,FALSE()),1))) | X14: =IF(OR($V14="",$T14="",$T14=0),"",$V14/(1+IF(IFERROR(INDEX('03 Suppliers'!$N$5:$N$34,MATCH($S14,'03 Suppliers'!$B$5:$B$34,0)),"Excl VAT")="Incl VAT",'01 Control'!$C$6,0))/($T14*IFERROR(VLOOKUP($U14,'02 Lists'!$A$5:$B$18,2,FALSE()),1))) | AD14: =IF(OR($AB14="",$Z14="",$Z14=0),"",$AB14/(1+IF(IFERROR(INDEX('03 Suppliers'!$N$5:$N$34,MATCH($Y14,'03 Suppliers'!$B$5:$B$34,0)),"Excl VAT")="Incl VAT",'01 Control'!$C$6,0))/($Z14*IFERROR(VLOOKUP($AA14,'02 Lists'!$A$5:$B$18,2,FALSE()),1))) | AJ14: =IF(OR($AH14="",$AF14="",$AF14=0),"",$AH14/(1+IF(IFERROR(INDEX('03 Suppliers'!$N$5:$N$34,MATCH($AE14,'03 Suppliers'!$B$5:$B$34,0)),"Excl VAT")="Incl VAT",'01 Control'!$C$6,0))/($AF14*IFERROR(VLOOKUP($AG14,'02 Lists'!$A$5:$B$18,2,FALSE()),1))) | AK14: =IF(COUNT(L14,R14,X14,AD14,AJ14)=0,"",MIN(L14,R14,X14,AD14,AJ14)) | AL14: =IF($AK14="","",IF(L14=$AK14,$G14,IF(R14=$AK14,$M14,IF(X14=$AK14,$S14,IF(AD14=$AK14,$Y14,IF(AJ14=$AK14,$AE14,"")))))) | AM14: =IF($AK14="","",$AK14/IF($E14="",1,$E14)) | AN14: =COUNT(L14,R14,X14,AD14,AJ14) | AO14: =IF(COUNT(L14,R14,X14,AD14,AJ14)=0,"",MAX(L14,R14,X14,AD14,AJ14)) | AP14: =IF(OR($AK14="",$AO14="",$AO14=0),"",($AO14-$AK14)/$AO14) | AQ14: =IF($AK14="","",IF(L14=$AK14,$K14,IF(R14=$AK14,$Q14,IF(X14=$AK14,$W14,IF(AD14=$AK14,$AC14,IF(AJ14=$AK14,$AI14,"")))))) | AS14: ='02 Lists'!$A$14&"" | AT14: ='03 Suppliers'!$B$14&""
A15: PP-LIONSMANE-POWDER | B15: Flour / Dough | C15: Lion's mane powder (The Local Farmer) | D15: g | E15: 1 | F15: CEILING 5% - sensory limit | L15: =IF(OR($J15="",$H15="",$H15=0),"",$J15/(1+IF(IFERROR(INDEX('03 Suppliers'!$N$5:$N$34,MATCH($G15,'03 Suppliers'!$B$5:$B$34,0)),"Excl VAT")="Incl VAT",'01 Control'!$C$6,0))/($H15*IFERROR(VLOOKUP($I15,'02 Lists'!$A$5:$B$18,2,FALSE()),1))) | R15: =IF(OR($P15="",$N15="",$N15=0),"",$P15/(1+IF(IFERROR(INDEX('03 Suppliers'!$N$5:$N$34,MATCH($M15,'03 Suppliers'!$B$5:$B$34,0)),"Excl VAT")="Incl VAT",'01 Control'!$C$6,0))/($N15*IFERROR(VLOOKUP($O15,'02 Lists'!$A$5:$B$18,2,FALSE()),1))) | X15: =IF(OR($V15="",$T15="",$T15=0),"",$V15/(1+IF(IFERROR(INDEX('03 Suppliers'!$N$5:$N$34,MATCH($S15,'03 Suppliers'!$B$5:$B$34,0)),"Excl VAT")="Incl VAT",'01 Control'!$C$6,0))/($T15*IFERROR(VLOOKUP($U15,'02 Lists'!$A$5:$B$18,2,FALSE()),1))) | AD15: =IF(OR($AB15="",$Z15="",$Z15=0),"",$AB15/(1+IF(IFERROR(INDEX('03 Suppliers'!$N$5:$N$34,MATCH($Y15,'03 Suppliers'!$B$5:$B$34,0)),"Excl VAT")="Incl VAT",'01 Control'!$C$6,0))/($Z15*IFERROR(VLOOKUP($AA15,'02 Lists'!$A$5:$B$18,2,FALSE()),1))) | AJ15: =IF(OR($AH15="",$AF15="",$AF15=0),"",$AH15/(1+IF(IFERROR(INDEX('03 Suppliers'!$N$5:$N$34,MATCH($AE15,'03 Suppliers'!$B$5:$B$34,0)),"Excl VAT")="Incl VAT",'01 Control'!$C$6,0))/($AF15*IFERROR(VLOOKUP($AG15,'02 Lists'!$A$5:$B$18,2,FALSE()),1))) | AK15: =IF(COUNT(L15,R15,X15,AD15,AJ15)=0,"",MIN(L15,R15,X15,AD15,AJ15)) | AL15: =IF($AK15="","",IF(L15=$AK15,$G15,IF(R15=$AK15,$M15,IF(X15=$AK15,$S15,IF(AD15=$AK15,$Y15,IF(AJ15=$AK15,$AE15,"")))))) | AM15: =IF($AK15="","",$AK15/IF($E15="",1,$E15)) | AN15: =COUNT(L15,R15,X15,AD15,AJ15) | AO15: =IF(COUNT(L15,R15,X15,AD15,AJ15)=0,"",MAX(L15,R15,X15,AD15,AJ15)) | AP15: =IF(OR($AK15="",$AO15="",$AO15=0),"",($AO15-$AK15)/$AO15) | AQ15: =IF($AK15="","",IF(L15=$AK15,$K15,IF(R15=$AK15,$Q15,IF(X15=$AK15,$W15,IF(AD15=$AK15,$AC15,IF(AJ15=$AK15,$AI15,"")))))) | AS15: ='02 Lists'!$A$15&"" | AT15: ='03 Suppliers'!$B$15&""
A16: PP-MICROGREEN-POWDER | B16: Flour / Dough | C16: Microgreen powder (The Local Farmer) | D16: g | E16: 1 | F16: CEILING 3%; freeze-dry preferred for colour | L16: =IF(OR($J16="",$H16="",$H16=0),"",$J16/(1+IF(IFERROR(INDEX('03 Suppliers'!$N$5:$N$34,MATCH($G16,'03 Suppliers'!$B$5:$B$34,0)),"Excl VAT")="Incl VAT",'01 Control'!$C$6,0))/($H16*IFERROR(VLOOKUP($I16,'02 Lists'!$A$5:$B$18,2,FALSE()),1))) | R16: =IF(OR($P16="",$N16="",$N16=0),"",$P16/(1+IF(IFERROR(INDEX('03 Suppliers'!$N$5:$N$34,MATCH($M16,'03 Suppliers'!$B$5:$B$34,0)),"Excl VAT")="Incl VAT",'01 Control'!$C$6,0))/($N16*IFERROR(VLOOKUP($O16,'02 Lists'!$A$5:$B$18,2,FALSE()),1))) | X16: =IF(OR($V16="",$T16="",$T16=0),"",$V16/(1+IF(IFERROR(INDEX('03 Suppliers'!$N$5:$N$34,MATCH($S16,'03 Suppliers'!$B$5:$B$34,0)),"Excl VAT")="Incl VAT",'01 Control'!$C$6,0))/($T16*IFERROR(VLOOKUP($U16,'02 Lists'!$A$5:$B$18,2,FALSE()),1))) | AD16: =IF(OR($AB16="",$Z16="",$Z16=0),"",$AB16/(1+IF(IFERROR(INDEX('03 Suppliers'!$N$5:$N$34,MATCH($Y16,'03 Suppliers'!$B$5:$B$34,0)),"Excl VAT")="Incl VAT",'01 Control'!$C$6,0))/($Z16*IFERROR(VLOOKUP($AA16,'02 Lists'!$A$5:$B$18,2,FALSE()),1))) | AJ16: =IF(OR($AH16="",$AF16="",$AF16=0),"",$AH16/(1+IF(IFERROR(INDEX('03 Suppliers'!$N$5:$N$34,MATCH($AE16,'03 Suppliers'!$B$5:$B$34,0)),"Excl VAT")="Incl VAT",'01 Control'!$C$6,0))/($AF16*IFERROR(VLOOKUP($AG16,'02 Lists'!$A$5:$B$18,2,FALSE()),1))) | AK16: =IF(COUNT(L16,R16,X16,AD16,AJ16)=0,"",MIN(L16,R16,X16,AD16,AJ16)) | AL16: =IF($AK16="","",IF(L16=$AK16,$G16,IF(R16=$AK16,$M16,IF(X16=$AK16,$S16,IF(AD16=$AK16,$Y16,IF(AJ16=$AK16,$AE16,"")))))) | AM16: =IF($AK16="","",$AK16/IF($E16="",1,$E16)) | AN16: =COUNT(L16,R16,X16,AD16,AJ16) | AO16: =IF(COUNT(L16,R16,X16,AD16,AJ16)=0,"",MAX(L16,R16,X16,AD16,AJ16)) | AP16: =IF(OR($AK16="",$AO16="",$AO16=0),"",($AO16-$AK16)/$AO16) | AQ16: =IF($AK16="","",IF(L16=$AK16,$K16,IF(R16=$AK16,$Q16,IF(X16=$AK16,$W16,IF(AD16=$AK16,$AC16,IF(AJ16=$AK16,$AI16,"")))))) | AS16: ='02 Lists'!$A$16&"" | AT16: ='03 Suppliers'!$B$16&""
A17: PP-WATER-PURIFIED | B17: Utilities | C17: Purified water (38-40 C) | D17: ml | E17: 1 | F17: Fresh-daily hydration water | L17: =IF(OR($J17="",$H17="",$H17=0),"",$J17/(1+IF(IFERROR(INDEX('03 Suppliers'!$N$5:$N$34,MATCH($G17,'03 Suppliers'!$B$5:$B$34,0)),"Excl VAT")="Incl VAT",'01 Control'!$C$6,0))/($H17*IFERROR(VLOOKUP($I17,'02 Lists'!$A$5:$B$18,2,FALSE()),1))) | R17: =IF(OR($P17="",$N17="",$N17=0),"",$P17/(1+IF(IFERROR(INDEX('03 Suppliers'!$N$5:$N$34,MATCH($M17,'03 Suppliers'!$B$5:$B$34,0)),"Excl VAT")="Incl VAT",'01 Control'!$C$6,0))/($N17*IFERROR(VLOOKUP($O17,'02 Lists'!$A$5:$B$18,2,FALSE()),1))) | X17: =IF(OR($V17="",$T17="",$T17=0),"",$V17/(1+IF(IFERROR(INDEX('03 Suppliers'!$N$5:$N$34,MATCH($S17,'03 Suppliers'!$B$5:$B$34,0)),"Excl VAT")="Incl VAT",'01 Control'!$C$6,0))/($T17*IFERROR(VLOOKUP($U17,'02 Lists'!$A$5:$B$18,2,FALSE()),1))) | AD17: =IF(OR($AB17="",$Z17="",$Z17=0),"",$AB17/(1+IF(IFERROR(INDEX('03 Suppliers'!$N$5:$N$34,MATCH($Y17,'03 Suppliers'!$B$5:$B$34,0)),"Excl VAT")="Incl VAT",'01 Control'!$C$6,0))/($Z17*IFERROR(VLOOKUP($AA17,'02 Lists'!$A$5:$B$18,2,FALSE()),1))) | AJ17: =IF(OR($AH17="",$AF17="",$AF17=0),"",$AH17/(1+IF(IFERROR(INDEX('03 Suppliers'!$N$5:$N$34,MATCH($AE17,'03 Suppliers'!$B$5:$B$34,0)),"Excl VAT")="Incl VAT",'01 Control'!$C$6,0))/($AF17*IFERROR(VLOOKUP($AG17,'02 Lists'!$A$5:$B$18,2,FALSE()),1))) | AK17: =IF(COUNT(L17,R17,X17,AD17,AJ17)=0,"",MIN(L17,R17,X17,AD17,AJ17)) | AL17: =IF($AK17="","",IF(L17=$AK17,$G17,IF(R17=$AK17,$M17,IF(X17=$AK17,$S17,IF(AD17=$AK17,$Y17,IF(AJ17=$AK17,$AE17,"")))))) | AM17: =IF($AK17="","",$AK17/IF($E17="",1,$E17)) | AN17: =COUNT(L17,R17,X17,AD17,AJ17) | AO17: =IF(COUNT(L17,R17,X17,AD17,AJ17)=0,"",MAX(L17,R17,X17,AD17,AJ17)) | AP17: =IF(OR($AK17="",$AO17="",$AO17=0),"",($AO17-$AK17)/$AO17) | AQ17: =IF($AK17="","",IF(L17=$AK17,$K17,IF(R17=$AK17,$Q17,IF(X17=$AK17,$W17,IF(AD17=$AK17,$AC17,IF(AJ17=$AK17,$AI17,"")))))) | AS17: ='02 Lists'!$A$17&"" | AT17: ='03 Suppliers'!$B$17&""
A18: PP-SALT | B18: Dry Goods | C18: Salt | D18: g | E18: 1 | F18: Optional/recommended at 1-1.5% of dry weight | L18: =IF(OR($J18="",$H18="",$H18=0),"",$J18/(1+IF(IFERROR(INDEX('03 Suppliers'!$N$5:$N$34,MATCH($G18,'03 Suppliers'!$B$5:$B$34,0)),"Excl VAT")="Incl VAT",'01 Control'!$C$6,0))/($H18*IFERROR(VLOOKUP($I18,'02 Lists'!$A$5:$B$18,2,FALSE()),1))) | R18: =IF(OR($P18="",$N18="",$N18=0),"",$P18/(1+IF(IFERROR(INDEX('03 Suppliers'!$N$5:$N$34,MATCH($M18,'03 Suppliers'!$B$5:$B$34,0)),"Excl VAT")="Incl VAT",'01 Control'!$C$6,0))/($N18*IFERROR(VLOOKUP($O18,'02 Lists'!$A$5:$B$18,2,FALSE()),1))) | X18: =IF(OR($V18="",$T18="",$T18=0),"",$V18/(1+IF(IFERROR(INDEX('03 Suppliers'!$N$5:$N$34,MATCH($S18,'03 Suppliers'!$B$5:$B$34,0)),"Excl VAT")="Incl VAT",'01 Control'!$C$6,0))/($T18*IFERROR(VLOOKUP($U18,'02 Lists'!$A$5:$B$18,2,FALSE()),1))) | AD18: =IF(OR($AB18="",$Z18="",$Z18=0),"",$AB18/(1+IF(IFERROR(INDEX('03 Suppliers'!$N$5:$N$34,MATCH($Y18,'03 Suppliers'!$B$5:$B$34,0)),"Excl VAT")="Incl VAT",'01 Control'!$C$6,0))/($Z18*IFERROR(VLOOKUP($AA18,'02 Lists'!$A$5:$B$18,2,FALSE()),1))) | AJ18: =IF(OR($AH18="",$AF18="",$AF18=0),"",$AH18/(1+IF(IFERROR(INDEX('03 Suppliers'!$N$5:$N$34,MATCH($AE18,'03 Suppliers'!$B$5:$B$34,0)),"Excl VAT")="Incl VAT",'01 Control'!$C$6,0))/($AF18*IFERROR(VLOOKUP($AG18,'02 Lists'!$A$5:$B$18,2,FALSE()),1))) | AK18: =IF(COUNT(L18,R18,X18,AD18,AJ18)=0,"",MIN(L18,R18,X18,AD18,AJ18)) | AL18: =IF($AK18="","",IF(L18=$AK18,$G18,IF(R18=$AK18,$M18,IF(X18=$AK18,$S18,IF(AD18=$AK18,$Y18,IF(AJ18=$AK18,$AE18,"")))))) | AM18: =IF($AK18="","",$AK18/IF($E18="",1,$E18)) | AN18: =COUNT(L18,R18,X18,AD18,AJ18) | AO18: =IF(COUNT(L18,R18,X18,AD18,AJ18)=0,"",MAX(L18,R18,X18,AD18,AJ18)) | AP18: =IF(OR($AK18="",$AO18="",$AO18=0),"",($AO18-$AK18)/$AO18) | AQ18: =IF($AK18="","",IF(L18=$AK18,$K18,IF(R18=$AK18,$Q18,IF(X18=$AK18,$W18,IF(AD18=$AK18,$AC18,IF(AJ18=$AK18,$AI18,"")))))) | AS18: ='02 Lists'!$A$18&"" | AT18: ='03 Suppliers'!$B$18&""
A19: PP-EVOO | B19: Oil / Fat | C19: Extra-virgin olive oil | D19: ml | E19: 1 | F19: Mouthfeel / aroma carrier; also a finishing item | L19: =IF(OR($J19="",$H19="",$H19=0),"",$J19/(1+IF(IFERROR(INDEX('03 Suppliers'!$N$5:$N$34,MATCH($G19,'03 Suppliers'!$B$5:$B$34,0)),"Excl VAT")="Incl VAT",'01 Control'!$C$6,0))/($H19*IFERROR(VLOOKUP($I19,'02 Lists'!$A$5:$B$18,2,FALSE()),1))) | R19: =IF(OR($P19="",$N19="",$N19=0),"",$P19/(1+IF(IFERROR(INDEX('03 Suppliers'!$N$5:$N$34,MATCH($M19,'03 Suppliers'!$B$5:$B$34,0)),"Excl VAT")="Incl VAT",'01 Control'!$C$6,0))/($N19*IFERROR(VLOOKUP($O19,'02 Lists'!$A$5:$B$18,2,FALSE()),1))) | X19: =IF(OR($V19="",$T19="",$T19=0),"",$V19/(1+IF(IFERROR(INDEX('03 Suppliers'!$N$5:$N$34,MATCH($S19,'03 Suppliers'!$B$5:$B$34,0)),"Excl VAT")="Incl VAT",'01 Control'!$C$6,0))/($T19*IFERROR(VLOOKUP($U19,'02 Lists'!$A$5:$B$18,2,FALSE()),1))) | AD19: =IF(OR($AB19="",$Z19="",$Z19=0),"",$AB19/(1+IF(IFERROR(INDEX('03 Suppliers'!$N$5:$N$34,MATCH($Y19,'03 Suppliers'!$B$5:$B$34,0)),"Excl VAT")="Incl VAT",'01 Control'!$C$6,0))/($Z19*IFERROR(VLOOKUP($AA19,'02 Lists'!$A$5:$B$18,2,FALSE()),1))) | AJ19: =IF(OR($AH19="",$AF19="",$AF19=0),"",$AH19/(1+IF(IFERROR(INDEX('03 Suppliers'!$N$5:$N$34,MATCH($AE19,'03 Suppliers'!$B$5:$B$34,0)),"Excl VAT")="Incl VAT",'01 Control'!$C$6,0))/($AF19*IFERROR(VLOOKUP($AG19,'02 Lists'!$A$5:$B$18,2,FALSE()),1))) | AK19: =IF(COUNT(L19,R19,X19,AD19,AJ19)=0,"",MIN(L19,R19,X19,AD19,AJ19)) | AL19: =IF($AK19="","",IF(L19=$AK19,$G19,IF(R19=$AK19,$M19,IF(X19=$AK19,$S19,IF(AD19=$AK19,$Y19,IF(AJ19=$AK19,$AE19,"")))))) | AM19: =IF($AK19="","",$AK19/IF($E19="",1,$E19)) | AN19: =COUNT(L19,R19,X19,AD19,AJ19) | AO19: =IF(COUNT(L19,R19,X19,AD19,AJ19)=0,"",MAX(L19,R19,X19,AD19,AJ19)) | AP19: =IF(OR($AK19="",$AO19="",$AO19=0),"",($AO19-$AK19)/$AO19) | AQ19: =IF($AK19="","",IF(L19=$AK19,$K19,IF(R19=$AK19,$Q19,IF(X19=$AK19,$W19,IF(AD19=$AK19,$AC19,IF(AJ19=$AK19,$AI19,"")))))) | AS19: ='02 Lists'!$A$19&"" | AT19: ='03 Suppliers'!$B$19&""
A20: PP-OIL | B20: Oil / Fat | C20: Cooking oil (sunflower / canola) | D20: ml | E20: 1 | F20: Commissary soffritto base | L20: =IF(OR($J20="",$H20="",$H20=0),"",$J20/(1+IF(IFERROR(INDEX('03 Suppliers'!$N$5:$N$34,MATCH($G20,'03 Suppliers'!$B$5:$B$34,0)),"Excl VAT")="Incl VAT",'01 Control'!$C$6,0))/($H20*IFERROR(VLOOKUP($I20,'02 Lists'!$A$5:$B$18,2,FALSE()),1))) | R20: =IF(OR($P20="",$N20="",$N20=0),"",$P20/(1+IF(IFERROR(INDEX('03 Suppliers'!$N$5:$N$34,MATCH($M20,'03 Suppliers'!$B$5:$B$34,0)),"Excl VAT")="Incl VAT",'01 Control'!$C$6,0))/($N20*IFERROR(VLOOKUP($O20,'02 Lists'!$A$5:$B$18,2,FALSE()),1))) | X20: =IF(OR($V20="",$T20="",$T20=0),"",$V20/(1+IF(IFERROR(INDEX('03 Suppliers'!$N$5:$N$34,MATCH($S20,'03 Suppliers'!$B$5:$B$34,0)),"Excl VAT")="Incl VAT",'01 Control'!$C$6,0))/($T20*IFERROR(VLOOKUP($U20,'02 Lists'!$A$5:$B$18,2,FALSE()),1))) | AD20: =IF(OR($AB20="",$Z20="",$Z20=0),"",$AB20/(1+IF(IFERROR(INDEX('03 Suppliers'!$N$5:$N$34,MATCH($Y20,'03 Suppliers'!$B$5:$B$34,0)),"Excl VAT")="Incl VAT",'01 Control'!$C$6,0))/($Z20*IFERROR(VLOOKUP($AA20,'02 Lists'!$A$5:$B$18,2,FALSE()),1))) | AJ20: =IF(OR($AH20="",$AF20="",$AF20=0),"",$AH20/(1+IF(IFERROR(INDEX('03 Suppliers'!$N$5:$N$34,MATCH($AE20,'03 Suppliers'!$B$5:$B$34,0)),"Excl VAT")="Incl VAT",'01 Control'!$C$6,0))/($AF20*IFERROR(VLOOKUP($AG20,'02 Lists'!$A$5:$B$18,2,FALSE()),1))) | AK20: =IF(COUNT(L20,R20,X20,AD20,AJ20)=0,"",MIN(L20,R20,X20,AD20,AJ20)) | AL20: =IF($AK20="","",IF(L20=$AK20,$G20,IF(R20=$AK20,$M20,IF(X20=$AK20,$S20,IF(AD20=$AK20,$Y20,IF(AJ20=$AK20,$AE20,"")))))) | AM20: =IF($AK20="","",$AK20/IF($E20="",1,$E20)) | AN20: =COUNT(L20,R20,X20,AD20,AJ20) | AO20: =IF(COUNT(L20,R20,X20,AD20,AJ20)=0,"",MAX(L20,R20,X20,AD20,AJ20)) | AP20: =IF(OR($AK20="",$AO20="",$AO20=0),"",($AO20-$AK20)/$AO20) | AQ20: =IF($AK20="","",IF(L20=$AK20,$K20,IF(R20=$AK20,$Q20,IF(X20=$AK20,$W20,IF(AD20=$AK20,$AC20,IF(AJ20=$AK20,$AI20,"")))))) | AS20: ='02 Lists'!$A$20&"" | AT20: ='03 Suppliers'!$B$20&""
A21: PP-BUTTER | B21: Dairy | C21: Butter, salted | D21: g | E21: 1 | F21: Cream sauce bases | L21: =IF(OR($J21="",$H21="",$H21=0),"",$J21/(1+IF(IFERROR(INDEX('03 Suppliers'!$N$5:$N$34,MATCH($G21,'03 Suppliers'!$B$5:$B$34,0)),"Excl VAT")="Incl VAT",'01 Control'!$C$6,0))/($H21*IFERROR(VLOOKUP($I21,'02 Lists'!$A$5:$B$18,2,FALSE()),1))) | R21: =IF(OR($P21="",$N21="",$N21=0),"",$P21/(1+IF(IFERROR(INDEX('03 Suppliers'!$N$5:$N$34,MATCH($M21,'03 Suppliers'!$B$5:$B$34,0)),"Excl VAT")="Incl VAT",'01 Control'!$C$6,0))/($N21*IFERROR(VLOOKUP($O21,'02 Lists'!$A$5:$B$18,2,FALSE()),1))) | X21: =IF(OR($V21="",$T21="",$T21=0),"",$V21/(1+IF(IFERROR(INDEX('03 Suppliers'!$N$5:$N$34,MATCH($S21,'03 Suppliers'!$B$5:$B$34,0)),"Excl VAT")="Incl VAT",'01 Control'!$C$6,0))/($T21*IFERROR(VLOOKUP($U21,'02 Lists'!$A$5:$B$18,2,FALSE()),1))) | AD21: =IF(OR($AB21="",$Z21="",$Z21=0),"",$AB21/(1+IF(IFERROR(INDEX('03 Suppliers'!$N$5:$N$34,MATCH($Y21,'03 Suppliers'!$B$5:$B$34,0)),"Excl VAT")="Incl VAT",'01 Control'!$C$6,0))/($Z21*IFERROR(VLOOKUP($AA21,'02 Lists'!$A$5:$B$18,2,FALSE()),1))) | AJ21: =IF(OR($AH21="",$AF21="",$AF21=0),"",$AH21/(1+IF(IFERROR(INDEX('03 Suppliers'!$N$5:$N$34,MATCH($AE21,'03 Suppliers'!$B$5:$B$34,0)),"Excl VAT")="Incl VAT",'01 Control'!$C$6,0))/($AF21*IFERROR(VLOOKUP($AG21,'02 Lists'!$A$5:$B$18,2,FALSE()),1))) | AK21: =IF(COUNT(L21,R21,X21,AD21,AJ21)=0,"",MIN(L21,R21,X21,AD21,AJ21)) | AL21: =IF($AK21="","",IF(L21=$AK21,$G21,IF(R21=$AK21,$M21,IF(X21=$AK21,$S21,IF(AD21=$AK21,$Y21,IF(AJ21=$AK21,$AE21,"")))))) | AM21: =IF($AK21="","",$AK21/IF($E21="",1,$E21)) | AN21: =COUNT(L21,R21,X21,AD21,AJ21) | AO21: =IF(COUNT(L21,R21,X21,AD21,AJ21)=0,"",MAX(L21,R21,X21,AD21,AJ21)) | AP21: =IF(OR($AK21="",$AO21="",$AO21=0),"",($AO21-$AK21)/$AO21) | AQ21: =IF($AK21="","",IF(L21=$AK21,$K21,IF(R21=$AK21,$Q21,IF(X21=$AK21,$W21,IF(AD21=$AK21,$AC21,IF(AJ21=$AK21,$AI21,"")))))) | AS21: ='02 Lists'!$A$21&"" | AT21: ='03 Suppliers'!$B$21&""
A22: PP-CHILLI-OIL | B22: Oil / Fat | C22: Chilli oil (finishing, dial-a-heat) | D22: ml | E22: 1 | F22: Store finishing item - Mild/Medium/Hot | L22: =IF(OR($J22="",$H22="",$H22=0),"",$J22/(1+IF(IFERROR(INDEX('03 Suppliers'!$N$5:$N$34,MATCH($G22,'03 Suppliers'!$B$5:$B$34,0)),"Excl VAT")="Incl VAT",'01 Control'!$C$6,0))/($H22*IFERROR(VLOOKUP($I22,'02 Lists'!$A$5:$B$18,2,FALSE()),1))) | R22: =IF(OR($P22="",$N22="",$N22=0),"",$P22/(1+IF(IFERROR(INDEX('03 Suppliers'!$N$5:$N$34,MATCH($M22,'03 Suppliers'!$B$5:$B$34,0)),"Excl VAT")="Incl VAT",'01 Control'!$C$6,0))/($N22*IFERROR(VLOOKUP($O22,'02 Lists'!$A$5:$B$18,2,FALSE()),1))) | X22: =IF(OR($V22="",$T22="",$T22=0),"",$V22/(1+IF(IFERROR(INDEX('03 Suppliers'!$N$5:$N$34,MATCH($S22,'03 Suppliers'!$B$5:$B$34,0)),"Excl VAT")="Incl VAT",'01 Control'!$C$6,0))/($T22*IFERROR(VLOOKUP($U22,'02 Lists'!$A$5:$B$18,2,FALSE()),1))) | AD22: =IF(OR($AB22="",$Z22="",$Z22=0),"",$AB22/(1+IF(IFERROR(INDEX('03 Suppliers'!$N$5:$N$34,MATCH($Y22,'03 Suppliers'!$B$5:$B$34,0)),"Excl VAT")="Incl VAT",'01 Control'!$C$6,0))/($Z22*IFERROR(VLOOKUP($AA22,'02 Lists'!$A$5:$B$18,2,FALSE()),1))) | AJ22: =IF(OR($AH22="",$AF22="",$AF22=0),"",$AH22/(1+IF(IFERROR(INDEX('03 Suppliers'!$N$5:$N$34,MATCH($AE22,'03 Suppliers'!$B$5:$B$34,0)),"Excl VAT")="Incl VAT",'01 Control'!$C$6,0))/($AF22*IFERROR(VLOOKUP($AG22,'02 Lists'!$A$5:$B$18,2,FALSE()),1))) | AK22: =IF(COUNT(L22,R22,X22,AD22,AJ22)=0,"",MIN(L22,R22,X22,AD22,AJ22)) | AL22: =IF($AK22="","",IF(L22=$AK22,$G22,IF(R22=$AK22,$M22,IF(X22=$AK22,$S22,IF(AD22=$AK22,$Y22,IF(AJ22=$AK22,$AE22,"")))))) | AM22: =IF($AK22="","",$AK22/IF($E22="",1,$E22)) | AN22: =COUNT(L22,R22,X22,AD22,AJ22) | AO22: =IF(COUNT(L22,R22,X22,AD22,AJ22)=0,"",MAX(L22,R22,X22,AD22,AJ22)) | AP22: =IF(OR($AK22="",$AO22="",$AO22=0),"",($AO22-$AK22)/$AO22) | AQ22: =IF($AK22="","",IF(L22=$AK22,$K22,IF(R22=$AK22,$Q22,IF(X22=$AK22,$W22,IF(AD22=$AK22,$AC22,IF(AJ22=$AK22,$AI22,"")))))) | AT22: ='03 Suppliers'!$B$22&""
A23: PP-TOM-PLUM | B23: Tomato | C23: San Marzano-style plum tomatoes, tinned | D23: g | E23: 1 | F23: Napoletana / Bolognese / Arrabbiata base | L23: =IF(OR($J23="",$H23="",$H23=0),"",$J23/(1+IF(IFERROR(INDEX('03 Suppliers'!$N$5:$N$34,MATCH($G23,'03 Suppliers'!$B$5:$B$34,0)),"Excl VAT")="Incl VAT",'01 Control'!$C$6,0))/($H23*IFERROR(VLOOKUP($I23,'02 Lists'!$A$5:$B$18,2,FALSE()),1))) | R23: =IF(OR($P23="",$N23="",$N23=0),"",$P23/(1+IF(IFERROR(INDEX('03 Suppliers'!$N$5:$N$34,MATCH($M23,'03 Suppliers'!$B$5:$B$34,0)),"Excl VAT")="Incl VAT",'01 Control'!$C$6,0))/($N23*IFERROR(VLOOKUP($O23,'02 Lists'!$A$5:$B$18,2,FALSE()),1))) | X23: =IF(OR($V23="",$T23="",$T23=0),"",$V23/(1+IF(IFERROR(INDEX('03 Suppliers'!$N$5:$N$34,MATCH($S23,'03 Suppliers'!$B$5:$B$34,0)),"Excl VAT")="Incl VAT",'01 Control'!$C$6,0))/($T23*IFERROR(VLOOKUP($U23,'02 Lists'!$A$5:$B$18,2,FALSE()),1))) | AD23: =IF(OR($AB23="",$Z23="",$Z23=0),"",$AB23/(1+IF(IFERROR(INDEX('03 Suppliers'!$N$5:$N$34,MATCH($Y23,'03 Suppliers'!$B$5:$B$34,0)),"Excl VAT")="Incl VAT",'01 Control'!$C$6,0))/($Z23*IFERROR(VLOOKUP($AA23,'02 Lists'!$A$5:$B$18,2,FALSE()),1))) | AJ23: =IF(OR($AH23="",$AF23="",$AF23=0),"",$AH23/(1+IF(IFERROR(INDEX('03 Suppliers'!$N$5:$N$34,MATCH($AE23,'03 Suppliers'!$B$5:$B$34,0)),"Excl VAT")="Incl VAT",'01 Control'!$C$6,0))/($AF23*IFERROR(VLOOKUP($AG23,'02 Lists'!$A$5:$B$18,2,FALSE()),1))) | AK23: =IF(COUNT(L23,R23,X23,AD23,AJ23)=0,"",MIN(L23,R23,X23,AD23,AJ23)) | AL23: =IF($AK23="","",IF(L23=$AK23,$G23,IF(R23=$AK23,$M23,IF(X23=$AK23,$S23,IF(AD23=$AK23,$Y23,IF(AJ23=$AK23,$AE23,"")))))) | AM23: =IF($AK23="","",$AK23/IF($E23="",1,$E23)) | AN23: =COUNT(L23,R23,X23,AD23,AJ23) | AO23: =IF(COUNT(L23,R23,X23,AD23,AJ23)=0,"",MAX(L23,R23,X23,AD23,AJ23)) | AP23: =IF(OR($AK23="",$AO23="",$AO23=0),"",($AO23-$AK23)/$AO23) | AQ23: =IF($AK23="","",IF(L23=$AK23,$K23,IF(R23=$AK23,$Q23,IF(X23=$AK23,$W23,IF(AD23=$AK23,$AC23,IF(AJ23=$AK23,$AI23,"")))))) | AT23: ='03 Suppliers'!$B$23&""
A24: PP-TOM-PASTE | B24: Tomato | C24: Tomato paste / concentrate | D24: g | E24: 1 | F24: Depth without wine (alcohol-free build) | L24: =IF(OR($J24="",$H24="",$H24=0),"",$J24/(1+IF(IFERROR(INDEX('03 Suppliers'!$N$5:$N$34,MATCH($G24,'03 Suppliers'!$B$5:$B$34,0)),"Excl VAT")="Incl VAT",'01 Control'!$C$6,0))/($H24*IFERROR(VLOOKUP($I24,'02 Lists'!$A$5:$B$18,2,FALSE()),1))) | R24: =IF(OR($P24="",$N24="",$N24=0),"",$P24/(1+IF(IFERROR(INDEX('03 Suppliers'!$N$5:$N$34,MATCH($M24,'03 Suppliers'!$B$5:$B$34,0)),"Excl VAT")="Incl VAT",'01 Control'!$C$6,0))/($N24*IFERROR(VLOOKUP($O24,'02 Lists'!$A$5:$B$18,2,FALSE()),1))) | X24: =IF(OR($V24="",$T24="",$T24=0),"",$V24/(1+IF(IFERROR(INDEX('03 Suppliers'!$N$5:$N$34,MATCH($S24,'03 Suppliers'!$B$5:$B$34,0)),"Excl VAT")="Incl VAT",'01 Control'!$C$6,0))/($T24*IFERROR(VLOOKUP($U24,'02 Lists'!$A$5:$B$18,2,FALSE()),1))) | AD24: =IF(OR($AB24="",$Z24="",$Z24=0),"",$AB24/(1+IF(IFERROR(INDEX('03 Suppliers'!$N$5:$N$34,MATCH($Y24,'03 Suppliers'!$B$5:$B$34,0)),"Excl VAT")="Incl VAT",'01 Control'!$C$6,0))/($Z24*IFERROR(VLOOKUP($AA24,'02 Lists'!$A$5:$B$18,2,FALSE()),1))) | AJ24: =IF(OR($AH24="",$AF24="",$AF24=0),"",$AH24/(1+IF(IFERROR(INDEX('03 Suppliers'!$N$5:$N$34,MATCH($AE24,'03 Suppliers'!$B$5:$B$34,0)),"Excl VAT")="Incl VAT",'01 Control'!$C$6,0))/($AF24*IFERROR(VLOOKUP($AG24,'02 Lists'!$A$5:$B$18,2,FALSE()),1))) | AK24: =IF(COUNT(L24,R24,X24,AD24,AJ24)=0,"",MIN(L24,R24,X24,AD24,AJ24)) | AL24: =IF($AK24="","",IF(L24=$AK24,$G24,IF(R24=$AK24,$M24,IF(X24=$AK24,$S24,IF(AD24=$AK24,$Y24,IF(AJ24=$AK24,$AE24,"")))))) | AM24: =IF($AK24="","",$AK24/IF($E24="",1,$E24)) | AN24: =COUNT(L24,R24,X24,AD24,AJ24) | AO24: =IF(COUNT(L24,R24,X24,AD24,AJ24)=0,"",MAX(L24,R24,X24,AD24,AJ24)) | AP24: =IF(OR($AK24="",$AO24="",$AO24=0),"",($AO24-$AK24)/$AO24) | AQ24: =IF($AK24="","",IF(L24=$AK24,$K24,IF(R24=$AK24,$Q24,IF(X24=$AK24,$W24,IF(AD24=$AK24,$AC24,IF(AJ24=$AK24,$AI24,"")))))) | AT24: ='03 Suppliers'!$B$24&""
A25: PP-SUGAR | B25: Dry Goods | C25: Sugar (acidity balance) | D25: g | E25: 1 | F25: Whisper only - balance, not sweetness | L25: =IF(OR($J25="",$H25="",$H25=0),"",$J25/(1+IF(IFERROR(INDEX('03 Suppliers'!$N$5:$N$34,MATCH($G25,'03 Suppliers'!$B$5:$B$34,0)),"Excl VAT")="Incl VAT",'01 Control'!$C$6,0))/($H25*IFERROR(VLOOKUP($I25,'02 Lists'!$A$5:$B$18,2,FALSE()),1))) | R25: =IF(OR($P25="",$N25="",$N25=0),"",$P25/(1+IF(IFERROR(INDEX('03 Suppliers'!$N$5:$N$34,MATCH($M25,'03 Suppliers'!$B$5:$B$34,0)),"Excl VAT")="Incl VAT",'01 Control'!$C$6,0))/($N25*IFERROR(VLOOKUP($O25,'02 Lists'!$A$5:$B$18,2,FALSE()),1))) | X25: =IF(OR($V25="",$T25="",$T25=0),"",$V25/(1+IF(IFERROR(INDEX('03 Suppliers'!$N$5:$N$34,MATCH($S25,'03 Suppliers'!$B$5:$B$34,0)),"Excl VAT")="Incl VAT",'01 Control'!$C$6,0))/($T25*IFERROR(VLOOKUP($U25,'02 Lists'!$A$5:$B$18,2,FALSE()),1))) | AD25: =IF(OR($AB25="",$Z25="",$Z25=0),"",$AB25/(1+IF(IFERROR(INDEX('03 Suppliers'!$N$5:$N$34,MATCH($Y25,'03 Suppliers'!$B$5:$B$34,0)),"Excl VAT")="Incl VAT",'01 Control'!$C$6,0))/($Z25*IFERROR(VLOOKUP($AA25,'02 Lists'!$A$5:$B$18,2,FALSE()),1))) | AJ25: =IF(OR($AH25="",$AF25="",$AF25=0),"",$AH25/(1+IF(IFERROR(INDEX('03 Suppliers'!$N$5:$N$34,MATCH($AE25,'03 Suppliers'!$B$5:$B$34,0)),"Excl VAT")="Incl VAT",'01 Control'!$C$6,0))/($AF25*IFERROR(VLOOKUP($AG25,'02 Lists'!$A$5:$B$18,2,FALSE()),1))) | AK25: =IF(COUNT(L25,R25,X25,AD25,AJ25)=0,"",MIN(L25,R25,X25,AD25,AJ25)) | AL25: =IF($AK25="","",IF(L25=$AK25,$G25,IF(R25=$AK25,$M25,IF(X25=$AK25,$S25,IF(AD25=$AK25,$Y25,IF(AJ25=$AK25,$AE25,"")))))) | AM25: =IF($AK25="","",$AK25/IF($E25="",1,$E25)) | AN25: =COUNT(L25,R25,X25,AD25,AJ25) | AO25: =IF(COUNT(L25,R25,X25,AD25,AJ25)=0,"",MAX(L25,R25,X25,AD25,AJ25)) | AP25: =IF(OR($AK25="",$AO25="",$AO25=0),"",($AO25-$AK25)/$AO25) | AQ25: =IF($AK25="","",IF(L25=$AK25,$K25,IF(R25=$AK25,$Q25,IF(X25=$AK25,$W25,IF(AD25=$AK25,$AC25,IF(AJ25=$AK25,$AI25,"")))))) | AT25: ='03 Suppliers'!$B$25&""
A26: PP-STOCK-BEEF | B26: Dry Goods | C26: Beef stock / bouillon (halaal) | D26: ml | E26: 1 | F26: Halaal-certified | L26: =IF(OR($J26="",$H26="",$H26=0),"",$J26/(1+IF(IFERROR(INDEX('03 Suppliers'!$N$5:$N$34,MATCH($G26,'03 Suppliers'!$B$5:$B$34,0)),"Excl VAT")="Incl VAT",'01 Control'!$C$6,0))/($H26*IFERROR(VLOOKUP($I26,'02 Lists'!$A$5:$B$18,2,FALSE()),1))) | R26: =IF(OR($P26="",$N26="",$N26=0),"",$P26/(1+IF(IFERROR(INDEX('03 Suppliers'!$N$5:$N$34,MATCH($M26,'03 Suppliers'!$B$5:$B$34,0)),"Excl VAT")="Incl VAT",'01 Control'!$C$6,0))/($N26*IFERROR(VLOOKUP($O26,'02 Lists'!$A$5:$B$18,2,FALSE()),1))) | X26: =IF(OR($V26="",$T26="",$T26=0),"",$V26/(1+IF(IFERROR(INDEX('03 Suppliers'!$N$5:$N$34,MATCH($S26,'03 Suppliers'!$B$5:$B$34,0)),"Excl VAT")="Incl VAT",'01 Control'!$C$6,0))/($T26*IFERROR(VLOOKUP($U26,'02 Lists'!$A$5:$B$18,2,FALSE()),1))) | AD26: =IF(OR($AB26="",$Z26="",$Z26=0),"",$AB26/(1+IF(IFERROR(INDEX('03 Suppliers'!$N$5:$N$34,MATCH($Y26,'03 Suppliers'!$B$5:$B$34,0)),"Excl VAT")="Incl VAT",'01 Control'!$C$6,0))/($Z26*IFERROR(VLOOKUP($AA26,'02 Lists'!$A$5:$B$18,2,FALSE()),1))) | AJ26: =IF(OR($AH26="",$AF26="",$AF26=0),"",$AH26/(1+IF(IFERROR(INDEX('03 Suppliers'!$N$5:$N$34,MATCH($AE26,'03 Suppliers'!$B$5:$B$34,0)),"Excl VAT")="Incl VAT",'01 Control'!$C$6,0))/($AF26*IFERROR(VLOOKUP($AG26,'02 Lists'!$A$5:$B$18,2,FALSE()),1))) | AK26: =IF(COUNT(L26,R26,X26,AD26,AJ26)=0,"",MIN(L26,R26,X26,AD26,AJ26)) | AL26: =IF($AK26="","",IF(L26=$AK26,$G26,IF(R26=$AK26,$M26,IF(X26=$AK26,$S26,IF(AD26=$AK26,$Y26,IF(AJ26=$AK26,$AE26,"")))))) | AM26: =IF($AK26="","",$AK26/IF($E26="",1,$E26)) | AN26: =COUNT(L26,R26,X26,AD26,AJ26) | AO26: =IF(COUNT(L26,R26,X26,AD26,AJ26)=0,"",MAX(L26,R26,X26,AD26,AJ26)) | AP26: =IF(OR($AK26="",$AO26="",$AO26=0),"",($AO26-$AK26)/$AO26) | AQ26: =IF($AK26="","",IF(L26=$AK26,$K26,IF(R26=$AK26,$Q26,IF(X26=$AK26,$W26,IF(AD26=$AK26,$AC26,IF(AJ26=$AK26,$AI26,"")))))) | AT26: ='03 Suppliers'!$B$26&""
A27: PP-STOCK-VEG | B27: Dry Goods | C27: Vegetable stock | D27: ml | E27: 1 | L27: =IF(OR($J27="",$H27="",$H27=0),"",$J27/(1+IF(IFERROR(INDEX('03 Suppliers'!$N$5:$N$34,MATCH($G27,'03 Suppliers'!$B$5:$B$34,0)),"Excl VAT")="Incl VAT",'01 Control'!$C$6,0))/($H27*IFERROR(VLOOKUP($I27,'02 Lists'!$A$5:$B$18,2,FALSE()),1))) | R27: =IF(OR($P27="",$N27="",$N27=0),"",$P27/(1+IF(IFERROR(INDEX('03 Suppliers'!$N$5:$N$34,MATCH($M27,'03 Suppliers'!$B$5:$B$34,0)),"Excl VAT")="Incl VAT",'01 Control'!$C$6,0))/($N27*IFERROR(VLOOKUP($O27,'02 Lists'!$A$5:$B$18,2,FALSE()),1))) | X27: =IF(OR($V27="",$T27="",$T27=0),"",$V27/(1+IF(IFERROR(INDEX('03 Suppliers'!$N$5:$N$34,MATCH($S27,'03 Suppliers'!$B$5:$B$34,0)),"Excl VAT")="Incl VAT",'01 Control'!$C$6,0))/($T27*IFERROR(VLOOKUP($U27,'02 Lists'!$A$5:$B$18,2,FALSE()),1))) | AD27: =IF(OR($AB27="",$Z27="",$Z27=0),"",$AB27/(1+IF(IFERROR(INDEX('03 Suppliers'!$N$5:$N$34,MATCH($Y27,'03 Suppliers'!$B$5:$B$34,0)),"Excl VAT")="Incl VAT",'01 Control'!$C$6,0))/($Z27*IFERROR(VLOOKUP($AA27,'02 Lists'!$A$5:$B$18,2,FALSE()),1))) | AJ27: =IF(OR($AH27="",$AF27="",$AF27=0),"",$AH27/(1+IF(IFERROR(INDEX('03 Suppliers'!$N$5:$N$34,MATCH($AE27,'03 Suppliers'!$B$5:$B$34,0)),"Excl VAT")="Incl VAT",'01 Control'!$C$6,0))/($AF27*IFERROR(VLOOKUP($AG27,'02 Lists'!$A$5:$B$18,2,FALSE()),1))) | AK27: =IF(COUNT(L27,R27,X27,AD27,AJ27)=0,"",MIN(L27,R27,X27,AD27,AJ27)) | AL27: =IF($AK27="","",IF(L27=$AK27,$G27,IF(R27=$AK27,$M27,IF(X27=$AK27,$S27,IF(AD27=$AK27,$Y27,IF(AJ27=$AK27,$AE27,"")))))) | AM27: =IF($AK27="","",$AK27/IF($E27="",1,$E27)) | AN27: =COUNT(L27,R27,X27,AD27,AJ27) | AO27: =IF(COUNT(L27,R27,X27,AD27,AJ27)=0,"",MAX(L27,R27,X27,AD27,AJ27)) | AP27: =IF(OR($AK27="",$AO27="",$AO27=0),"",($AO27-$AK27)/$AO27) | AQ27: =IF($AK27="","",IF(L27=$AK27,$K27,IF(R27=$AK27,$Q27,IF(X27=$AK27,$W27,IF(AD27=$AK27,$AC27,IF(AJ27=$AK27,$AI27,"")))))) | AT27: ='03 Suppliers'!$B$27&""
A28: PP-PEPPER-BLACK | B28: Spice | C28: Black pepper, cracked | D28: g | E28: 1 | F28: Carbonara signature | L28: =IF(OR($J28="",$H28="",$H28=0),"",$J28/(1+IF(IFERROR(INDEX('03 Suppliers'!$N$5:$N$34,MATCH($G28,'03 Suppliers'!$B$5:$B$34,0)),"Excl VAT")="Incl VAT",'01 Control'!$C$6,0))/($H28*IFERROR(VLOOKUP($I28,'02 Lists'!$A$5:$B$18,2,FALSE()),1))) | R28: =IF(OR($P28="",$N28="",$N28=0),"",$P28/(1+IF(IFERROR(INDEX('03 Suppliers'!$N$5:$N$34,MATCH($M28,'03 Suppliers'!$B$5:$B$34,0)),"Excl VAT")="Incl VAT",'01 Control'!$C$6,0))/($N28*IFERROR(VLOOKUP($O28,'02 Lists'!$A$5:$B$18,2,FALSE()),1))) | X28: =IF(OR($V28="",$T28="",$T28=0),"",$V28/(1+IF(IFERROR(INDEX('03 Suppliers'!$N$5:$N$34,MATCH($S28,'03 Suppliers'!$B$5:$B$34,0)),"Excl VAT")="Incl VAT",'01 Control'!$C$6,0))/($T28*IFERROR(VLOOKUP($U28,'02 Lists'!$A$5:$B$18,2,FALSE()),1))) | AD28: =IF(OR($AB28="",$Z28="",$Z28=0),"",$AB28/(1+IF(IFERROR(INDEX('03 Suppliers'!$N$5:$N$34,MATCH($Y28,'03 Suppliers'!$B$5:$B$34,0)),"Excl VAT")="Incl VAT",'01 Control'!$C$6,0))/($Z28*IFERROR(VLOOKUP($AA28,'02 Lists'!$A$5:$B$18,2,FALSE()),1))) | AJ28: =IF(OR($AH28="",$AF28="",$AF28=0),"",$AH28/(1+IF(IFERROR(INDEX('03 Suppliers'!$N$5:$N$34,MATCH($AE28,'03 Suppliers'!$B$5:$B$34,0)),"Excl VAT")="Incl VAT",'01 Control'!$C$6,0))/($AF28*IFERROR(VLOOKUP($AG28,'02 Lists'!$A$5:$B$18,2,FALSE()),1))) | AK28: =IF(COUNT(L28,R28,X28,AD28,AJ28)=0,"",MIN(L28,R28,X28,AD28,AJ28)) | AL28: =IF($AK28="","",IF(L28=$AK28,$G28,IF(R28=$AK28,$M28,IF(X28=$AK28,$S28,IF(AD28=$AK28,$Y28,IF(AJ28=$AK28,$AE28,"")))))) | AM28: =IF($AK28="","",$AK28/IF($E28="",1,$E28)) | AN28: =COUNT(L28,R28,X28,AD28,AJ28) | AO28: =IF(COUNT(L28,R28,X28,AD28,AJ28)=0,"",MAX(L28,R28,X28,AD28,AJ28)) | AP28: =IF(OR($AK28="",$AO28="",$AO28=0),"",($AO28-$AK28)/$AO28) | AQ28: =IF($AK28="","",IF(L28=$AK28,$K28,IF(R28=$AK28,$Q28,IF(X28=$AK28,$W28,IF(AD28=$AK28,$AC28,IF(AJ28=$AK28,$AI28,"")))))) | AT28: ='03 Suppliers'!$B$28&""
A29: PP-CHILLI-FLAKE | B29: Spice | C29: Dried chilli flakes | D29: g | E29: 1 | F29: Arrabbiata / Aglio e Olio | L29: =IF(OR($J29="",$H29="",$H29=0),"",$J29/(1+IF(IFERROR(INDEX('03 Suppliers'!$N$5:$N$34,MATCH($G29,'03 Suppliers'!$B$5:$B$34,0)),"Excl VAT")="Incl VAT",'01 Control'!$C$6,0))/($H29*IFERROR(VLOOKUP($I29,'02 Lists'!$A$5:$B$18,2,FALSE()),1))) | R29: =IF(OR($P29="",$N29="",$N29=0),"",$P29/(1+IF(IFERROR(INDEX('03 Suppliers'!$N$5:$N$34,MATCH($M29,'03 Suppliers'!$B$5:$B$34,0)),"Excl VAT")="Incl VAT",'01 Control'!$C$6,0))/($N29*IFERROR(VLOOKUP($O29,'02 Lists'!$A$5:$B$18,2,FALSE()),1))) | X29: =IF(OR($V29="",$T29="",$T29=0),"",$V29/(1+IF(IFERROR(INDEX('03 Suppliers'!$N$5:$N$34,MATCH($S29,'03 Suppliers'!$B$5:$B$34,0)),"Excl VAT")="Incl VAT",'01 Control'!$C$6,0))/($T29*IFERROR(VLOOKUP($U29,'02 Lists'!$A$5:$B$18,2,FALSE()),1))) | AD29: =IF(OR($AB29="",$Z29="",$Z29=0),"",$AB29/(1+IF(IFERROR(INDEX('03 Suppliers'!$N$5:$N$34,MATCH($Y29,'03 Suppliers'!$B$5:$B$34,0)),"Excl VAT")="Incl VAT",'01 Control'!$C$6,0))/($Z29*IFERROR(VLOOKUP($AA29,'02 Lists'!$A$5:$B$18,2,FALSE()),1))) | AJ29: =IF(OR($AH29="",$AF29="",$AF29=0),"",$AH29/(1+IF(IFERROR(INDEX('03 Suppliers'!$N$5:$N$34,MATCH($AE29,'03 Suppliers'!$B$5:$B$34,0)),"Excl VAT")="Incl VAT",'01 Control'!$C$6,0))/($AF29*IFERROR(VLOOKUP($AG29,'02 Lists'!$A$5:$B$18,2,FALSE()),1))) | AK29: =IF(COUNT(L29,R29,X29,AD29,AJ29)=0,"",MIN(L29,R29,X29,AD29,AJ29)) | AL29: =IF($AK29="","",IF(L29=$AK29,$G29,IF(R29=$AK29,$M29,IF(X29=$AK29,$S29,IF(AD29=$AK29,$Y29,IF(AJ29=$AK29,$AE29,"")))))) | AM29: =IF($AK29="","",$AK29/IF($E29="",1,$E29)) | AN29: =COUNT(L29,R29,X29,AD29,AJ29) | AO29: =IF(COUNT(L29,R29,X29,AD29,AJ29)=0,"",MAX(L29,R29,X29,AD29,AJ29)) | AP29: =IF(OR($AK29="",$AO29="",$AO29=0),"",($AO29-$AK29)/$AO29) | AQ29: =IF($AK29="","",IF(L29=$AK29,$K29,IF(R29=$AK29,$Q29,IF(X29=$AK29,$W29,IF(AD29=$AK29,$AC29,IF(AJ29=$AK29,$AI29,"")))))) | AT29: ='03 Suppliers'!$B$29&""
A30: PP-HERB-BASIL-DRY | B30: Spice | C30: Dried basil / oregano blend | D30: g | E30: 1 | F30: Commissary sauce bases | L30: =IF(OR($J30="",$H30="",$H30=0),"",$J30/(1+IF(IFERROR(INDEX('03 Suppliers'!$N$5:$N$34,MATCH($G30,'03 Suppliers'!$B$5:$B$34,0)),"Excl VAT")="Incl VAT",'01 Control'!$C$6,0))/($H30*IFERROR(VLOOKUP($I30,'02 Lists'!$A$5:$B$18,2,FALSE()),1))) | R30: =IF(OR($P30="",$N30="",$N30=0),"",$P30/(1+IF(IFERROR(INDEX('03 Suppliers'!$N$5:$N$34,MATCH($M30,'03 Suppliers'!$B$5:$B$34,0)),"Excl VAT")="Incl VAT",'01 Control'!$C$6,0))/($N30*IFERROR(VLOOKUP($O30,'02 Lists'!$A$5:$B$18,2,FALSE()),1))) | X30: =IF(OR($V30="",$T30="",$T30=0),"",$V30/(1+IF(IFERROR(INDEX('03 Suppliers'!$N$5:$N$34,MATCH($S30,'03 Suppliers'!$B$5:$B$34,0)),"Excl VAT")="Incl VAT",'01 Control'!$C$6,0))/($T30*IFERROR(VLOOKUP($U30,'02 Lists'!$A$5:$B$18,2,FALSE()),1))) | AD30: =IF(OR($AB30="",$Z30="",$Z30=0),"",$AB30/(1+IF(IFERROR(INDEX('03 Suppliers'!$N$5:$N$34,MATCH($Y30,'03 Suppliers'!$B$5:$B$34,0)),"Excl VAT")="Incl VAT",'01 Control'!$C$6,0))/($Z30*IFERROR(VLOOKUP($AA30,'02 Lists'!$A$5:$B$18,2,FALSE()),1))) | AJ30: =IF(OR($AH30="",$AF30="",$AF30=0),"",$AH30/(1+IF(IFERROR(INDEX('03 Suppliers'!$N$5:$N$34,MATCH($AE30,'03 Suppliers'!$B$5:$B$34,0)),"Excl VAT")="Incl VAT",'01 Control'!$C$6,0))/($AF30*IFERROR(VLOOKUP($AG30,'02 Lists'!$A$5:$B$18,2,FALSE()),1))) | AK30: =IF(COUNT(L30,R30,X30,AD30,AJ30)=0,"",MIN(L30,R30,X30,AD30,AJ30)) | AL30: =IF($AK30="","",IF(L30=$AK30,$G30,IF(R30=$AK30,$M30,IF(X30=$AK30,$S30,IF(AD30=$AK30,$Y30,IF(AJ30=$AK30,$AE30,"")))))) | AM30: =IF($AK30="","",$AK30/IF($E30="",1,$E30)) | AN30: =COUNT(L30,R30,X30,AD30,AJ30) | AO30: =IF(COUNT(L30,R30,X30,AD30,AJ30)=0,"",MAX(L30,R30,X30,AD30,AJ30)) | AP30: =IF(OR($AK30="",$AO30="",$AO30=0),"",($AO30-$AK30)/$AO30) | AQ30: =IF($AK30="","",IF(L30=$AK30,$K30,IF(R30=$AK30,$Q30,IF(X30=$AK30,$W30,IF(AD30=$AK30,$AC30,IF(AJ30=$AK30,$AI30,"")))))) | AT30: ='03 Suppliers'!$B$30&""
A31: PP-HERB-BASIL-FRESH | B31: Fresh Herb | C31: Fresh basil | D31: g | E31: 0.85 | F31: Pesto + finishing; high trim loss | L31: =IF(OR($J31="",$H31="",$H31=0),"",$J31/(1+IF(IFERROR(INDEX('03 Suppliers'!$N$5:$N$34,MATCH($G31,'03 Suppliers'!$B$5:$B$34,0)),"Excl VAT")="Incl VAT",'01 Control'!$C$6,0))/($H31*IFERROR(VLOOKUP($I31,'02 Lists'!$A$5:$B$18,2,FALSE()),1))) | R31: =IF(OR($P31="",$N31="",$N31=0),"",$P31/(1+IF(IFERROR(INDEX('03 Suppliers'!$N$5:$N$34,MATCH($M31,'03 Suppliers'!$B$5:$B$34,0)),"Excl VAT")="Incl VAT",'01 Control'!$C$6,0))/($N31*IFERROR(VLOOKUP($O31,'02 Lists'!$A$5:$B$18,2,FALSE()),1))) | X31: =IF(OR($V31="",$T31="",$T31=0),"",$V31/(1+IF(IFERROR(INDEX('03 Suppliers'!$N$5:$N$34,MATCH($S31,'03 Suppliers'!$B$5:$B$34,0)),"Excl VAT")="Incl VAT",'01 Control'!$C$6,0))/($T31*IFERROR(VLOOKUP($U31,'02 Lists'!$A$5:$B$18,2,FALSE()),1))) | AD31: =IF(OR($AB31="",$Z31="",$Z31=0),"",$AB31/(1+IF(IFERROR(INDEX('03 Suppliers'!$N$5:$N$34,MATCH($Y31,'03 Suppliers'!$B$5:$B$34,0)),"Excl VAT")="Incl VAT",'01 Control'!$C$6,0))/($Z31*IFERROR(VLOOKUP($AA31,'02 Lists'!$A$5:$B$18,2,FALSE()),1))) | AJ31: =IF(OR($AH31="",$AF31="",$AF31=0),"",$AH31/(1+IF(IFERROR(INDEX('03 Suppliers'!$N$5:$N$34,MATCH($AE31,'03 Suppliers'!$B$5:$B$34,0)),"Excl VAT")="Incl VAT",'01 Control'!$C$6,0))/($AF31*IFERROR(VLOOKUP($AG31,'02 Lists'!$A$5:$B$18,2,FALSE()),1))) | AK31: =IF(COUNT(L31,R31,X31,AD31,AJ31)=0,"",MIN(L31,R31,X31,AD31,AJ31)) | AL31: =IF($AK31="","",IF(L31=$AK31,$G31,IF(R31=$AK31,$M31,IF(X31=$AK31,$S31,IF(AD31=$AK31,$Y31,IF(AJ31=$AK31,$AE31,"")))))) | AM31: =IF($AK31="","",$AK31/IF($E31="",1,$E31)) | AN31: =COUNT(L31,R31,X31,AD31,AJ31) | AO31: =IF(COUNT(L31,R31,X31,AD31,AJ31)=0,"",MAX(L31,R31,X31,AD31,AJ31)) | AP31: =IF(OR($AK31="",$AO31="",$AO31=0),"",($AO31-$AK31)/$AO31) | AQ31: =IF($AK31="","",IF(L31=$AK31,$K31,IF(R31=$AK31,$Q31,IF(X31=$AK31,$W31,IF(AD31=$AK31,$AC31,IF(AJ31=$AK31,$AI31,"")))))) | AT31: ='03 Suppliers'!$B$31&""
A32: PP-HERB-PARSLEY | B32: Fresh Herb | C32: Fresh parsley | D32: g | E32: 0.8 | F32: Aglio e Olio finish | L32: =IF(OR($J32="",$H32="",$H32=0),"",$J32/(1+IF(IFERROR(INDEX('03 Suppliers'!$N$5:$N$34,MATCH($G32,'03 Suppliers'!$B$5:$B$34,0)),"Excl VAT")="Incl VAT",'01 Control'!$C$6,0))/($H32*IFERROR(VLOOKUP($I32,'02 Lists'!$A$5:$B$18,2,FALSE()),1))) | R32: =IF(OR($P32="",$N32="",$N32=0),"",$P32/(1+IF(IFERROR(INDEX('03 Suppliers'!$N$5:$N$34,MATCH($M32,'03 Suppliers'!$B$5:$B$34,0)),"Excl VAT")="Incl VAT",'01 Control'!$C$6,0))/($N32*IFERROR(VLOOKUP($O32,'02 Lists'!$A$5:$B$18,2,FALSE()),1))) | X32: =IF(OR($V32="",$T32="",$T32=0),"",$V32/(1+IF(IFERROR(INDEX('03 Suppliers'!$N$5:$N$34,MATCH($S32,'03 Suppliers'!$B$5:$B$34,0)),"Excl VAT")="Incl VAT",'01 Control'!$C$6,0))/($T32*IFERROR(VLOOKUP($U32,'02 Lists'!$A$5:$B$18,2,FALSE()),1))) | AD32: =IF(OR($AB32="",$Z32="",$Z32=0),"",$AB32/(1+IF(IFERROR(INDEX('03 Suppliers'!$N$5:$N$34,MATCH($Y32,'03 Suppliers'!$B$5:$B$34,0)),"Excl VAT")="Incl VAT",'01 Control'!$C$6,0))/($Z32*IFERROR(VLOOKUP($AA32,'02 Lists'!$A$5:$B$18,2,FALSE()),1))) | AJ32: =IF(OR($AH32="",$AF32="",$AF32=0),"",$AH32/(1+IF(IFERROR(INDEX('03 Suppliers'!$N$5:$N$34,MATCH($AE32,'03 Suppliers'!$B$5:$B$34,0)),"Excl VAT")="Incl VAT",'01 Control'!$C$6,0))/($AF32*IFERROR(VLOOKUP($AG32,'02 Lists'!$A$5:$B$18,2,FALSE()),1))) | AK32: =IF(COUNT(L32,R32,X32,AD32,AJ32)=0,"",MIN(L32,R32,X32,AD32,AJ32)) | AL32: =IF($AK32="","",IF(L32=$AK32,$G32,IF(R32=$AK32,$M32,IF(X32=$AK32,$S32,IF(AD32=$AK32,$Y32,IF(AJ32=$AK32,$AE32,"")))))) | AM32: =IF($AK32="","",$AK32/IF($E32="",1,$E32)) | AN32: =COUNT(L32,R32,X32,AD32,AJ32) | AO32: =IF(COUNT(L32,R32,X32,AD32,AJ32)=0,"",MAX(L32,R32,X32,AD32,AJ32)) | AP32: =IF(OR($AK32="",$AO32="",$AO32=0),"",($AO32-$AK32)/$AO32) | AQ32: =IF($AK32="","",IF(L32=$AK32,$K32,IF(R32=$AK32,$Q32,IF(X32=$AK32,$W32,IF(AD32=$AK32,$AC32,IF(AJ32=$AK32,$AI32,"")))))) | AT32: ='03 Suppliers'!$B$32&""
A33: PP-HERB-THYME | B33: Fresh Herb | C33: Fresh thyme | D33: g | E33: 0.7 | F33: Boscaiola / Harvest seasonal | L33: =IF(OR($J33="",$H33="",$H33=0),"",$J33/(1+IF(IFERROR(INDEX('03 Suppliers'!$N$5:$N$34,MATCH($G33,'03 Suppliers'!$B$5:$B$34,0)),"Excl VAT")="Incl VAT",'01 Control'!$C$6,0))/($H33*IFERROR(VLOOKUP($I33,'02 Lists'!$A$5:$B$18,2,FALSE()),1))) | R33: =IF(OR($P33="",$N33="",$N33=0),"",$P33/(1+IF(IFERROR(INDEX('03 Suppliers'!$N$5:$N$34,MATCH($M33,'03 Suppliers'!$B$5:$B$34,0)),"Excl VAT")="Incl VAT",'01 Control'!$C$6,0))/($N33*IFERROR(VLOOKUP($O33,'02 Lists'!$A$5:$B$18,2,FALSE()),1))) | X33: =IF(OR($V33="",$T33="",$T33=0),"",$V33/(1+IF(IFERROR(INDEX('03 Suppliers'!$N$5:$N$34,MATCH($S33,'03 Suppliers'!$B$5:$B$34,0)),"Excl VAT")="Incl VAT",'01 Control'!$C$6,0))/($T33*IFERROR(VLOOKUP($U33,'02 Lists'!$A$5:$B$18,2,FALSE()),1))) | AD33: =IF(OR($AB33="",$Z33="",$Z33=0),"",$AB33/(1+IF(IFERROR(INDEX('03 Suppliers'!$N$5:$N$34,MATCH($Y33,'03 Suppliers'!$B$5:$B$34,0)),"Excl VAT")="Incl VAT",'01 Control'!$C$6,0))/($Z33*IFERROR(VLOOKUP($AA33,'02 Lists'!$A$5:$B$18,2,FALSE()),1))) | AJ33: =IF(OR($AH33="",$AF33="",$AF33=0),"",$AH33/(1+IF(IFERROR(INDEX('03 Suppliers'!$N$5:$N$34,MATCH($AE33,'03 Suppliers'!$B$5:$B$34,0)),"Excl VAT")="Incl VAT",'01 Control'!$C$6,0))/($AF33*IFERROR(VLOOKUP($AG33,'02 Lists'!$A$5:$B$18,2,FALSE()),1))) | AK33: =IF(COUNT(L33,R33,X33,AD33,AJ33)=0,"",MIN(L33,R33,X33,AD33,AJ33)) | AL33: =IF($AK33="","",IF(L33=$AK33,$G33,IF(R33=$AK33,$M33,IF(X33=$AK33,$S33,IF(AD33=$AK33,$Y33,IF(AJ33=$AK33,$AE33,"")))))) | AM33: =IF($AK33="","",$AK33/IF($E33="",1,$E33)) | AN33: =COUNT(L33,R33,X33,AD33,AJ33) | AO33: =IF(COUNT(L33,R33,X33,AD33,AJ33)=0,"",MAX(L33,R33,X33,AD33,AJ33)) | AP33: =IF(OR($AK33="",$AO33="",$AO33=0),"",($AO33-$AK33)/$AO33) | AQ33: =IF($AK33="","",IF(L33=$AK33,$K33,IF(R33=$AK33,$Q33,IF(X33=$AK33,$W33,IF(AD33=$AK33,$AC33,IF(AJ33=$AK33,$AI33,"")))))) | AT33: ='03 Suppliers'!$B$33&""
A34: PP-HERB-SAGE | B34: Fresh Herb | C34: Fresh sage | D34: g | E34: 0.7 | F34: Autumn seasonal - butternut & sage | L34: =IF(OR($J34="",$H34="",$H34=0),"",$J34/(1+IF(IFERROR(INDEX('03 Suppliers'!$N$5:$N$34,MATCH($G34,'03 Suppliers'!$B$5:$B$34,0)),"Excl VAT")="Incl VAT",'01 Control'!$C$6,0))/($H34*IFERROR(VLOOKUP($I34,'02 Lists'!$A$5:$B$18,2,FALSE()),1))) | R34: =IF(OR($P34="",$N34="",$N34=0),"",$P34/(1+IF(IFERROR(INDEX('03 Suppliers'!$N$5:$N$34,MATCH($M34,'03 Suppliers'!$B$5:$B$34,0)),"Excl VAT")="Incl VAT",'01 Control'!$C$6,0))/($N34*IFERROR(VLOOKUP($O34,'02 Lists'!$A$5:$B$18,2,FALSE()),1))) | X34: =IF(OR($V34="",$T34="",$T34=0),"",$V34/(1+IF(IFERROR(INDEX('03 Suppliers'!$N$5:$N$34,MATCH($S34,'03 Suppliers'!$B$5:$B$34,0)),"Excl VAT")="Incl VAT",'01 Control'!$C$6,0))/($T34*IFERROR(VLOOKUP($U34,'02 Lists'!$A$5:$B$18,2,FALSE()),1))) | AD34: =IF(OR($AB34="",$Z34="",$Z34=0),"",$AB34/(1+IF(IFERROR(INDEX('03 Suppliers'!$N$5:$N$34,MATCH($Y34,'03 Suppliers'!$B$5:$B$34,0)),"Excl VAT")="Incl VAT",'01 Control'!$C$6,0))/($Z34*IFERROR(VLOOKUP($AA34,'02 Lists'!$A$5:$B$18,2,FALSE()),1))) | AJ34: =IF(OR($AH34="",$AF34="",$AF34=0),"",$AH34/(1+IF(IFERROR(INDEX('03 Suppliers'!$N$5:$N$34,MATCH($AE34,'03 Suppliers'!$B$5:$B$34,0)),"Excl VAT")="Incl VAT",'01 Control'!$C$6,0))/($AF34*IFERROR(VLOOKUP($AG34,'02 Lists'!$A$5:$B$18,2,FALSE()),1))) | AK34: =IF(COUNT(L34,R34,X34,AD34,AJ34)=0,"",MIN(L34,R34,X34,AD34,AJ34)) | AL34: =IF($AK34="","",IF(L34=$AK34,$G34,IF(R34=$AK34,$M34,IF(X34=$AK34,$S34,IF(AD34=$AK34,$Y34,IF(AJ34=$AK34,$AE34,"")))))) | AM34: =IF($AK34="","",$AK34/IF($E34="",1,$E34)) | AN34: =COUNT(L34,R34,X34,AD34,AJ34) | AO34: =IF(COUNT(L34,R34,X34,AD34,AJ34)=0,"",MAX(L34,R34,X34,AD34,AJ34)) | AP34: =IF(OR($AK34="",$AO34="",$AO34=0),"",($AO34-$AK34)/$AO34) | AQ34: =IF($AK34="","",IF(L34=$AK34,$K34,IF(R34=$AK34,$Q34,IF(X34=$AK34,$W34,IF(AD34=$AK34,$AC34,IF(AJ34=$AK34,$AI34,"")))))) | AT34: ='03 Suppliers'!$B$34&""
A35: PP-HERB-MINT | B35: Fresh Herb | C35: Fresh mint | D35: g | E35: 0.8 | F35: Year 3 spring - pea, mint & ricotta | L35: =IF(OR($J35="",$H35="",$H35=0),"",$J35/(1+IF(IFERROR(INDEX('03 Suppliers'!$N$5:$N$34,MATCH($G35,'03 Suppliers'!$B$5:$B$34,0)),"Excl VAT")="Incl VAT",'01 Control'!$C$6,0))/($H35*IFERROR(VLOOKUP($I35,'02 Lists'!$A$5:$B$18,2,FALSE()),1))) | R35: =IF(OR($P35="",$N35="",$N35=0),"",$P35/(1+IF(IFERROR(INDEX('03 Suppliers'!$N$5:$N$34,MATCH($M35,'03 Suppliers'!$B$5:$B$34,0)),"Excl VAT")="Incl VAT",'01 Control'!$C$6,0))/($N35*IFERROR(VLOOKUP($O35,'02 Lists'!$A$5:$B$18,2,FALSE()),1))) | X35: =IF(OR($V35="",$T35="",$T35=0),"",$V35/(1+IF(IFERROR(INDEX('03 Suppliers'!$N$5:$N$34,MATCH($S35,'03 Suppliers'!$B$5:$B$34,0)),"Excl VAT")="Incl VAT",'01 Control'!$C$6,0))/($T35*IFERROR(VLOOKUP($U35,'02 Lists'!$A$5:$B$18,2,FALSE()),1))) | AD35: =IF(OR($AB35="",$Z35="",$Z35=0),"",$AB35/(1+IF(IFERROR(INDEX('03 Suppliers'!$N$5:$N$34,MATCH($Y35,'03 Suppliers'!$B$5:$B$34,0)),"Excl VAT")="Incl VAT",'01 Control'!$C$6,0))/($Z35*IFERROR(VLOOKUP($AA35,'02 Lists'!$A$5:$B$18,2,FALSE()),1))) | AJ35: =IF(OR($AH35="",$AF35="",$AF35=0),"",$AH35/(1+IF(IFERROR(INDEX('03 Suppliers'!$N$5:$N$34,MATCH($AE35,'03 Suppliers'!$B$5:$B$34,0)),"Excl VAT")="Incl VAT",'01 Control'!$C$6,0))/($AF35*IFERROR(VLOOKUP($AG35,'02 Lists'!$A$5:$B$18,2,FALSE()),1))) | AK35: =IF(COUNT(L35,R35,X35,AD35,AJ35)=0,"",MIN(L35,R35,X35,AD35,AJ35)) | AL35: =IF($AK35="","",IF(L35=$AK35,$G35,IF(R35=$AK35,$M35,IF(X35=$AK35,$S35,IF(AD35=$AK35,$Y35,IF(AJ35=$AK35,$AE35,"")))))) | AM35: =IF($AK35="","",$AK35/IF($E35="",1,$E35)) | AN35: =COUNT(L35,R35,X35,AD35,AJ35) | AO35: =IF(COUNT(L35,R35,X35,AD35,AJ35)=0,"",MAX(L35,R35,X35,AD35,AJ35)) | AP35: =IF(OR($AK35="",$AO35="",$AO35=0),"",($AO35-$AK35)/$AO35) | AQ35: =IF($AK35="","",IF(L35=$AK35,$K35,IF(R35=$AK35,$Q35,IF(X35=$AK35,$W35,IF(AD35=$AK35,$AC35,IF(AJ35=$AK35,$AI35,""))))))
A36: PP-CREAM | B36: Dairy | C36: Fresh cream | D36: ml | E36: 1 | F36: Cream sauce bases | L36: =IF(OR($J36="",$H36="",$H36=0),"",$J36/(1+IF(IFERROR(INDEX('03 Suppliers'!$N$5:$N$34,MATCH($G36,'03 Suppliers'!$B$5:$B$34,0)),"Excl VAT")="Incl VAT",'01 Control'!$C$6,0))/($H36*IFERROR(VLOOKUP($I36,'02 Lists'!$A$5:$B$18,2,FALSE()),1))) | R36: =IF(OR($P36="",$N36="",$N36=0),"",$P36/(1+IF(IFERROR(INDEX('03 Suppliers'!$N$5:$N$34,MATCH($M36,'03 Suppliers'!$B$5:$B$34,0)),"Excl VAT")="Incl VAT",'01 Control'!$C$6,0))/($N36*IFERROR(VLOOKUP($O36,'02 Lists'!$A$5:$B$18,2,FALSE()),1))) | X36: =IF(OR($V36="",$T36="",$T36=0),"",$V36/(1+IF(IFERROR(INDEX('03 Suppliers'!$N$5:$N$34,MATCH($S36,'03 Suppliers'!$B$5:$B$34,0)),"Excl VAT")="Incl VAT",'01 Control'!$C$6,0))/($T36*IFERROR(VLOOKUP($U36,'02 Lists'!$A$5:$B$18,2,FALSE()),1))) | AD36: =IF(OR($AB36="",$Z36="",$Z36=0),"",$AB36/(1+IF(IFERROR(INDEX('03 Suppliers'!$N$5:$N$34,MATCH($Y36,'03 Suppliers'!$B$5:$B$34,0)),"Excl VAT")="Incl VAT",'01 Control'!$C$6,0))/($Z36*IFERROR(VLOOKUP($AA36,'02 Lists'!$A$5:$B$18,2,FALSE()),1))) | AJ36: =IF(OR($AH36="",$AF36="",$AF36=0),"",$AH36/(1+IF(IFERROR(INDEX('03 Suppliers'!$N$5:$N$34,MATCH($AE36,'03 Suppliers'!$B$5:$B$34,0)),"Excl VAT")="Incl VAT",'01 Control'!$C$6,0))/($AF36*IFERROR(VLOOKUP($AG36,'02 Lists'!$A$5:$B$18,2,FALSE()),1))) | AK36: =IF(COUNT(L36,R36,X36,AD36,AJ36)=0,"",MIN(L36,R36,X36,AD36,AJ36)) | AL36: =IF($AK36="","",IF(L36=$AK36,$G36,IF(R36=$AK36,$M36,IF(X36=$AK36,$S36,IF(AD36=$AK36,$Y36,IF(AJ36=$AK36,$AE36,"")))))) | AM36: =IF($AK36="","",$AK36/IF($E36="",1,$E36)) | AN36: =COUNT(L36,R36,X36,AD36,AJ36) | AO36: =IF(COUNT(L36,R36,X36,AD36,AJ36)=0,"",MAX(L36,R36,X36,AD36,AJ36)) | AP36: =IF(OR($AK36="",$AO36="",$AO36=0),"",($AO36-$AK36)/$AO36) | AQ36: =IF($AK36="","",IF(L36=$AK36,$K36,IF(R36=$AK36,$Q36,IF(X36=$AK36,$W36,IF(AD36=$AK36,$AC36,IF(AJ36=$AK36,$AI36,""))))))
A37: PP-PARM | B37: Cheese | C37: Parmesan / hard cheese (microbial rennet) | D37: g | E37: 0.95 | F37: HALAAL RENNET REQUIRED | L37: =IF(OR($J37="",$H37="",$H37=0),"",$J37/(1+IF(IFERROR(INDEX('03 Suppliers'!$N$5:$N$34,MATCH($G37,'03 Suppliers'!$B$5:$B$34,0)),"Excl VAT")="Incl VAT",'01 Control'!$C$6,0))/($H37*IFERROR(VLOOKUP($I37,'02 Lists'!$A$5:$B$18,2,FALSE()),1))) | R37: =IF(OR($P37="",$N37="",$N37=0),"",$P37/(1+IF(IFERROR(INDEX('03 Suppliers'!$N$5:$N$34,MATCH($M37,'03 Suppliers'!$B$5:$B$34,0)),"Excl VAT")="Incl VAT",'01 Control'!$C$6,0))/($N37*IFERROR(VLOOKUP($O37,'02 Lists'!$A$5:$B$18,2,FALSE()),1))) | X37: =IF(OR($V37="",$T37="",$T37=0),"",$V37/(1+IF(IFERROR(INDEX('03 Suppliers'!$N$5:$N$34,MATCH($S37,'03 Suppliers'!$B$5:$B$34,0)),"Excl VAT")="Incl VAT",'01 Control'!$C$6,0))/($T37*IFERROR(VLOOKUP($U37,'02 Lists'!$A$5:$B$18,2,FALSE()),1))) | AD37: =IF(OR($AB37="",$Z37="",$Z37=0),"",$AB37/(1+IF(IFERROR(INDEX('03 Suppliers'!$N$5:$N$34,MATCH($Y37,'03 Suppliers'!$B$5:$B$34,0)),"Excl VAT")="Incl VAT",'01 Control'!$C$6,0))/($Z37*IFERROR(VLOOKUP($AA37,'02 Lists'!$A$5:$B$18,2,FALSE()),1))) | AJ37: =IF(OR($AH37="",$AF37="",$AF37=0),"",$AH37/(1+IF(IFERROR(INDEX('03 Suppliers'!$N$5:$N$34,MATCH($AE37,'03 Suppliers'!$B$5:$B$34,0)),"Excl VAT")="Incl VAT",'01 Control'!$C$6,0))/($AF37*IFERROR(VLOOKUP($AG37,'02 Lists'!$A$5:$B$18,2,FALSE()),1))) | AK37: =IF(COUNT(L37,R37,X37,AD37,AJ37)=0,"",MIN(L37,R37,X37,AD37,AJ37)) | AL37: =IF($AK37="","",IF(L37=$AK37,$G37,IF(R37=$AK37,$M37,IF(X37=$AK37,$S37,IF(AD37=$AK37,$Y37,IF(AJ37=$AK37,$AE37,"")))))) | AM37: =IF($AK37="","",$AK37/IF($E37="",1,$E37)) | AN37: =COUNT(L37,R37,X37,AD37,AJ37) | AO37: =IF(COUNT(L37,R37,X37,AD37,AJ37)=0,"",MAX(L37,R37,X37,AD37,AJ37)) | AP37: =IF(OR($AK37="",$AO37="",$AO37=0),"",($AO37-$AK37)/$AO37) | AQ37: =IF($AK37="","",IF(L37=$AK37,$K37,IF(R37=$AK37,$Q37,IF(X37=$AK37,$W37,IF(AD37=$AK37,$AC37,IF(AJ37=$AK37,$AI37,""))))))
A38: PP-PECORINO | B38: Cheese | C38: Pecorino-style hard cheese (microbial rennet) | D38: g | E38: 0.95 | F38: HALAAL RENNET REQUIRED - Carbonara | L38: =IF(OR($J38="",$H38="",$H38=0),"",$J38/(1+IF(IFERROR(INDEX('03 Suppliers'!$N$5:$N$34,MATCH($G38,'03 Suppliers'!$B$5:$B$34,0)),"Excl VAT")="Incl VAT",'01 Control'!$C$6,0))/($H38*IFERROR(VLOOKUP($I38,'02 Lists'!$A$5:$B$18,2,FALSE()),1))) | R38: =IF(OR($P38="",$N38="",$N38=0),"",$P38/(1+IF(IFERROR(INDEX('03 Suppliers'!$N$5:$N$34,MATCH($M38,'03 Suppliers'!$B$5:$B$34,0)),"Excl VAT")="Incl VAT",'01 Control'!$C$6,0))/($N38*IFERROR(VLOOKUP($O38,'02 Lists'!$A$5:$B$18,2,FALSE()),1))) | X38: =IF(OR($V38="",$T38="",$T38=0),"",$V38/(1+IF(IFERROR(INDEX('03 Suppliers'!$N$5:$N$34,MATCH($S38,'03 Suppliers'!$B$5:$B$34,0)),"Excl VAT")="Incl VAT",'01 Control'!$C$6,0))/($T38*IFERROR(VLOOKUP($U38,'02 Lists'!$A$5:$B$18,2,FALSE()),1))) | AD38: =IF(OR($AB38="",$Z38="",$Z38=0),"",$AB38/(1+IF(IFERROR(INDEX('03 Suppliers'!$N$5:$N$34,MATCH($Y38,'03 Suppliers'!$B$5:$B$34,0)),"Excl VAT")="Incl VAT",'01 Control'!$C$6,0))/($Z38*IFERROR(VLOOKUP($AA38,'02 Lists'!$A$5:$B$18,2,FALSE()),1))) | AJ38: =IF(OR($AH38="",$AF38="",$AF38=0),"",$AH38/(1+IF(IFERROR(INDEX('03 Suppliers'!$N$5:$N$34,MATCH($AE38,'03 Suppliers'!$B$5:$B$34,0)),"Excl VAT")="Incl VAT",'01 Control'!$C$6,0))/($AF38*IFERROR(VLOOKUP($AG38,'02 Lists'!$A$5:$B$18,2,FALSE()),1))) | AK38: =IF(COUNT(L38,R38,X38,AD38,AJ38)=0,"",MIN(L38,R38,X38,AD38,AJ38)) | AL38: =IF($AK38="","",IF(L38=$AK38,$G38,IF(R38=$AK38,$M38,IF(X38=$AK38,$S38,IF(AD38=$AK38,$Y38,IF(AJ38=$AK38,$AE38,"")))))) | AM38: =IF($AK38="","",$AK38/IF($E38="",1,$E38)) | AN38: =COUNT(L38,R38,X38,AD38,AJ38) | AO38: =IF(COUNT(L38,R38,X38,AD38,AJ38)=0,"",MAX(L38,R38,X38,AD38,AJ38)) | AP38: =IF(OR($AK38="",$AO38="",$AO38=0),"",($AO38-$AK38)/$AO38) | AQ38: =IF($AK38="","",IF(L38=$AK38,$K38,IF(R38=$AK38,$Q38,IF(X38=$AK38,$W38,IF(AD38=$AK38,$AC38,IF(AJ38=$AK38,$AI38,""))))))
A39: PP-MOZZ | B39: Cheese | C39: Mozzarella | D39: g | E39: 1 | F39: Quattro Formaggi + bake top | L39: =IF(OR($J39="",$H39="",$H39=0),"",$J39/(1+IF(IFERROR(INDEX('03 Suppliers'!$N$5:$N$34,MATCH($G39,'03 Suppliers'!$B$5:$B$34,0)),"Excl VAT")="Incl VAT",'01 Control'!$C$6,0))/($H39*IFERROR(VLOOKUP($I39,'02 Lists'!$A$5:$B$18,2,FALSE()),1))) | R39: =IF(OR($P39="",$N39="",$N39=0),"",$P39/(1+IF(IFERROR(INDEX('03 Suppliers'!$N$5:$N$34,MATCH($M39,'03 Suppliers'!$B$5:$B$34,0)),"Excl VAT")="Incl VAT",'01 Control'!$C$6,0))/($N39*IFERROR(VLOOKUP($O39,'02 Lists'!$A$5:$B$18,2,FALSE()),1))) | X39: =IF(OR($V39="",$T39="",$T39=0),"",$V39/(1+IF(IFERROR(INDEX('03 Suppliers'!$N$5:$N$34,MATCH($S39,'03 Suppliers'!$B$5:$B$34,0)),"Excl VAT")="Incl VAT",'01 Control'!$C$6,0))/($T39*IFERROR(VLOOKUP($U39,'02 Lists'!$A$5:$B$18,2,FALSE()),1))) | AD39: =IF(OR($AB39="",$Z39="",$Z39=0),"",$AB39/(1+IF(IFERROR(INDEX('03 Suppliers'!$N$5:$N$34,MATCH($Y39,'03 Suppliers'!$B$5:$B$34,0)),"Excl VAT")="Incl VAT",'01 Control'!$C$6,0))/($Z39*IFERROR(VLOOKUP($AA39,'02 Lists'!$A$5:$B$18,2,FALSE()),1))) | AJ39: =IF(OR($AH39="",$AF39="",$AF39=0),"",$AH39/(1+IF(IFERROR(INDEX('03 Suppliers'!$N$5:$N$34,MATCH($AE39,'03 Suppliers'!$B$5:$B$34,0)),"Excl VAT")="Incl VAT",'01 Control'!$C$6,0))/($AF39*IFERROR(VLOOKUP($AG39,'02 Lists'!$A$5:$B$18,2,FALSE()),1))) | AK39: =IF(COUNT(L39,R39,X39,AD39,AJ39)=0,"",MIN(L39,R39,X39,AD39,AJ39)) | AL39: =IF($AK39="","",IF(L39=$AK39,$G39,IF(R39=$AK39,$M39,IF(X39=$AK39,$S39,IF(AD39=$AK39,$Y39,IF(AJ39=$AK39,$AE39,"")))))) | AM39: =IF($AK39="","",$AK39/IF($E39="",1,$E39)) | AN39: =COUNT(L39,R39,X39,AD39,AJ39) | AO39: =IF(COUNT(L39,R39,X39,AD39,AJ39)=0,"",MAX(L39,R39,X39,AD39,AJ39)) | AP39: =IF(OR($AK39="",$AO39="",$AO39=0),"",($AO39-$AK39)/$AO39) | AQ39: =IF($AK39="","",IF(L39=$AK39,$K39,IF(R39=$AK39,$Q39,IF(X39=$AK39,$W39,IF(AD39=$AK39,$AC39,IF(AJ39=$AK39,$AI39,""))))))
A40: PP-CHEDDAR-MAT | B40: Cheese | C40: Mature cheddar | D40: g | E40: 1 | F40: Quattro Formaggi | L40: =IF(OR($J40="",$H40="",$H40=0),"",$J40/(1+IF(IFERROR(INDEX('03 Suppliers'!$N$5:$N$34,MATCH($G40,'03 Suppliers'!$B$5:$B$34,0)),"Excl VAT")="Incl VAT",'01 Control'!$C$6,0))/($H40*IFERROR(VLOOKUP($I40,'02 Lists'!$A$5:$B$18,2,FALSE()),1))) | R40: =IF(OR($P40="",$N40="",$N40=0),"",$P40/(1+IF(IFERROR(INDEX('03 Suppliers'!$N$5:$N$34,MATCH($M40,'03 Suppliers'!$B$5:$B$34,0)),"Excl VAT")="Incl VAT",'01 Control'!$C$6,0))/($N40*IFERROR(VLOOKUP($O40,'02 Lists'!$A$5:$B$18,2,FALSE()),1))) | X40: =IF(OR($V40="",$T40="",$T40=0),"",$V40/(1+IF(IFERROR(INDEX('03 Suppliers'!$N$5:$N$34,MATCH($S40,'03 Suppliers'!$B$5:$B$34,0)),"Excl VAT")="Incl VAT",'01 Control'!$C$6,0))/($T40*IFERROR(VLOOKUP($U40,'02 Lists'!$A$5:$B$18,2,FALSE()),1))) | AD40: =IF(OR($AB40="",$Z40="",$Z40=0),"",$AB40/(1+IF(IFERROR(INDEX('03 Suppliers'!$N$5:$N$34,MATCH($Y40,'03 Suppliers'!$B$5:$B$34,0)),"Excl VAT")="Incl VAT",'01 Control'!$C$6,0))/($Z40*IFERROR(VLOOKUP($AA40,'02 Lists'!$A$5:$B$18,2,FALSE()),1))) | AJ40: =IF(OR($AH40="",$AF40="",$AF40=0),"",$AH40/(1+IF(IFERROR(INDEX('03 Suppliers'!$N$5:$N$34,MATCH($AE40,'03 Suppliers'!$B$5:$B$34,0)),"Excl VAT")="Incl VAT",'01 Control'!$C$6,0))/($AF40*IFERROR(VLOOKUP($AG40,'02 Lists'!$A$5:$B$18,2,FALSE()),1))) | AK40: =IF(COUNT(L40,R40,X40,AD40,AJ40)=0,"",MIN(L40,R40,X40,AD40,AJ40)) | AL40: =IF($AK40="","",IF(L40=$AK40,$G40,IF(R40=$AK40,$M40,IF(X40=$AK40,$S40,IF(AD40=$AK40,$Y40,IF(AJ40=$AK40,$AE40,"")))))) | AM40: =IF($AK40="","",$AK40/IF($E40="",1,$E40)) | AN40: =COUNT(L40,R40,X40,AD40,AJ40) | AO40: =IF(COUNT(L40,R40,X40,AD40,AJ40)=0,"",MAX(L40,R40,X40,AD40,AJ40)) | AP40: =IF(OR($AK40="",$AO40="",$AO40=0),"",($AO40-$AK40)/$AO40) | AQ40: =IF($AK40="","",IF(L40=$AK40,$K40,IF(R40=$AK40,$Q40,IF(X40=$AK40,$W40,IF(AD40=$AK40,$AC40,IF(AJ40=$AK40,$AI40,""))))))
A41: PP-BLUE | B41: Cheese | C41: Gorgonzola / blue cheese | D41: g | E41: 1 | F41: Dialled subtle or omitted | L41: =IF(OR($J41="",$H41="",$H41=0),"",$J41/(1+IF(IFERROR(INDEX('03 Suppliers'!$N$5:$N$34,MATCH($G41,'03 Suppliers'!$B$5:$B$34,0)),"Excl VAT")="Incl VAT",'01 Control'!$C$6,0))/($H41*IFERROR(VLOOKUP($I41,'02 Lists'!$A$5:$B$18,2,FALSE()),1))) | R41: =IF(OR($P41="",$N41="",$N41=0),"",$P41/(1+IF(IFERROR(INDEX('03 Suppliers'!$N$5:$N$34,MATCH($M41,'03 Suppliers'!$B$5:$B$34,0)),"Excl VAT")="Incl VAT",'01 Control'!$C$6,0))/($N41*IFERROR(VLOOKUP($O41,'02 Lists'!$A$5:$B$18,2,FALSE()),1))) | X41: =IF(OR($V41="",$T41="",$T41=0),"",$V41/(1+IF(IFERROR(INDEX('03 Suppliers'!$N$5:$N$34,MATCH($S41,'03 Suppliers'!$B$5:$B$34,0)),"Excl VAT")="Incl VAT",'01 Control'!$C$6,0))/($T41*IFERROR(VLOOKUP($U41,'02 Lists'!$A$5:$B$18,2,FALSE()),1))) | AD41: =IF(OR($AB41="",$Z41="",$Z41=0),"",$AB41/(1+IF(IFERROR(INDEX('03 Suppliers'!$N$5:$N$34,MATCH($Y41,'03 Suppliers'!$B$5:$B$34,0)),"Excl VAT")="Incl VAT",'01 Control'!$C$6,0))/($Z41*IFERROR(VLOOKUP($AA41,'02 Lists'!$A$5:$B$18,2,FALSE()),1))) | AJ41: =IF(OR($AH41="",$AF41="",$AF41=0),"",$AH41/(1+IF(IFERROR(INDEX('03 Suppliers'!$N$5:$N$34,MATCH($AE41,'03 Suppliers'!$B$5:$B$34,0)),"Excl VAT")="Incl VAT",'01 Control'!$C$6,0))/($AF41*IFERROR(VLOOKUP($AG41,'02 Lists'!$A$5:$B$18,2,FALSE()),1))) | AK41: =IF(COUNT(L41,R41,X41,AD41,AJ41)=0,"",MIN(L41,R41,X41,AD41,AJ41)) | AL41: =IF($AK41="","",IF(L41=$AK41,$G41,IF(R41=$AK41,$M41,IF(X41=$AK41,$S41,IF(AD41=$AK41,$Y41,IF(AJ41=$AK41,$AE41,"")))))) | AM41: =IF($AK41="","",$AK41/IF($E41="",1,$E41)) | AN41: =COUNT(L41,R41,X41,AD41,AJ41) | AO41: =IF(COUNT(L41,R41,X41,AD41,AJ41)=0,"",MAX(L41,R41,X41,AD41,AJ41)) | AP41: =IF(OR($AK41="",$AO41="",$AO41=0),"",($AO41-$AK41)/$AO41) | AQ41: =IF($AK41="","",IF(L41=$AK41,$K41,IF(R41=$AK41,$Q41,IF(X41=$AK41,$W41,IF(AD41=$AK41,$AC41,IF(AJ41=$AK41,$AI41,""))))))
A42: PP-RICOTTA | B42: Cheese | C42: Ricotta | D42: g | E42: 1 | F42: Year 3 spring seasonal | L42: =IF(OR($J42="",$H42="",$H42=0),"",$J42/(1+IF(IFERROR(INDEX('03 Suppliers'!$N$5:$N$34,MATCH($G42,'03 Suppliers'!$B$5:$B$34,0)),"Excl VAT")="Incl VAT",'01 Control'!$C$6,0))/($H42*IFERROR(VLOOKUP($I42,'02 Lists'!$A$5:$B$18,2,FALSE()),1))) | R42: =IF(OR($P42="",$N42="",$N42=0),"",$P42/(1+IF(IFERROR(INDEX('03 Suppliers'!$N$5:$N$34,MATCH($M42,'03 Suppliers'!$B$5:$B$34,0)),"Excl VAT")="Incl VAT",'01 Control'!$C$6,0))/($N42*IFERROR(VLOOKUP($O42,'02 Lists'!$A$5:$B$18,2,FALSE()),1))) | X42: =IF(OR($V42="",$T42="",$T42=0),"",$V42/(1+IF(IFERROR(INDEX('03 Suppliers'!$N$5:$N$34,MATCH($S42,'03 Suppliers'!$B$5:$B$34,0)),"Excl VAT")="Incl VAT",'01 Control'!$C$6,0))/($T42*IFERROR(VLOOKUP($U42,'02 Lists'!$A$5:$B$18,2,FALSE()),1))) | AD42: =IF(OR($AB42="",$Z42="",$Z42=0),"",$AB42/(1+IF(IFERROR(INDEX('03 Suppliers'!$N$5:$N$34,MATCH($Y42,'03 Suppliers'!$B$5:$B$34,0)),"Excl VAT")="Incl VAT",'01 Control'!$C$6,0))/($Z42*IFERROR(VLOOKUP($AA42,'02 Lists'!$A$5:$B$18,2,FALSE()),1))) | AJ42: =IF(OR($AH42="",$AF42="",$AF42=0),"",$AH42/(1+IF(IFERROR(INDEX('03 Suppliers'!$N$5:$N$34,MATCH($AE42,'03 Suppliers'!$B$5:$B$34,0)),"Excl VAT")="Incl VAT",'01 Control'!$C$6,0))/($AF42*IFERROR(VLOOKUP($AG42,'02 Lists'!$A$5:$B$18,2,FALSE()),1))) | AK42: =IF(COUNT(L42,R42,X42,AD42,AJ42)=0,"",MIN(L42,R42,X42,AD42,AJ42)) | AL42: =IF($AK42="","",IF(L42=$AK42,$G42,IF(R42=$AK42,$M42,IF(X42=$AK42,$S42,IF(AD42=$AK42,$Y42,IF(AJ42=$AK42,$AE42,"")))))) | AM42: =IF($AK42="","",$AK42/IF($E42="",1,$E42)) | AN42: =COUNT(L42,R42,X42,AD42,AJ42) | AO42: =IF(COUNT(L42,R42,X42,AD42,AJ42)=0,"",MAX(L42,R42,X42,AD42,AJ42)) | AP42: =IF(OR($AK42="",$AO42="",$AO42=0),"",($AO42-$AK42)/$AO42) | AQ42: =IF($AK42="","",IF(L42=$AK42,$K42,IF(R42=$AK42,$Q42,IF(X42=$AK42,$W42,IF(AD42=$AK42,$AC42,IF(AJ42=$AK42,$AI42,""))))))
A43: PP-EGG-YOLK-PAST | B43: Dairy | C43: Pasteurised egg yolk | D43: g | E43: 1 | F43: Carbonara base - food-safety critical | L43: =IF(OR($J43="",$H43="",$H43=0),"",$J43/(1+IF(IFERROR(INDEX('03 Suppliers'!$N$5:$N$34,MATCH($G43,'03 Suppliers'!$B$5:$B$34,0)),"Excl VAT")="Incl VAT",'01 Control'!$C$6,0))/($H43*IFERROR(VLOOKUP($I43,'02 Lists'!$A$5:$B$18,2,FALSE()),1))) | R43: =IF(OR($P43="",$N43="",$N43=0),"",$P43/(1+IF(IFERROR(INDEX('03 Suppliers'!$N$5:$N$34,MATCH($M43,'03 Suppliers'!$B$5:$B$34,0)),"Excl VAT")="Incl VAT",'01 Control'!$C$6,0))/($N43*IFERROR(VLOOKUP($O43,'02 Lists'!$A$5:$B$18,2,FALSE()),1))) | X43: =IF(OR($V43="",$T43="",$T43=0),"",$V43/(1+IF(IFERROR(INDEX('03 Suppliers'!$N$5:$N$34,MATCH($S43,'03 Suppliers'!$B$5:$B$34,0)),"Excl VAT")="Incl VAT",'01 Control'!$C$6,0))/($T43*IFERROR(VLOOKUP($U43,'02 Lists'!$A$5:$B$18,2,FALSE()),1))) | AD43: =IF(OR($AB43="",$Z43="",$Z43=0),"",$AB43/(1+IF(IFERROR(INDEX('03 Suppliers'!$N$5:$N$34,MATCH($Y43,'03 Suppliers'!$B$5:$B$34,0)),"Excl VAT")="Incl VAT",'01 Control'!$C$6,0))/($Z43*IFERROR(VLOOKUP($AA43,'02 Lists'!$A$5:$B$18,2,FALSE()),1))) | AJ43: =IF(OR($AH43="",$AF43="",$AF43=0),"",$AH43/(1+IF(IFERROR(INDEX('03 Suppliers'!$N$5:$N$34,MATCH($AE43,'03 Suppliers'!$B$5:$B$34,0)),"Excl VAT")="Incl VAT",'01 Control'!$C$6,0))/($AF43*IFERROR(VLOOKUP($AG43,'02 Lists'!$A$5:$B$18,2,FALSE()),1))) | AK43: =IF(COUNT(L43,R43,X43,AD43,AJ43)=0,"",MIN(L43,R43,X43,AD43,AJ43)) | AL43: =IF($AK43="","",IF(L43=$AK43,$G43,IF(R43=$AK43,$M43,IF(X43=$AK43,$S43,IF(AD43=$AK43,$Y43,IF(AJ43=$AK43,$AE43,"")))))) | AM43: =IF($AK43="","",$AK43/IF($E43="",1,$E43)) | AN43: =COUNT(L43,R43,X43,AD43,AJ43) | AO43: =IF(COUNT(L43,R43,X43,AD43,AJ43)=0,"",MAX(L43,R43,X43,AD43,AJ43)) | AP43: =IF(OR($AK43="",$AO43="",$AO43=0),"",($AO43-$AK43)/$AO43) | AQ43: =IF($AK43="","",IF(L43=$AK43,$K43,IF(R43=$AK43,$Q43,IF(X43=$AK43,$W43,IF(AD43=$AK43,$AC43,IF(AJ43=$AK43,$AI43,""))))))
A44: PP-BEEF-MINCE | B44: Beef | C44: Beef mince (halaal) | D44: g | E44: 0.85 | F44: Cooking loss on braise; confirm on prep test | L44: =IF(OR($J44="",$H44="",$H44=0),"",$J44/(1+IF(IFERROR(INDEX('03 Suppliers'!$N$5:$N$34,MATCH($G44,'03 Suppliers'!$B$5:$B$34,0)),"Excl VAT")="Incl VAT",'01 Control'!$C$6,0))/($H44*IFERROR(VLOOKUP($I44,'02 Lists'!$A$5:$B$18,2,FALSE()),1))) | R44: =IF(OR($P44="",$N44="",$N44=0),"",$P44/(1+IF(IFERROR(INDEX('03 Suppliers'!$N$5:$N$34,MATCH($M44,'03 Suppliers'!$B$5:$B$34,0)),"Excl VAT")="Incl VAT",'01 Control'!$C$6,0))/($N44*IFERROR(VLOOKUP($O44,'02 Lists'!$A$5:$B$18,2,FALSE()),1))) | X44: =IF(OR($V44="",$T44="",$T44=0),"",$V44/(1+IF(IFERROR(INDEX('03 Suppliers'!$N$5:$N$34,MATCH($S44,'03 Suppliers'!$B$5:$B$34,0)),"Excl VAT")="Incl VAT",'01 Control'!$C$6,0))/($T44*IFERROR(VLOOKUP($U44,'02 Lists'!$A$5:$B$18,2,FALSE()),1))) | AD44: =IF(OR($AB44="",$Z44="",$Z44=0),"",$AB44/(1+IF(IFERROR(INDEX('03 Suppliers'!$N$5:$N$34,MATCH($Y44,'03 Suppliers'!$B$5:$B$34,0)),"Excl VAT")="Incl VAT",'01 Control'!$C$6,0))/($Z44*IFERROR(VLOOKUP($AA44,'02 Lists'!$A$5:$B$18,2,FALSE()),1))) | AJ44: =IF(OR($AH44="",$AF44="",$AF44=0),"",$AH44/(1+IF(IFERROR(INDEX('03 Suppliers'!$N$5:$N$34,MATCH($AE44,'03 Suppliers'!$B$5:$B$34,0)),"Excl VAT")="Incl VAT",'01 Control'!$C$6,0))/($AF44*IFERROR(VLOOKUP($AG44,'02 Lists'!$A$5:$B$18,2,FALSE()),1))) | AK44: =IF(COUNT(L44,R44,X44,AD44,AJ44)=0,"",MIN(L44,R44,X44,AD44,AJ44)) | AL44: =IF($AK44="","",IF(L44=$AK44,$G44,IF(R44=$AK44,$M44,IF(X44=$AK44,$S44,IF(AD44=$AK44,$Y44,IF(AJ44=$AK44,$AE44,"")))))) | AM44: =IF($AK44="","",$AK44/IF($E44="",1,$E44)) | AN44: =COUNT(L44,R44,X44,AD44,AJ44) | AO44: =IF(COUNT(L44,R44,X44,AD44,AJ44)=0,"",MAX(L44,R44,X44,AD44,AJ44)) | AP44: =IF(OR($AK44="",$AO44="",$AO44=0),"",($AO44-$AK44)/$AO44) | AQ44: =IF($AK44="","",IF(L44=$AK44,$K44,IF(R44=$AK44,$Q44,IF(X44=$AK44,$W44,IF(AD44=$AK44,$AC44,IF(AJ44=$AK44,$AI44,""))))))
A45: PP-BEEF-CHUNK | B45: Beef | C45: Beef chunks / cubes (halaal) | D45: g | E45: 0.85 | F45: Ragu texture layer | L45: =IF(OR($J45="",$H45="",$H45=0),"",$J45/(1+IF(IFERROR(INDEX('03 Suppliers'!$N$5:$N$34,MATCH($G45,'03 Suppliers'!$B$5:$B$34,0)),"Excl VAT")="Incl VAT",'01 Control'!$C$6,0))/($H45*IFERROR(VLOOKUP($I45,'02 Lists'!$A$5:$B$18,2,FALSE()),1))) | R45: =IF(OR($P45="",$N45="",$N45=0),"",$P45/(1+IF(IFERROR(INDEX('03 Suppliers'!$N$5:$N$34,MATCH($M45,'03 Suppliers'!$B$5:$B$34,0)),"Excl VAT")="Incl VAT",'01 Control'!$C$6,0))/($N45*IFERROR(VLOOKUP($O45,'02 Lists'!$A$5:$B$18,2,FALSE()),1))) | X45: =IF(OR($V45="",$T45="",$T45=0),"",$V45/(1+IF(IFERROR(INDEX('03 Suppliers'!$N$5:$N$34,MATCH($S45,'03 Suppliers'!$B$5:$B$34,0)),"Excl VAT")="Incl VAT",'01 Control'!$C$6,0))/($T45*IFERROR(VLOOKUP($U45,'02 Lists'!$A$5:$B$18,2,FALSE()),1))) | AD45: =IF(OR($AB45="",$Z45="",$Z45=0),"",$AB45/(1+IF(IFERROR(INDEX('03 Suppliers'!$N$5:$N$34,MATCH($Y45,'03 Suppliers'!$B$5:$B$34,0)),"Excl VAT")="Incl VAT",'01 Control'!$C$6,0))/($Z45*IFERROR(VLOOKUP($AA45,'02 Lists'!$A$5:$B$18,2,FALSE()),1))) | AJ45: =IF(OR($AH45="",$AF45="",$AF45=0),"",$AH45/(1+IF(IFERROR(INDEX('03 Suppliers'!$N$5:$N$34,MATCH($AE45,'03 Suppliers'!$B$5:$B$34,0)),"Excl VAT")="Incl VAT",'01 Control'!$C$6,0))/($AF45*IFERROR(VLOOKUP($AG45,'02 Lists'!$A$5:$B$18,2,FALSE()),1))) | AK45: =IF(COUNT(L45,R45,X45,AD45,AJ45)=0,"",MIN(L45,R45,X45,AD45,AJ45)) | AL45: =IF($AK45="","",IF(L45=$AK45,$G45,IF(R45=$AK45,$M45,IF(X45=$AK45,$S45,IF(AD45=$AK45,$Y45,IF(AJ45=$AK45,$AE45,"")))))) | AM45: =IF($AK45="","",$AK45/IF($E45="",1,$E45)) | AN45: =COUNT(L45,R45,X45,AD45,AJ45) | AO45: =IF(COUNT(L45,R45,X45,AD45,AJ45)=0,"",MAX(L45,R45,X45,AD45,AJ45)) | AP45: =IF(OR($AK45="",$AO45="",$AO45=0),"",($AO45-$AK45)/$AO45) | AQ45: =IF($AK45="","",IF(L45=$AK45,$K45,IF(R45=$AK45,$Q45,IF(X45=$AK45,$W45,IF(AD45=$AK45,$AC45,IF(AJ45=$AK45,$AI45,""))))))
A46: PP-BEEF-SHRED | B46: Beef | C46: Shredded / pulled beef (halaal) | D46: g | E46: 0.8 | F46: Seasonal - BBQ pulled beef | L46: =IF(OR($J46="",$H46="",$H46=0),"",$J46/(1+IF(IFERROR(INDEX('03 Suppliers'!$N$5:$N$34,MATCH($G46,'03 Suppliers'!$B$5:$B$34,0)),"Excl VAT")="Incl VAT",'01 Control'!$C$6,0))/($H46*IFERROR(VLOOKUP($I46,'02 Lists'!$A$5:$B$18,2,FALSE()),1))) | R46: =IF(OR($P46="",$N46="",$N46=0),"",$P46/(1+IF(IFERROR(INDEX('03 Suppliers'!$N$5:$N$34,MATCH($M46,'03 Suppliers'!$B$5:$B$34,0)),"Excl VAT")="Incl VAT",'01 Control'!$C$6,0))/($N46*IFERROR(VLOOKUP($O46,'02 Lists'!$A$5:$B$18,2,FALSE()),1))) | X46: =IF(OR($V46="",$T46="",$T46=0),"",$V46/(1+IF(IFERROR(INDEX('03 Suppliers'!$N$5:$N$34,MATCH($S46,'03 Suppliers'!$B$5:$B$34,0)),"Excl VAT")="Incl VAT",'01 Control'!$C$6,0))/($T46*IFERROR(VLOOKUP($U46,'02 Lists'!$A$5:$B$18,2,FALSE()),1))) | AD46: =IF(OR($AB46="",$Z46="",$Z46=0),"",$AB46/(1+IF(IFERROR(INDEX('03 Suppliers'!$N$5:$N$34,MATCH($Y46,'03 Suppliers'!$B$5:$B$34,0)),"Excl VAT")="Incl VAT",'01 Control'!$C$6,0))/($Z46*IFERROR(VLOOKUP($AA46,'02 Lists'!$A$5:$B$18,2,FALSE()),1))) | AJ46: =IF(OR($AH46="",$AF46="",$AF46=0),"",$AH46/(1+IF(IFERROR(INDEX('03 Suppliers'!$N$5:$N$34,MATCH($AE46,'03 Suppliers'!$B$5:$B$34,0)),"Excl VAT")="Incl VAT",'01 Control'!$C$6,0))/($AF46*IFERROR(VLOOKUP($AG46,'02 Lists'!$A$5:$B$18,2,FALSE()),1))) | AK46: =IF(COUNT(L46,R46,X46,AD46,AJ46)=0,"",MIN(L46,R46,X46,AD46,AJ46)) | AL46: =IF($AK46="","",IF(L46=$AK46,$G46,IF(R46=$AK46,$M46,IF(X46=$AK46,$S46,IF(AD46=$AK46,$Y46,IF(AJ46=$AK46,$AE46,"")))))) | AM46: =IF($AK46="","",$AK46/IF($E46="",1,$E46)) | AN46: =COUNT(L46,R46,X46,AD46,AJ46) | AO46: =IF(COUNT(L46,R46,X46,AD46,AJ46)=0,"",MAX(L46,R46,X46,AD46,AJ46)) | AP46: =IF(OR($AK46="",$AO46="",$AO46=0),"",($AO46-$AK46)/$AO46) | AQ46: =IF($AK46="","",IF(L46=$AK46,$K46,IF(R46=$AK46,$Q46,IF(X46=$AK46,$W46,IF(AD46=$AK46,$AC46,IF(AJ46=$AK46,$AI46,""))))))
... A54: PP-ONION | B54: Vegetables | C54: Onion | D54: g | E54: 0.9 | F54: Soffritto base | L54: =IF(OR($J54="",$H54="",$H54=0),"",$J54/(1+IF(IFERROR(INDEX('03 Suppliers'!$N$5:$N$34,MATCH($G54,'03 Suppliers'!$B$5:$B$34,0)),"Excl VAT")="Incl VAT",'01 Control'!$C$6,0))/($H54*IFERROR(VLOOKUP($I54,'02 Lists'!$A$5:$B$18,2,FALSE()),1))) | R54: =IF(OR($P54="",$N54="",$N54=0),"",$P54/(1+IF(IFERROR(INDEX('03 Suppliers'!$N$5:$N$34,MATCH($M54,'03 Suppliers'!$B$5:$B$34,0)),"Excl VAT")="Incl VAT",'01 Control'!$C$6,0))/($N54*IFERROR(VLOOKUP($O54,'02 Lists'!$A$5:$B$18,2,FALSE()),1))) | X54: =IF(OR($V54="",$T54="",$T54=0),"",$V54/(1+IF(IFERROR(INDEX('03 Suppliers'!$N$5:$N$34,MATCH($S54,'03 Suppliers'!$B$5:$B$34,0)),"Excl VAT")="Incl VAT",'01 Control'!$C$6,0))/($T54*IFERROR(VLOOKUP($U54,'02 Lists'!$A$5:$B$18,2,FALSE()),1))) | AD54: =IF(OR($AB54="",$Z54="",$Z54=0),"",$AB54/(1+IF(IFERROR(INDEX('03 Suppliers'!$N$5:$N$34,MATCH($Y54,'03 Suppliers'!$B$5:$B$34,0)),"Excl VAT")="Incl VAT",'01 Control'!$C$6,0))/($Z54*IFERROR(VLOOKUP($AA54,'02 Lists'!$A$5:$B$18,2,FALSE()),1))) | AJ54: =IF(OR($AH54="",$AF54="",$AF54=0),"",$AH54/(1+IF(IFERROR(INDEX('03 Suppliers'!$N$5:$N$34,MATCH($AE54,'03 Suppliers'!$B$5:$B$34,0)),"Excl VAT")="Incl VAT",'01 Control'!$C$6,0))/($AF54*IFERROR(VLOOKUP($AG54,'02 Lists'!$A$5:$B$18,2,FALSE()),1))) | AK54: =IF(COUNT(L54,R54,X54,AD54,AJ54)=0,"",MIN(L54,R54,X54,AD54,AJ54)) | AL54: =IF($AK54="","",IF(L54=$AK54,$G54,IF(R54=$AK54,$M54,IF(X54=$AK54,$S54,IF(AD54=$AK54,$Y54,IF(AJ54=$AK54,$AE54,"")))))) | AM54: =IF($AK54="","",$AK54/IF($E54="",1,$E54)) | AN54: =COUNT(L54,R54,X54,AD54,AJ54) | AO54: =IF(COUNT(L54,R54,X54,AD54,AJ54)=0,"",MAX(L54,R54,X54,AD54,AJ54)) | AP54: =IF(OR($AK54="",$AO54="",$AO54=0),"",($AO54-$AK54)/$AO54) | AQ54: =IF($AK54="","",IF(L54=$AK54,$K54,IF(R54=$AK54,$Q54,IF(X54=$AK54,$W54,IF(AD54=$AK54,$AC54,IF(AJ54=$AK54,$AI54,""))))))
A55: PP-VEG-REDONION | B55: Vegetables | C55: Red onion | D55: g | E55: 0.9 | F55: Salad base | G55: Ferreira Fresh | H55: 1 | I55: kg | J55: 39.5 | K55: 46250 | L55: =IF(OR($J55="",$H55="",$H55=0),"",$J55/(1+IF(IFERROR(INDEX('03 Suppliers'!$N$5:$N$34,MATCH($G55,'03 Suppliers'!$B$5:$B$34,0)),"Excl VAT")="Incl VAT",'01 Control'!$C$6,0))/($H55*IFERROR(VLOOKUP($I55,'02 Lists'!$A$5:$B$18,2,FALSE()),1))) | R55: =IF(OR($P55="",$N55="",$N55=0),"",$P55/(1+IF(IFERROR(INDEX('03 Suppliers'!$N$5:$N$34,MATCH($M55,'03 Suppliers'!$B$5:$B$34,0)),"Excl VAT")="Incl VAT",'01 Control'!$C$6,0))/($N55*IFERROR(VLOOKUP($O55,'02 Lists'!$A$5:$B$18,2,FALSE()),1))) | X55: =IF(OR($V55="",$T55="",$T55=0),"",$V55/(1+IF(IFERROR(INDEX('03 Suppliers'!$N$5:$N$34,MATCH($S55,'03 Suppliers'!$B$5:$B$34,0)),"Excl VAT")="Incl VAT",'01 Control'!$C$6,0))/($T55*IFERROR(VLOOKUP($U55,'02 Lists'!$A$5:$B$18,2,FALSE()),1))) | AD55: =IF(OR($AB55="",$Z55="",$Z55=0),"",$AB55/(1+IF(IFERROR(INDEX('03 Suppliers'!$N$5:$N$34,MATCH($Y55,'03 Suppliers'!$B$5:$B$34,0)),"Excl VAT")="Incl VAT",'01 Control'!$C$6,0))/($Z55*IFERROR(VLOOKUP($AA55,'02 Lists'!$A$5:$B$18,2,FALSE()),1))) | AJ55: =IF(OR($AH55="",$AF55="",$AF55=0),"",$AH55/(1+IF(IFERROR(INDEX('03 Suppliers'!$N$5:$N$34,MATCH($AE55,'03 Suppliers'!$B$5:$B$34,0)),"Excl VAT")="Incl VAT",'01 Control'!$C$6,0))/($AF55*IFERROR(VLOOKUP($AG55,'02 Lists'!$A$5:$B$18,2,FALSE()),1))) | AK55: =IF(COUNT(L55,R55,X55,AD55,AJ55)=0,"",MIN(L55,R55,X55,AD55,AJ55)) | AL55: =IF($AK55="","",IF(L55=$AK55,$G55,IF(R55=$AK55,$M55,IF(X55=$AK55,$S55,IF(AD55=$AK55,$Y55,IF(AJ55=$AK55,$AE55,"")))))) | AM55: =IF($AK55="","",$AK55/IF($E55="",1,$E55)) | AN55: =COUNT(L55,R55,X55,AD55,AJ55) | AO55: =IF(COUNT(L55,R55,X55,AD55,AJ55)=0,"",MAX(L55,R55,X55,AD55,AJ55)) | AP55: =IF(OR($AK55="",$AO55="",$AO55=0),"",($AO55-$AK55)/$AO55) | AQ55: =IF($AK55="","",IF(L55=$AK55,$K55,IF(R55=$AK55,$Q55,IF(X55=$AK55,$W55,IF(AD55=$AK55,$AC55,IF(AJ55=$AK55,$AI55,""))))))
A56: PP-GARLIC | B56: Vegetables | C56: Garlic | D56: g | E56: 0.85 | F56: Every sauce | L56: =IF(OR($J56="",$H56="",$H56=0),"",$J56/(1+IF(IFERROR(INDEX('03 Suppliers'!$N$5:$N$34,MATCH($G56,'03 Suppliers'!$B$5:$B$34,0)),"Excl VAT")="Incl VAT",'01 Control'!$C$6,0))/($H56*IFERROR(VLOOKUP($I56,'02 Lists'!$A$5:$B$18,2,FALSE()),1))) | R56: =IF(OR($P56="",$N56="",$N56=0),"",$P56/(1+IF(IFERROR(INDEX('03 Suppliers'!$N$5:$N$34,MATCH($M56,'03 Suppliers'!$B$5:$B$34,0)),"Excl VAT")="Incl VAT",'01 Control'!$C$6,0))/($N56*IFERROR(VLOOKUP($O56,'02 Lists'!$A$5:$B$18,2,FALSE()),1))) | X56: =IF(OR($V56="",$T56="",$T56=0),"",$V56/(1+IF(IFERROR(INDEX('03 Suppliers'!$N$5:$N$34,MATCH($S56,'03 Suppliers'!$B$5:$B$34,0)),"Excl VAT")="Incl VAT",'01 Control'!$C$6,0))/($T56*IFERROR(VLOOKUP($U56,'02 Lists'!$A$5:$B$18,2,FALSE()),1))) | AD56: =IF(OR($AB56="",$Z56="",$Z56=0),"",$AB56/(1+IF(IFERROR(INDEX('03 Suppliers'!$N$5:$N$34,MATCH($Y56,'03 Suppliers'!$B$5:$B$34,0)),"Excl VAT")="Incl VAT",'01 Control'!$C$6,0))/($Z56*IFERROR(VLOOKUP($AA56,'02 Lists'!$A$5:$B$18,2,FALSE()),1))) | AJ56: =IF(OR($AH56="",$AF56="",$AF56=0),"",$AH56/(1+IF(IFERROR(INDEX('03 Suppliers'!$N$5:$N$34,MATCH($AE56,'03 Suppliers'!$B$5:$B$34,0)),"Excl VAT")="Incl VAT",'01 Control'!$C$6,0))/($AF56*IFERROR(VLOOKUP($AG56,'02 Lists'!$A$5:$B$18,2,FALSE()),1))) | AK56: =IF(COUNT(L56,R56,X56,AD56,AJ56)=0,"",MIN(L56,R56,X56,AD56,AJ56)) | AL56: =IF($AK56="","",IF(L56=$AK56,$G56,IF(R56=$AK56,$M56,IF(X56=$AK56,$S56,IF(AD56=$AK56,$Y56,IF(AJ56=$AK56,$AE56,"")))))) | AM56: =IF($AK56="","",$AK56/IF($E56="",1,$E56)) | AN56: =COUNT(L56,R56,X56,AD56,AJ56) | AO56: =IF(COUNT(L56,R56,X56,AD56,AJ56)=0,"",MAX(L56,R56,X56,AD56,AJ56)) | AP56: =IF(OR($AK56="",$AO56="",$AO56=0),"",($AO56-$AK56)/$AO56) | AQ56: =IF($AK56="","",IF(L56=$AK56,$K56,IF(R56=$AK56,$Q56,IF(X56=$AK56,$W56,IF(AD56=$AK56,$AC56,IF(AJ56=$AK56,$AI56,""))))))
A57: PP-CELERY | B57: Vegetables | C57: Celery | D57: g | E57: 0.85 | F57: Soffritto base | L57: =IF(OR($J57="",$H57="",$H57=0),"",$J57/(1+IF(IFERROR(INDEX('03 Suppliers'!$N$5:$N$34,MATCH($G57,'03 Suppliers'!$B$5:$B$34,0)),"Excl VAT")="Incl VAT",'01 Control'!$C$6,0))/($H57*IFERROR(VLOOKUP($I57,'02 Lists'!$A$5:$B$18,2,FALSE()),1))) | R57: =IF(OR($P57="",$N57="",$N57=0),"",$P57/(1+IF(IFERROR(INDEX('03 Suppliers'!$N$5:$N$34,MATCH($M57,'03 Suppliers'!$B$5:$B$34,0)),"Excl VAT")="Incl VAT",'01 Control'!$C$6,0))/($N57*IFERROR(VLOOKUP($O57,'02 Lists'!$A$5:$B$18,2,FALSE()),1))) | X57: =IF(OR($V57="",$T57="",$T57=0),"",$V57/(1+IF(IFERROR(INDEX('03 Suppliers'!$N$5:$N$34,MATCH($S57,'03 Suppliers'!$B$5:$B$34,0)),"Excl VAT")="Incl VAT",'01 Control'!$C$6,0))/($T57*IFERROR(VLOOKUP($U57,'02 Lists'!$A$5:$B$18,2,FALSE()),1))) | AD57: =IF(OR($AB57="",$Z57="",$Z57=0),"",$AB57/(1+IF(IFERROR(INDEX('03 Suppliers'!$N$5:$N$34,MATCH($Y57,'03 Suppliers'!$B$5:$B$34,0)),"Excl VAT")="Incl VAT",'01 Control'!$C$6,0))/($Z57*IFERROR(VLOOKUP($AA57,'02 Lists'!$A$5:$B$18,2,FALSE()),1))) | AJ57: =IF(OR($AH57="",$AF57="",$AF57=0),"",$AH57/(1+IF(IFERROR(INDEX('03 Suppliers'!$N$5:$N$34,MATCH($AE57,'03 Suppliers'!$B$5:$B$34,0)),"Excl VAT")="Incl VAT",'01 Control'!$C$6,0))/($AF57*IFERROR(VLOOKUP($AG57,'02 Lists'!$A$5:$B$18,2,FALSE()),1))) | AK57: =IF(COUNT(L57,R57,X57,AD57,AJ57)=0,"",MIN(L57,R57,X57,AD57,AJ57)) | AL57: =IF($AK57="","",IF(L57=$AK57,$G57,IF(R57=$AK57,$M57,IF(X57=$AK57,$S57,IF(AD57=$AK57,$Y57,IF(AJ57=$AK57,$AE57,"")))))) | AM57: =IF($AK57="","",$AK57/IF($E57="",1,$E57)) | AN57: =COUNT(L57,R57,X57,AD57,AJ57) | AO57: =IF(COUNT(L57,R57,X57,AD57,AJ57)=0,"",MAX(L57,R57,X57,AD57,AJ57)) | AP57: =IF(OR($AK57="",$AO57="",$AO57=0),"",($AO57-$AK57)/$AO57) | AQ57: =IF($AK57="","",IF(L57=$AK57,$K57,IF(R57=$AK57,$Q57,IF(X57=$AK57,$W57,IF(AD57=$AK57,$AC57,IF(AJ57=$AK57,$AI57,""))))))
A58: PP-VEG-CARROT | B58: Vegetables | C58: Carrots | D58: g | E58: 0.9 | F58: Soffritto base CHECK THE UNIT: the carried-over quote reads R148.00/kg, which is out of line with the rest of the list. Confirm per-kg vs pack price before this reaches a menu price. | G58: Ferreira Fresh | H58: 1 | I58: kg | J58: 148 | K58: 46251 | L58: =IF(OR($J58="",$H58="",$H58=0),"",$J58/(1+IF(IFERROR(INDEX('03 Suppliers'!$N$5:$N$34,MATCH($G58,'03 Suppliers'!$B$5:$B$34,0)),"Excl VAT")="Incl VAT",'01 Control'!$C$6,0))/($H58*IFERROR(VLOOKUP($I58,'02 Lists'!$A$5:$B$18,2,FALSE()),1))) | R58: =IF(OR($P58="",$N58="",$N58=0),"",$P58/(1+IF(IFERROR(INDEX('03 Suppliers'!$N$5:$N$34,MATCH($M58,'03 Suppliers'!$B$5:$B$34,0)),"Excl VAT")="Incl VAT",'01 Control'!$C$6,0))/($N58*IFERROR(VLOOKUP($O58,'02 Lists'!$A$5:$B$18,2,FALSE()),1))) | X58: =IF(OR($V58="",$T58="",$T58=0),"",$V58/(1+IF(IFERROR(INDEX('03 Suppliers'!$N$5:$N$34,MATCH($S58,'03 Suppliers'!$B$5:$B$34,0)),"Excl VAT")="Incl VAT",'01 Control'!$C$6,0))/($T58*IFERROR(VLOOKUP($U58,'02 Lists'!$A$5:$B$18,2,FALSE()),1))) | AD58: =IF(OR($AB58="",$Z58="",$Z58=0),"",$AB58/(1+IF(IFERROR(INDEX('03 Suppliers'!$N$5:$N$34,MATCH($Y58,'03 Suppliers'!$B$5:$B$34,0)),"Excl VAT")="Incl VAT",'01 Control'!$C$6,0))/($Z58*IFERROR(VLOOKUP($AA58,'02 Lists'!$A$5:$B$18,2,FALSE()),1))) | AJ58: =IF(OR($AH58="",$AF58="",$AF58=0),"",$AH58/(1+IF(IFERROR(INDEX('03 Suppliers'!$N$5:$N$34,MATCH($AE58,'03 Suppliers'!$B$5:$B$34,0)),"Excl VAT")="Incl VAT",'01 Control'!$C$6,0))/($AF58*IFERROR(VLOOKUP($AG58,'02 Lists'!$A$5:$B$18,2,FALSE()),1))) | AK58: =IF(COUNT(L58,R58,X58,AD58,AJ58)=0,"",MIN(L58,R58,X58,AD58,AJ58)) | AL58: =IF($AK58="","",IF(L58=$AK58,$G58,IF(R58=$AK58,$M58,IF(X58=$AK58,$S58,IF(AD58=$AK58,$Y58,IF(AJ58=$AK58,$AE58,"")))))) | AM58: =IF($AK58="","",$AK58/IF($E58="",1,$E58)) | AN58: =COUNT(L58,R58,X58,AD58,AJ58) | AO58: =IF(COUNT(L58,R58,X58,AD58,AJ58)=0,"",MAX(L58,R58,X58,AD58,AJ58)) | AP58: =IF(OR($AK58="",$AO58="",$AO58=0),"",($AO58-$AK58)/$AO58) | AQ58: =IF($AK58="","",IF(L58=$AK58,$K58,IF(R58=$AK58,$Q58,IF(X58=$AK58,$W58,IF(AD58=$AK58,$AC58,IF(AJ58=$AK58,$AI58,""))))))
A59: PP-VEG-MUSH | B59: Vegetables | C59: Mushrooms (brown / button) | D59: g | E59: 0.95 | F59: Boscaiola | L59: =IF(OR($J59="",$H59="",$H59=0),"",$J59/(1+IF(IFERROR(INDEX('03 Suppliers'!$N$5:$N$34,MATCH($G59,'03 Suppliers'!$B$5:$B$34,0)),"Excl VAT")="Incl VAT",'01 Control'!$C$6,0))/($H59*IFERROR(VLOOKUP($I59,'02 Lists'!$A$5:$B$18,2,FALSE()),1))) | R59: =IF(OR($P59="",$N59="",$N59=0),"",$P59/(1+IF(IFERROR(INDEX('03 Suppliers'!$N$5:$N$34,MATCH($M59,'03 Suppliers'!$B$5:$B$34,0)),"Excl VAT")="Incl VAT",'01 Control'!$C$6,0))/($N59*IFERROR(VLOOKUP($O59,'02 Lists'!$A$5:$B$18,2,FALSE()),1))) | X59: =IF(OR($V59="",$T59="",$T59=0),"",$V59/(1+IF(IFERROR(INDEX('03 Suppliers'!$N$5:$N$34,MATCH($S59,'03 Suppliers'!$B$5:$B$34,0)),"Excl VAT")="Incl VAT",'01 Control'!$C$6,0))/($T59*IFERROR(VLOOKUP($U59,'02 Lists'!$A$5:$B$18,2,FALSE()),1))) | AD59: =IF(OR($AB59="",$Z59="",$Z59=0),"",$AB59/(1+IF(IFERROR(INDEX('03 Suppliers'!$N$5:$N$34,MATCH($Y59,'03 Suppliers'!$B$5:$B$34,0)),"Excl VAT")="Incl VAT",'01 Control'!$C$6,0))/($Z59*IFERROR(VLOOKUP($AA59,'02 Lists'!$A$5:$B$18,2,FALSE()),1))) | AJ59: =IF(OR($AH59="",$AF59="",$AF59=0),"",$AH59/(1+IF(IFERROR(INDEX('03 Suppliers'!$N$5:$N$34,MATCH($AE59,'03 Suppliers'!$B$5:$B$34,0)),"Excl VAT")="Incl VAT",'01 Control'!$C$6,0))/($AF59*IFERROR(VLOOKUP($AG59,'02 Lists'!$A$5:$B$18,2,FALSE()),1))) | AK59: =IF(COUNT(L59,R59,X59,AD59,AJ59)=0,"",MIN(L59,R59,X59,AD59,AJ59)) | AL59: =IF($AK59="","",IF(L59=$AK59,$G59,IF(R59=$AK59,$M59,IF(X59=$AK59,$S59,IF(AD59=$AK59,$Y59,IF(AJ59=$AK59,$AE59,"")))))) | AM59: =IF($AK59="","",$AK59/IF($E59="",1,$E59)) | AN59: =COUNT(L59,R59,X59,AD59,AJ59) | AO59: =IF(COUNT(L59,R59,X59,AD59,AJ59)=0,"",MAX(L59,R59,X59,AD59,AJ59)) | AP59: =IF(OR($AK59="",$AO59="",$AO59=0),"",($AO59-$AK59)/$AO59) | AQ59: =IF($AK59="","",IF(L59=$AK59,$K59,IF(R59=$AK59,$Q59,IF(X59=$AK59,$W59,IF(AD59=$AK59,$AC59,IF(AJ59=$AK59,$AI59,""))))))
A60: PP-VEG-SPINACH | B60: Vegetables | C60: Baby spinach | D60: g | E60: 0.9 | G60: Ferreira Fresh | H60: 1 | I60: kg | J60: 129.5 | K60: 46251 | L60: =IF(OR($J60="",$H60="",$H60=0),"",$J60/(1+IF(IFERROR(INDEX('03 Suppliers'!$N$5:$N$34,MATCH($G60,'03 Suppliers'!$B$5:$B$34,0)),"Excl VAT")="Incl VAT",'01 Control'!$C$6,0))/($H60*IFERROR(VLOOKUP($I60,'02 Lists'!$A$5:$B$18,2,FALSE()),1))) | R60: =IF(OR($P60="",$N60="",$N60=0),"",$P60/(1+IF(IFERROR(INDEX('03 Suppliers'!$N$5:$N$34,MATCH($M60,'03 Suppliers'!$B$5:$B$34,0)),"Excl VAT")="Incl VAT",'01 Control'!$C$6,0))/($N60*IFERROR(VLOOKUP($O60,'02 Lists'!$A$5:$B$18,2,FALSE()),1))) | X60: =IF(OR($V60="",$T60="",$T60=0),"",$V60/(1+IF(IFERROR(INDEX('03 Suppliers'!$N$5:$N$34,MATCH($S60,'03 Suppliers'!$B$5:$B$34,0)),"Excl VAT")="Incl VAT",'01 Control'!$C$6,0))/($T60*IFERROR(VLOOKUP($U60,'02 Lists'!$A$5:$B$18,2,FALSE()),1))) | AD60: =IF(OR($AB60="",$Z60="",$Z60=0),"",$AB60/(1+IF(IFERROR(INDEX('03 Suppliers'!$N$5:$N$34,MATCH($Y60,'03 Suppliers'!$B$5:$B$34,0)),"Excl VAT")="Incl VAT",'01 Control'!$C$6,0))/($Z60*IFERROR(VLOOKUP($AA60,'02 Lists'!$A$5:$B$18,2,FALSE()),1))) | AJ60: =IF(OR($AH60="",$AF60="",$AF60=0),"",$AH60/(1+IF(IFERROR(INDEX('03 Suppliers'!$N$5:$N$34,MATCH($AE60,'03 Suppliers'!$B$5:$B$34,0)),"Excl VAT")="Incl VAT",'01 Control'!$C$6,0))/($AF60*IFERROR(VLOOKUP($AG60,'02 Lists'!$A$5:$B$18,2,FALSE()),1))) | AK60: =IF(COUNT(L60,R60,X60,AD60,AJ60)=0,"",MIN(L60,R60,X60,AD60,AJ60)) | AL60: =IF($AK60="","",IF(L60=$AK60,$G60,IF(R60=$AK60,$M60,IF(X60=$AK60,$S60,IF(AD60=$AK60,$Y60,IF(AJ60=$AK60,$AE60,"")))))) | AM60: =IF($AK60="","",$AK60/IF($E60="",1,$E60)) | AN60: =COUNT(L60,R60,X60,AD60,AJ60) | AO60: =IF(COUNT(L60,R60,X60,AD60,AJ60)=0,"",MAX(L60,R60,X60,AD60,AJ60)) | AP60: =IF(OR($AK60="",$AO60="",$AO60=0),"",($AO60-$AK60)/$AO60) | AQ60: =IF($AK60="","",IF(L60=$AK60,$K60,IF(R60=$AK60,$Q60,IF(X60=$AK60,$W60,IF(AD60=$AK60,$AC60,IF(AJ60=$AK60,$AI60,""))))))
A61: PP-VEG-BROCC | B61: Vegetables | C61: Broccoli | D61: g | E61: 0.8 | G61: Ferreira Fresh | H61: 1 | I61: kg | J61: 79.9 | K61: 46251 | L61: =IF(OR($J61="",$H61="",$H61=0),"",$J61/(1+IF(IFERROR(INDEX('03 Suppliers'!$N$5:$N$34,MATCH($G61,'03 Suppliers'!$B$5:$B$34,0)),"Excl VAT")="Incl VAT",'01 Control'!$C$6,0))/($H61*IFERROR(VLOOKUP($I61,'02 Lists'!$A$5:$B$18,2,FALSE()),1))) | R61: =IF(OR($P61="",$N61="",$N61=0),"",$P61/(1+IF(IFERROR(INDEX('03 Suppliers'!$N$5:$N$34,MATCH($M61,'03 Suppliers'!$B$5:$B$34,0)),"Excl VAT")="Incl VAT",'01 Control'!$C$6,0))/($N61*IFERROR(VLOOKUP($O61,'02 Lists'!$A$5:$B$18,2,FALSE()),1))) | X61: =IF(OR($V61="",$T61="",$T61=0),"",$V61/(1+IF(IFERROR(INDEX('03 Suppliers'!$N$5:$N$34,MATCH($S61,'03 Suppliers'!$B$5:$B$34,0)),"Excl VAT")="Incl VAT",'01 Control'!$C$6,0))/($T61*IFERROR(VLOOKUP($U61,'02 Lists'!$A$5:$B$18,2,FALSE()),1))) | AD61: =IF(OR($AB61="",$Z61="",$Z61=0),"",$AB61/(1+IF(IFERROR(INDEX('03 Suppliers'!$N$5:$N$34,MATCH($Y61,'03 Suppliers'!$B$5:$B$34,0)),"Excl VAT")="Incl VAT",'01 Control'!$C$6,0))/($Z61*IFERROR(VLOOKUP($AA61,'02 Lists'!$A$5:$B$18,2,FALSE()),1))) | AJ61: =IF(OR($AH61="",$AF61="",$AF61=0),"",$AH61/(1+IF(IFERROR(INDEX('03 Suppliers'!$N$5:$N$34,MATCH($AE61,'03 Suppliers'!$B$5:$B$34,0)),"Excl VAT")="Incl VAT",'01 Control'!$C$6,0))/($AF61*IFERROR(VLOOKUP($AG61,'02 Lists'!$A$5:$B$18,2,FALSE()),1))) | AK61: =IF(COUNT(L61,R61,X61,AD61,AJ61)=0,"",MIN(L61,R61,X61,AD61,AJ61)) | AL61: =IF($AK61="","",IF(L61=$AK61,$G61,IF(R61=$AK61,$M61,IF(X61=$AK61,$S61,IF(AD61=$AK61,$Y61,IF(AJ61=$AK61,$AE61,"")))))) | AM61: =IF($AK61="","",$AK61/IF($E61="",1,$E61)) | AN61: =COUNT(L61,R61,X61,AD61,AJ61) | AO61: =IF(COUNT(L61,R61,X61,AD61,AJ61)=0,"",MAX(L61,R61,X61,AD61,AJ61)) | AP61: =IF(OR($AK61="",$AO61="",$AO61=0),"",($AO61-$AK61)/$AO61) | AQ61: =IF($AK61="","",IF(L61=$AK61,$K61,IF(R61=$AK61,$Q61,IF(X61=$AK61,$W61,IF(AD61=$AK61,$AC61,IF(AJ61=$AK61,$AI61,""))))))
A62: PP-VEG-PEPPER | B62: Vegetables | C62: Bell peppers / mixed peppers | D62: g | E62: 0.85 | G62: Ferreira Fresh | H62: 1 | I62: kg | J62: 39.5 | K62: 46251 | L62: =IF(OR($J62="",$H62="",$H62=0),"",$J62/(1+IF(IFERROR(INDEX('03 Suppliers'!$N$5:$N$34,MATCH($G62,'03 Suppliers'!$B$5:$B$34,0)),"Excl VAT")="Incl VAT",'01 Control'!$C$6,0))/($H62*IFERROR(VLOOKUP($I62,'02 Lists'!$A$5:$B$18,2,FALSE()),1))) | R62: =IF(OR($P62="",$N62="",$N62=0),"",$P62/(1+IF(IFERROR(INDEX('03 Suppliers'!$N$5:$N$34,MATCH($M62,'03 Suppliers'!$B$5:$B$34,0)),"Excl VAT")="Incl VAT",'01 Control'!$C$6,0))/($N62*IFERROR(VLOOKUP($O62,'02 Lists'!$A$5:$B$18,2,FALSE()),1))) | X62: =IF(OR($V62="",$T62="",$T62=0),"",$V62/(1+IF(IFERROR(INDEX('03 Suppliers'!$N$5:$N$34,MATCH($S62,'03 Suppliers'!$B$5:$B$34,0)),"Excl VAT")="Incl VAT",'01 Control'!$C$6,0))/($T62*IFERROR(VLOOKUP($U62,'02 Lists'!$A$5:$B$18,2,FALSE()),1))) | AD62: =IF(OR($AB62="",$Z62="",$Z62=0),"",$AB62/(1+IF(IFERROR(INDEX('03 Suppliers'!$N$5:$N$34,MATCH($Y62,'03 Suppliers'!$B$5:$B$34,0)),"Excl VAT")="Incl VAT",'01 Control'!$C$6,0))/($Z62*IFERROR(VLOOKUP($AA62,'02 Lists'!$A$5:$B$18,2,FALSE()),1))) | AJ62: =IF(OR($AH62="",$AF62="",$AF62=0),"",$AH62/(1+IF(IFERROR(INDEX('03 Suppliers'!$N$5:$N$34,MATCH($AE62,'03 Suppliers'!$B$5:$B$34,0)),"Excl VAT")="Incl VAT",'01 Control'!$C$6,0))/($AF62*IFERROR(VLOOKUP($AG62,'02 Lists'!$A$5:$B$18,2,FALSE()),1))) | AK62: =IF(COUNT(L62,R62,X62,AD62,AJ62)=0,"",MIN(L62,R62,X62,AD62,AJ62)) | AL62: =IF($AK62="","",IF(L62=$AK62,$G62,IF(R62=$AK62,$M62,IF(X62=$AK62,$S62,IF(AD62=$AK62,$Y62,IF(AJ62=$AK62,$AE62,"")))))) | AM62: =IF($AK62="","",$AK62/IF($E62="",1,$E62)) | AN62: =COUNT(L62,R62,X62,AD62,AJ62) | AO62: =IF(COUNT(L62,R62,X62,AD62,AJ62)=0,"",MAX(L62,R62,X62,AD62,AJ62)) | AP62: =IF(OR($AK62="",$AO62="",$AO62=0),"",($AO62-$AK62)/$AO62) | AQ62: =IF($AK62="","",IF(L62=$AK62,$K62,IF(R62=$AK62,$Q62,IF(X62=$AK62,$W62,IF(AD62=$AK62,$AC62,IF(AJ62=$AK62,$AI62,""))))))
A63: PP-VEG-ZUCCHINI | B63: Vegetables | C63: Baby marrow / zucchini | D63: g | E63: 0.95 | G63: Ferreira Fresh | H63: 1 | I63: kg | J63: 26.9 | K63: 46251 | L63: =IF(OR($J63="",$H63="",$H63=0),"",$J63/(1+IF(IFERROR(INDEX('03 Suppliers'!$N$5:$N$34,MATCH($G63,'03 Suppliers'!$B$5:$B$34,0)),"Excl VAT")="Incl VAT",'01 Control'!$C$6,0))/($H63*IFERROR(VLOOKUP($I63,'02 Lists'!$A$5:$B$18,2,FALSE()),1))) | R63: =IF(OR($P63="",$N63="",$N63=0),"",$P63/(1+IF(IFERROR(INDEX('03 Suppliers'!$N$5:$N$34,MATCH($M63,'03 Suppliers'!$B$5:$B$34,0)),"Excl VAT")="Incl VAT",'01 Control'!$C$6,0))/($N63*IFERROR(VLOOKUP($O63,'02 Lists'!$A$5:$B$18,2,FALSE()),1))) | X63: =IF(OR($V63="",$T63="",$T63=0),"",$V63/(1+IF(IFERROR(INDEX('03 Suppliers'!$N$5:$N$34,MATCH($S63,'03 Suppliers'!$B$5:$B$34,0)),"Excl VAT")="Incl VAT",'01 Control'!$C$6,0))/($T63*IFERROR(VLOOKUP($U63,'02 Lists'!$A$5:$B$18,2,FALSE()),1))) | AD63: =IF(OR($AB63="",$Z63="",$Z63=0),"",$AB63/(1+IF(IFERROR(INDEX('03 Suppliers'!$N$5:$N$34,MATCH($Y63,'03 Suppliers'!$B$5:$B$34,0)),"Excl VAT")="Incl VAT",'01 Control'!$C$6,0))/($Z63*IFERROR(VLOOKUP($AA63,'02 Lists'!$A$5:$B$18,2,FALSE()),1))) | AJ63: =IF(OR($AH63="",$AF63="",$AF63=0),"",$AH63/(1+IF(IFERROR(INDEX('03 Suppliers'!$N$5:$N$34,MATCH($AE63,'03 Suppliers'!$B$5:$B$34,0)),"Excl VAT")="Incl VAT",'01 Control'!$C$6,0))/($AF63*IFERROR(VLOOKUP($AG63,'02 Lists'!$A$5:$B$18,2,FALSE()),1))) | AK63: =IF(COUNT(L63,R63,X63,AD63,AJ63)=0,"",MIN(L63,R63,X63,AD63,AJ63)) | AL63: =IF($AK63="","",IF(L63=$AK63,$G63,IF(R63=$AK63,$M63,IF(X63=$AK63,$S63,IF(AD63=$AK63,$Y63,IF(AJ63=$AK63,$AE63,"")))))) | AM63: =IF($AK63="","",$AK63/IF($E63="",1,$E63)) | AN63: =COUNT(L63,R63,X63,AD63,AJ63) | AO63: =IF(COUNT(L63,R63,X63,AD63,AJ63)=0,"",MAX(L63,R63,X63,AD63,AJ63)) | AP63: =IF(OR($AK63="",$AO63="",$AO63=0),"",($AO63-$AK63)/$AO63) | AQ63: =IF($AK63="","",IF(L63=$AK63,$K63,IF(R63=$AK63,$Q63,IF(X63=$AK63,$W63,IF(AD63=$AK63,$AC63,IF(AJ63=$AK63,$AI63,""))))))
A64: PP-VEG-CHERRYTOM | B64: Vegetables | C64: Cherry tomatoes | D64: g | E64: 0.95 | F64: Salad base | L64: =IF(OR($J64="",$H64="",$H64=0),"",$J64/(1+IF(IFERROR(INDEX('03 Suppliers'!$N$5:$N$34,MATCH($G64,'03 Suppliers'!$B$5:$B$34,0)),"Excl VAT")="Incl VAT",'01 Control'!$C$6,0))/($H64*IFERROR(VLOOKUP($I64,'02 Lists'!$A$5:$B$18,2,FALSE()),1))) | R64: =IF(OR($P64="",$N64="",$N64=0),"",$P64/(1+IF(IFERROR(INDEX('03 Suppliers'!$N$5:$N$34,MATCH($M64,'03 Suppliers'!$B$5:$B$34,0)),"Excl VAT")="Incl VAT",'01 Control'!$C$6,0))/($N64*IFERROR(VLOOKUP($O64,'02 Lists'!$A$5:$B$18,2,FALSE()),1))) | X64: =IF(OR($V64="",$T64="",$T64=0),"",$V64/(1+IF(IFERROR(INDEX('03 Suppliers'!$N$5:$N$34,MATCH($S64,'03 Suppliers'!$B$5:$B$34,0)),"Excl VAT")="Incl VAT",'01 Control'!$C$6,0))/($T64*IFERROR(VLOOKUP($U64,'02 Lists'!$A$5:$B$18,2,FALSE()),1))) | AD64: =IF(OR($AB64="",$Z64="",$Z64=0),"",$AB64/(1+IF(IFERROR(INDEX('03 Suppliers'!$N$5:$N$34,MATCH($Y64,'03 Suppliers'!$B$5:$B$34,0)),"Excl VAT")="Incl VAT",'01 Control'!$C$6,0))/($Z64*IFERROR(VLOOKUP($AA64,'02 Lists'!$A$5:$B$18,2,FALSE()),1))) | AJ64: =IF(OR($AH64="",$AF64="",$AF64=0),"",$AH64/(1+IF(IFERROR(INDEX('03 Suppliers'!$N$5:$N$34,MATCH($AE64,'03 Suppliers'!$B$5:$B$34,0)),"Excl VAT")="Incl VAT",'01 Control'!$C$6,0))/($AF64*IFERROR(VLOOKUP($AG64,'02 Lists'!$A$5:$B$18,2,FALSE()),1))) | AK64: =IF(COUNT(L64,R64,X64,AD64,AJ64)=0,"",MIN(L64,R64,X64,AD64,AJ64)) | AL64: =IF($AK64="","",IF(L64=$AK64,$G64,IF(R64=$AK64,$M64,IF(X64=$AK64,$S64,IF(AD64=$AK64,$Y64,IF(AJ64=$AK64,$AE64,"")))))) | AM64: =IF($AK64="","",$AK64/IF($E64="",1,$E64)) | AN64: =COUNT(L64,R64,X64,AD64,AJ64) | AO64: =IF(COUNT(L64,R64,X64,AD64,AJ64)=0,"",MAX(L64,R64,X64,AD64,AJ64)) | AP64: =IF(OR($AK64="",$AO64="",$AO64=0),"",($AO64-$AK64)/$AO64) | AQ64: =IF($AK64="","",IF(L64=$AK64,$K64,IF(R64=$AK64,$Q64,IF(X64=$AK64,$W64,IF(AD64=$AK64,$AC64,IF(AJ64=$AK64,$AI64,""))))))
A65: PP-VEG-SUNDRIEDTOM | B65: Vegetables | C65: Sun-dried tomatoes | D65: g | E65: 1 | F65: Y3 Mediterranean | G65: Ferreira Fresh | H65: 1 | I65: kg | J65: 318.5 | K65: 46251 | L65: =IF(OR($J65="",$H65="",$H65=0),"",$J65/(1+IF(IFERROR(INDEX('03 Suppliers'!$N$5:$N$34,MATCH($G65,'03 Suppliers'!$B$5:$B$34,0)),"Excl VAT")="Incl VAT",'01 Control'!$C$6,0))/($H65*IFERROR(VLOOKUP($I65,'02 Lists'!$A$5:$B$18,2,FALSE()),1))) | R65: =IF(OR($P65="",$N65="",$N65=0),"",$P65/(1+IF(IFERROR(INDEX('03 Suppliers'!$N$5:$N$34,MATCH($M65,'03 Suppliers'!$B$5:$B$34,0)),"Excl VAT")="Incl VAT",'01 Control'!$C$6,0))/($N65*IFERROR(VLOOKUP($O65,'02 Lists'!$A$5:$B$18,2,FALSE()),1))) | X65: =IF(OR($V65="",$T65="",$T65=0),"",$V65/(1+IF(IFERROR(INDEX('03 Suppliers'!$N$5:$N$34,MATCH($S65,'03 Suppliers'!$B$5:$B$34,0)),"Excl VAT")="Incl VAT",'01 Control'!$C$6,0))/($T65*IFERROR(VLOOKUP($U65,'02 Lists'!$A$5:$B$18,2,FALSE()),1))) | AD65: =IF(OR($AB65="",$Z65="",$Z65=0),"",$AB65/(1+IF(IFERROR(INDEX('03 Suppliers'!$N$5:$N$34,MATCH($Y65,'03 Suppliers'!$B$5:$B$34,0)),"Excl VAT")="Incl VAT",'01 Control'!$C$6,0))/($Z65*IFERROR(VLOOKUP($AA65,'02 Lists'!$A$5:$B$18,2,FALSE()),1))) | AJ65: =IF(OR($AH65="",$AF65="",$AF65=0),"",$AH65/(1+IF(IFERROR(INDEX('03 Suppliers'!$N$5:$N$34,MATCH($AE65,'03 Suppliers'!$B$5:$B$34,0)),"Excl VAT")="Incl VAT",'01 Control'!$C$6,0))/($AF65*IFERROR(VLOOKUP($AG65,'02 Lists'!$A$5:$B$18,2,FALSE()),1))) | AK65: =IF(COUNT(L65,R65,X65,AD65,AJ65)=0,"",MIN(L65,R65,X65,AD65,AJ65)) | AL65: =IF($AK65="","",IF(L65=$AK65,$G65,IF(R65=$AK65,$M65,IF(X65=$AK65,$S65,IF(AD65=$AK65,$Y65,IF(AJ65=$AK65,$AE65,"")))))) | AM65: =IF($AK65="","",$AK65/IF($E65="",1,$E65)) | AN65: =COUNT(L65,R65,X65,AD65,AJ65) | AO65: =IF(COUNT(L65,R65,X65,AD65,AJ65)=0,"",MAX(L65,R65,X65,AD65,AJ65)) | AP65: =IF(OR($AK65="",$AO65="",$AO65=0),"",($AO65-$AK65)/$AO65) | AQ65: =IF($AK65="","",IF(L65=$AK65,$K65,IF(R65=$AK65,$Q65,IF(X65=$AK65,$W65,IF(AD65=$AK65,$AC65,IF(AJ65=$AK65,$AI65,""))))))
A66: PP-VEG-SWEETCORN | B66: Vegetables | C66: Sweetcorn | D66: g | E66: 1 | F66: Rainbow salad | G66: Ferreira Fresh | H66: 1 | I66: kg | J66: 49.9 | K66: 46251 | L66: =IF(OR($J66="",$H66="",$H66=0),"",$J66/(1+IF(IFERROR(INDEX('03 Suppliers'!$N$5:$N$34,MATCH($G66,'03 Suppliers'!$B$5:$B$34,0)),"Excl VAT")="Incl VAT",'01 Control'!$C$6,0))/($H66*IFERROR(VLOOKUP($I66,'02 Lists'!$A$5:$B$18,2,FALSE()),1))) | R66: =IF(OR($P66="",$N66="",$N66=0),"",$P66/(1+IF(IFERROR(INDEX('03 Suppliers'!$N$5:$N$34,MATCH($M66,'03 Suppliers'!$B$5:$B$34,0)),"Excl VAT")="Incl VAT",'01 Control'!$C$6,0))/($N66*IFERROR(VLOOKUP($O66,'02 Lists'!$A$5:$B$18,2,FALSE()),1))) | X66: =IF(OR($V66="",$T66="",$T66=0),"",$V66/(1+IF(IFERROR(INDEX('03 Suppliers'!$N$5:$N$34,MATCH($S66,'03 Suppliers'!$B$5:$B$34,0)),"Excl VAT")="Incl VAT",'01 Control'!$C$6,0))/($T66*IFERROR(VLOOKUP($U66,'02 Lists'!$A$5:$B$18,2,FALSE()),1))) | AD66: =IF(OR($AB66="",$Z66="",$Z66=0),"",$AB66/(1+IF(IFERROR(INDEX('03 Suppliers'!$N$5:$N$34,MATCH($Y66,'03 Suppliers'!$B$5:$B$34,0)),"Excl VAT")="Incl VAT",'01 Control'!$C$6,0))/($Z66*IFERROR(VLOOKUP($AA66,'02 Lists'!$A$5:$B$18,2,FALSE()),1))) | AJ66: =IF(OR($AH66="",$AF66="",$AF66=0),"",$AH66/(1+IF(IFERROR(INDEX('03 Suppliers'!$N$5:$N$34,MATCH($AE66,'03 Suppliers'!$B$5:$B$34,0)),"Excl VAT")="Incl VAT",'01 Control'!$C$6,0))/($AF66*IFERROR(VLOOKUP($AG66,'02 Lists'!$A$5:$B$18,2,FALSE()),1))) | AK66: =IF(COUNT(L66,R66,X66,AD66,AJ66)=0,"",MIN(L66,R66,X66,AD66,AJ66)) | AL66: =IF($AK66="","",IF(L66=$AK66,$G66,IF(R66=$AK66,$M66,IF(X66=$AK66,$S66,IF(AD66=$AK66,$Y66,IF(AJ66=$AK66,$AE66,"")))))) | AM66: =IF($AK66="","",$AK66/IF($E66="",1,$E66)) | AN66: =COUNT(L66,R66,X66,AD66,AJ66) | AO66: =IF(COUNT(L66,R66,X66,AD66,AJ66)=0,"",MAX(L66,R66,X66,AD66,AJ66)) | AP66: =IF(OR($AK66="",$AO66="",$AO66=0),"",($AO66-$AK66)/$AO66) | AQ66: =IF($AK66="","",IF(L66=$AK66,$K66,IF(R66=$AK66,$Q66,IF(X66=$AK66,$W66,IF(AD66=$AK66,$AC66,IF(AJ66=$AK66,$AI66,""))))))
A67: PP-VEG-PEAS | B67: Vegetables | C67: Peas | D67: g | E67: 1 | F67: Spring seasonal CHECK THE UNIT: the carried-over quote reads R348.50/kg, which is out of line with the rest of the list. Confirm per-kg vs pack price before this reaches a menu price. | G67: Ferreira Fresh | H67: 1 | I67: kg | J67: 348.5 | K67: 46251 | L67: =IF(OR($J67="",$H67="",$H67=0),"",$J67/(1+IF(IFERROR(INDEX('03 Suppliers'!$N$5:$N$34,MATCH($G67,'03 Suppliers'!$B$5:$B$34,0)),"Excl VAT")="Incl VAT",'01 Control'!$C$6,0))/($H67*IFERROR(VLOOKUP($I67,'02 Lists'!$A$5:$B$18,2,FALSE()),1))) | R67: =IF(OR($P67="",$N67="",$N67=0),"",$P67/(1+IF(IFERROR(INDEX('03 Suppliers'!$N$5:$N$34,MATCH($M67,'03 Suppliers'!$B$5:$B$34,0)),"Excl VAT")="Incl VAT",'01 Control'!$C$6,0))/($N67*IFERROR(VLOOKUP($O67,'02 Lists'!$A$5:$B$18,2,FALSE()),1))) | X67: =IF(OR($V67="",$T67="",$T67=0),"",$V67/(1+IF(IFERROR(INDEX('03 Suppliers'!$N$5:$N$34,MATCH($S67,'03 Suppliers'!$B$5:$B$34,0)),"Excl VAT")="Incl VAT",'01 Control'!$C$6,0))/($T67*IFERROR(VLOOKUP($U67,'02 Lists'!$A$5:$B$18,2,FALSE()),1))) | AD67: =IF(OR($AB67="",$Z67="",$Z67=0),"",$AB67/(1+IF(IFERROR(INDEX('03 Suppliers'!$N$5:$N$34,MATCH($Y67,'03 Suppliers'!$B$5:$B$34,0)),"Excl VAT")="Incl VAT",'01 Control'!$C$6,0))/($Z67*IFERROR(VLOOKUP($AA67,'02 Lists'!$A$5:$B$18,2,FALSE()),1))) | AJ67: =IF(OR($AH67="",$AF67="",$AF67=0),"",$AH67/(1+IF(IFERROR(INDEX('03 Suppliers'!$N$5:$N$34,MATCH($AE67,'03 Suppliers'!$B$5:$B$34,0)),"Excl VAT")="Incl VAT",'01 Control'!$C$6,0))/($AF67*IFERROR(VLOOKUP($AG67,'02 Lists'!$A$5:$B$18,2,FALSE()),1))) | AK67: =IF(COUNT(L67,R67,X67,AD67,AJ67)=0,"",MIN(L67,R67,X67,AD67,AJ67)) | AL67: =IF($AK67="","",IF(L67=$AK67,$G67,IF(R67=$AK67,$M67,IF(X67=$AK67,$S67,IF(AD67=$AK67,$Y67,IF(AJ67=$AK67,$AE67,"")))))) | AM67: =IF($AK67="","",$AK67/IF($E67="",1,$E67)) | AN67: =COUNT(L67,R67,X67,AD67,AJ67) | AO67: =IF(COUNT(L67,R67,X67,AD67,AJ67)=0,"",MAX(L67,R67,X67,AD67,AJ67)) | AP67: =IF(OR($AK67="",$AO67="",$AO67=0),"",($AO67-$AK67)/$AO67) | AQ67: =IF($AK67="","",IF(L67=$AK67,$K67,IF(R67=$AK67,$Q67,IF(X67=$AK67,$W67,IF(AD67=$AK67,$AC67,IF(AJ67=$AK67,$AI67,""))))))
A68: PP-VEG-BUTTERNUT | B68: Vegetables | C68: Butternut | D68: g | E68: 0.75 | F68: Autumn seasonal + rainbow salad | G68: Ferreira Fresh | H68: 1 | I68: kg | J68: 10.9 | K68: 46251 | L68: =IF(OR($J68="",$H68="",$H68=0),"",$J68/(1+IF(IFERROR(INDEX('03 Suppliers'!$N$5:$N$34,MATCH($G68,'03 Suppliers'!$B$5:$B$34,0)),"Excl VAT")="Incl VAT",'01 Control'!$C$6,0))/($H68*IFERROR(VLOOKUP($I68,'02 Lists'!$A$5:$B$18,2,FALSE()),1))) | R68: =IF(OR($P68="",$N68="",$N68=0),"",$P68/(1+IF(IFERROR(INDEX('03 Suppliers'!$N$5:$N$34,MATCH($M68,'03 Suppliers'!$B$5:$B$34,0)),"Excl VAT")="Incl VAT",'01 Control'!$C$6,0))/($N68*IFERROR(VLOOKUP($O68,'02 Lists'!$A$5:$B$18,2,FALSE()),1))) | X68: =IF(OR($V68="",$T68="",$T68=0),"",$V68/(1+IF(IFERROR(INDEX('03 Suppliers'!$N$5:$N$34,MATCH($S68,'03 Suppliers'!$B$5:$B$34,0)),"Excl VAT")="Incl VAT",'01 Control'!$C$6,0))/($T68*IFERROR(VLOOKUP($U68,'02 Lists'!$A$5:$B$18,2,FALSE()),1))) | AD68: =IF(OR($AB68="",$Z68="",$Z68=0),"",$AB68/(1+IF(IFERROR(INDEX('03 Suppliers'!$N$5:$N$34,MATCH($Y68,'03 Suppliers'!$B$5:$B$34,0)),"Excl VAT")="Incl VAT",'01 Control'!$C$6,0))/($Z68*IFERROR(VLOOKUP($AA68,'02 Lists'!$A$5:$B$18,2,FALSE()),1))) | AJ68: =IF(OR($AH68="",$AF68="",$AF68=0),"",$AH68/(1+IF(IFERROR(INDEX('03 Suppliers'!$N$5:$N$34,MATCH($AE68,'03 Suppliers'!$B$5:$B$34,0)),"Excl VAT")="Incl VAT",'01 Control'!$C$6,0))/($AF68*IFERROR(VLOOKUP($AG68,'02 Lists'!$A$5:$B$18,2,FALSE()),1))) | AK68: =IF(COUNT(L68,R68,X68,AD68,AJ68)=0,"",MIN(L68,R68,X68,AD68,AJ68)) | AL68: =IF($AK68="","",IF(L68=$AK68,$G68,IF(R68=$AK68,$M68,IF(X68=$AK68,$S68,IF(AD68=$AK68,$Y68,IF(AJ68=$AK68,$AE68,"")))))) | AM68: =IF($AK68="","",$AK68/IF($E68="",1,$E68)) | AN68: =COUNT(L68,R68,X68,AD68,AJ68) | AO68: =IF(COUNT(L68,R68,X68,AD68,AJ68)=0,"",MAX(L68,R68,X68,AD68,AJ68)) | AP68: =IF(OR($AK68="",$AO68="",$AO68=0),"",($AO68-$AK68)/$AO68) | AQ68: =IF($AK68="","",IF(L68=$AK68,$K68,IF(R68=$AK68,$Q68,IF(X68=$AK68,$W68,IF(AD68=$AK68,$AC68,IF(AJ68=$AK68,$AI68,""))))))
A69: PP-VEG-AUBERGINE | B69: Vegetables | C69: Aubergine / eggplant | D69: g | E69: 0.95 | L69: =IF(OR($J69="",$H69="",$H69=0),"",$J69/(1+IF(IFERROR(INDEX('03 Suppliers'!$N$5:$N$34,MATCH($G69,'03 Suppliers'!$B$5:$B$34,0)),"Excl VAT")="Incl VAT",'01 Control'!$C$6,0))/($H69*IFERROR(VLOOKUP($I69,'02 Lists'!$A$5:$B$18,2,FALSE()),1))) | R69: =IF(OR($P69="",$N69="",$N69=0),"",$P69/(1+IF(IFERROR(INDEX('03 Suppliers'!$N$5:$N$34,MATCH($M69,'03 Suppliers'!$B$5:$B$34,0)),"Excl VAT")="Incl VAT",'01 Control'!$C$6,0))/($N69*IFERROR(VLOOKUP($O69,'02 Lists'!$A$5:$B$18,2,FALSE()),1))) | X69: =IF(OR($V69="",$T69="",$T69=0),"",$V69/(1+IF(IFERROR(INDEX('03 Suppliers'!$N$5:$N$34,MATCH($S69,'03 Suppliers'!$B$5:$B$34,0)),"Excl VAT")="Incl VAT",'01 Control'!$C$6,0))/($T69*IFERROR(VLOOKUP($U69,'02 Lists'!$A$5:$B$18,2,FALSE()),1))) | AD69: =IF(OR($AB69="",$Z69="",$Z69=0),"",$AB69/(1+IF(IFERROR(INDEX('03 Suppliers'!$N$5:$N$34,MATCH($Y69,'03 Suppliers'!$B$5:$B$34,0)),"Excl VAT")="Incl VAT",'01 Control'!$C$6,0))/($Z69*IFERROR(VLOOKUP($AA69,'02 Lists'!$A$5:$B$18,2,FALSE()),1))) | AJ69: =IF(OR($AH69="",$AF69="",$AF69=0),"",$AH69/(1+IF(IFERROR(INDEX('03 Suppliers'!$N$5:$N$34,MATCH($AE69,'03 Suppliers'!$B$5:$B$34,0)),"Excl VAT")="Incl VAT",'01 Control'!$C$6,0))/($AF69*IFERROR(VLOOKUP($AG69,'02 Lists'!$A$5:$B$18,2,FALSE()),1))) | AK69: =IF(COUNT(L69,R69,X69,AD69,AJ69)=0,"",MIN(L69,R69,X69,AD69,AJ69)) | AL69: =IF($AK69="","",IF(L69=$AK69,$G69,IF(R69=$AK69,$M69,IF(X69=$AK69,$S69,IF(AD69=$AK69,$Y69,IF(AJ69=$AK69,$AE69,"")))))) | AM69: =IF($AK69="","",$AK69/IF($E69="",1,$E69)) | AN69: =COUNT(L69,R69,X69,AD69,AJ69) | AO69: =IF(COUNT(L69,R69,X69,AD69,AJ69)=0,"",MAX(L69,R69,X69,AD69,AJ69)) | AP69: =IF(OR($AK69="",$AO69="",$AO69=0),"",($AO69-$AK69)/$AO69) | AQ69: =IF($AK69="","",IF(L69=$AK69,$K69,IF(R69=$AK69,$Q69,IF(X69=$AK69,$W69,IF(AD69=$AK69,$AC69,IF(AJ69=$AK69,$AI69,""))))))
A70: PP-VEG-GREENBEAN | B70: Vegetables | C70: Green beans | D70: g | E70: 0.9 | G70: Ferreira Fresh | H70: 1 | I70: kg | J70: 39.5 | K70: 46251 | L70: =IF(OR($J70="",$H70="",$H70=0),"",$J70/(1+IF(IFERROR(INDEX('03 Suppliers'!$N$5:$N$34,MATCH($G70,'03 Suppliers'!$B$5:$B$34,0)),"Excl VAT")="Incl VAT",'01 Control'!$C$6,0))/($H70*IFERROR(VLOOKUP($I70,'02 Lists'!$A$5:$B$18,2,FALSE()),1))) | R70: =IF(OR($P70="",$N70="",$N70=0),"",$P70/(1+IF(IFERROR(INDEX('03 Suppliers'!$N$5:$N$34,MATCH($M70,'03 Suppliers'!$B$5:$B$34,0)),"Excl VAT")="Incl VAT",'01 Control'!$C$6,0))/($N70*IFERROR(VLOOKUP($O70,'02 Lists'!$A$5:$B$18,2,FALSE()),1))) | X70: =IF(OR($V70="",$T70="",$T70=0),"",$V70/(1+IF(IFERROR(INDEX('03 Suppliers'!$N$5:$N$34,MATCH($S70,'03 Suppliers'!$B$5:$B$34,0)),"Excl VAT")="Incl VAT",'01 Control'!$C$6,0))/($T70*IFERROR(VLOOKUP($U70,'02 Lists'!$A$5:$B$18,2,FALSE()),1))) | AD70: =IF(OR($AB70="",$Z70="",$Z70=0),"",$AB70/(1+IF(IFERROR(INDEX('03 Suppliers'!$N$5:$N$34,MATCH($Y70,'03 Suppliers'!$B$5:$B$34,0)),"Excl VAT")="Incl VAT",'01 Control'!$C$6,0))/($Z70*IFERROR(VLOOKUP($AA70,'02 Lists'!$A$5:$B$18,2,FALSE()),1))) | AJ70: =IF(OR($AH70="",$AF70="",$AF70=0),"",$AH70/(1+IF(IFERROR(INDEX('03 Suppliers'!$N$5:$N$34,MATCH($AE70,'03 Suppliers'!$B$5:$B$34,0)),"Excl VAT")="Incl VAT",'01 Control'!$C$6,0))/($AF70*IFERROR(VLOOKUP($AG70,'02 Lists'!$A$5:$B$18,2,FALSE()),1))) | AK70: =IF(COUNT(L70,R70,X70,AD70,AJ70)=0,"",MIN(L70,R70,X70,AD70,AJ70)) | AL70: =IF($AK70="","",IF(L70=$AK70,$G70,IF(R70=$AK70,$M70,IF(X70=$AK70,$S70,IF(AD70=$AK70,$Y70,IF(AJ70=$AK70,$AE70,"")))))) | AM70: =IF($AK70="","",$AK70/IF($E70="",1,$E70)) | AN70: =COUNT(L70,R70,X70,AD70,AJ70) | AO70: =IF(COUNT(L70,R70,X70,AD70,AJ70)=0,"",MAX(L70,R70,X70,AD70,AJ70)) | AP70: =IF(OR($AK70="",$AO70="",$AO70=0),"",($AO70-$AK70)/$AO70) | AQ70: =IF($AK70="","",IF(L70=$AK70,$K70,IF(R70=$AK70,$Q70,IF(X70=$AK70,$W70,IF(AD70=$AK70,$AC70,IF(AJ70=$AK70,$AI70,""))))))
A71: PP-VEG-ASPARAGUS | B71: Vegetables | C71: Asparagus | D71: g | E71: 0.8 | F71: Y3 Spring seasonal CHECK THE UNIT: the carried-over quote reads R439.50/kg, which is out of line with the rest of the list. Confirm per-kg vs pack price before this reaches a menu price. | G71: Ferreira Fresh | H71: 1 | I71: kg | J71: 439.5 | K71: 46251 | L71: =IF(OR($J71="",$H71="",$H71=0),"",$J71/(1+IF(IFERROR(INDEX('03 Suppliers'!$N$5:$N$34,MATCH($G71,'03 Suppliers'!$B$5:$B$34,0)),"Excl VAT")="Incl VAT",'01 Control'!$C$6,0))/($H71*IFERROR(VLOOKUP($I71,'02 Lists'!$A$5:$B$18,2,FALSE()),1))) | R71: =IF(OR($P71="",$N71="",$N71=0),"",$P71/(1+IF(IFERROR(INDEX('03 Suppliers'!$N$5:$N$34,MATCH($M71,'03 Suppliers'!$B$5:$B$34,0)),"Excl VAT")="Incl VAT",'01 Control'!$C$6,0))/($N71*IFERROR(VLOOKUP($O71,'02 Lists'!$A$5:$B$18,2,FALSE()),1))) | X71: =IF(OR($V71="",$T71="",$T71=0),"",$V71/(1+IF(IFERROR(INDEX('03 Suppliers'!$N$5:$N$34,MATCH($S71,'03 Suppliers'!$B$5:$B$34,0)),"Excl VAT")="Incl VAT",'01 Control'!$C$6,0))/($T71*IFERROR(VLOOKUP($U71,'02 Lists'!$A$5:$B$18,2,FALSE()),1))) | AD71: =IF(OR($AB71="",$Z71="",$Z71=0),"",$AB71/(1+IF(IFERROR(INDEX('03 Suppliers'!$N$5:$N$34,MATCH($Y71,'03 Suppliers'!$B$5:$B$34,0)),"Excl VAT")="Incl VAT",'01 Control'!$C$6,0))/($Z71*IFERROR(VLOOKUP($AA71,'02 Lists'!$A$5:$B$18,2,FALSE()),1))) | AJ71: =IF(OR($AH71="",$AF71="",$AF71=0),"",$AH71/(1+IF(IFERROR(INDEX('03 Suppliers'!$N$5:$N$34,MATCH($AE71,'03 Suppliers'!$B$5:$B$34,0)),"Excl VAT")="Incl VAT",'01 Control'!$C$6,0))/($AF71*IFERROR(VLOOKUP($AG71,'02 Lists'!$A$5:$B$18,2,FALSE()),1))) | AK71: =IF(COUNT(L71,R71,X71,AD71,AJ71)=0,"",MIN(L71,R71,X71,AD71,AJ71)) | AL71: =IF($AK71="","",IF(L71=$AK71,$G71,IF(R71=$AK71,$M71,IF(X71=$AK71,$S71,IF(AD71=$AK71,$Y71,IF(AJ71=$AK71,$AE71,"")))))) | AM71: =IF($AK71="","",$AK71/IF($E71="",1,$E71)) | AN71: =COUNT(L71,R71,X71,AD71,AJ71) | AO71: =IF(COUNT(L71,R71,X71,AD71,AJ71)=0,"",MAX(L71,R71,X71,AD71,AJ71)) | AP71: =IF(OR($AK71="",$AO71="",$AO71=0),"",($AO71-$AK71)/$AO71) | AQ71: =IF($AK71="","",IF(L71=$AK71,$K71,IF(R71=$AK71,$Q71,IF(X71=$AK71,$W71,IF(AD71=$AK71,$AC71,IF(AJ71=$AK71,$AI71,""))))))
A72: PP-VEG-ARTICHOKE | B72: Vegetables | C72: Artichokes | D72: g | E72: 0.9 | L72: =IF(OR($J72="",$H72="",$H72=0),"",$J72/(1+IF(IFERROR(INDEX('03 Suppliers'!$N$5:$N$34,MATCH($G72,'03 Suppliers'!$B$5:$B$34,0)),"Excl VAT")="Incl VAT",'01 Control'!$C$6,0))/($H72*IFERROR(VLOOKUP($I72,'02 Lists'!$A$5:$B$18,2,FALSE()),1))) | R72: =IF(OR($P72="",$N72="",$N72=0),"",$P72/(1+IF(IFERROR(INDEX('03 Suppliers'!$N$5:$N$34,MATCH($M72,'03 Suppliers'!$B$5:$B$34,0)),"Excl VAT")="Incl VAT",'01 Control'!$C$6,0))/($N72*IFERROR(VLOOKUP($O72,'02 Lists'!$A$5:$B$18,2,FALSE()),1))) | X72: =IF(OR($V72="",$T72="",$T72=0),"",$V72/(1+IF(IFERROR(INDEX('03 Suppliers'!$N$5:$N$34,MATCH($S72,'03 Suppliers'!$B$5:$B$34,0)),"Excl VAT")="Incl VAT",'01 Control'!$C$6,0))/($T72*IFERROR(VLOOKUP($U72,'02 Lists'!$A$5:$B$18,2,FALSE()),1))) | AD72: =IF(OR($AB72="",$Z72="",$Z72=0),"",$AB72/(1+IF(IFERROR(INDEX('03 Suppliers'!$N$5:$N$34,MATCH($Y72,'03 Suppliers'!$B$5:$B$34,0)),"Excl VAT")="Incl VAT",'01 Control'!$C$6,0))/($Z72*IFERROR(VLOOKUP($AA72,'02 Lists'!$A$5:$B$18,2,FALSE()),1))) | AJ72: =IF(OR($AH72="",$AF72="",$AF72=0),"",$AH72/(1+IF(IFERROR(INDEX('03 Suppliers'!$N$5:$N$34,MATCH($AE72,'03 Suppliers'!$B$5:$B$34,0)),"Excl VAT")="Incl VAT",'01 Control'!$C$6,0))/($AF72*IFERROR(VLOOKUP($AG72,'02 Lists'!$A$5:$B$18,2,FALSE()),1))) | AK72: =IF(COUNT(L72,R72,X72,AD72,AJ72)=0,"",MIN(L72,R72,X72,AD72,AJ72)) | AL72: =IF($AK72="","",IF(L72=$AK72,$G72,IF(R72=$AK72,$M72,IF(X72=$AK72,$S72,IF(AD72=$AK72,$Y72,IF(AJ72=$AK72,$AE72,"")))))) | AM72: =IF($AK72="","",$AK72/IF($E72="",1,$E72)) | AN72: =COUNT(L72,R72,X72,AD72,AJ72) | AO72: =IF(COUNT(L72,R72,X72,AD72,AJ72)=0,"",MAX(L72,R72,X72,AD72,AJ72)) | AP72: =IF(OR($AK72="",$AO72="",$AO72=0),"",($AO72-$AK72)/$AO72) | AQ72: =IF($AK72="","",IF(L72=$AK72,$K72,IF(R72=$AK72,$Q72,IF(X72=$AK72,$W72,IF(AD72=$AK72,$AC72,IF(AJ72=$AK72,$AI72,""))))))
A73: PP-VEG-OLIVE | B73: Vegetables | C73: Olives | D73: g | E73: 1 | F73: Y3 Mediterranean | L73: =IF(OR($J73="",$H73="",$H73=0),"",$J73/(1+IF(IFERROR(INDEX('03 Suppliers'!$N$5:$N$34,MATCH($G73,'03 Suppliers'!$B$5:$B$34,0)),"Excl VAT")="Incl VAT",'01 Control'!$C$6,0))/($H73*IFERROR(VLOOKUP($I73,'02 Lists'!$A$5:$B$18,2,FALSE()),1))) | R73: =IF(OR($P73="",$N73="",$N73=0),"",$P73/(1+IF(IFERROR(INDEX('03 Suppliers'!$N$5:$N$34,MATCH($M73,'03 Suppliers'!$B$5:$B$34,0)),"Excl VAT")="Incl VAT",'01 Control'!$C$6,0))/($N73*IFERROR(VLOOKUP($O73,'02 Lists'!$A$5:$B$18,2,FALSE()),1))) | X73: =IF(OR($V73="",$T73="",$T73=0),"",$V73/(1+IF(IFERROR(INDEX('03 Suppliers'!$N$5:$N$34,MATCH($S73,'03 Suppliers'!$B$5:$B$34,0)),"Excl VAT")="Incl VAT",'01 Control'!$C$6,0))/($T73*IFERROR(VLOOKUP($U73,'02 Lists'!$A$5:$B$18,2,FALSE()),1))) | AD73: =IF(OR($AB73="",$Z73="",$Z73=0),"",$AB73/(1+IF(IFERROR(INDEX('03 Suppliers'!$N$5:$N$34,MATCH($Y73,'03 Suppliers'!$B$5:$B$34,0)),"Excl VAT")="Incl VAT",'01 Control'!$C$6,0))/($Z73*IFERROR(VLOOKUP($AA73,'02 Lists'!$A$5:$B$18,2,FALSE()),1))) | AJ73: =IF(OR($AH73="",$AF73="",$AF73=0),"",$AH73/(1+IF(IFERROR(INDEX('03 Suppliers'!$N$5:$N$34,MATCH($AE73,'03 Suppliers'!$B$5:$B$34,0)),"Excl VAT")="Incl VAT",'01 Control'!$C$6,0))/($AF73*IFERROR(VLOOKUP($AG73,'02 Lists'!$A$5:$B$18,2,FALSE()),1))) | AK73: =IF(COUNT(L73,R73,X73,AD73,AJ73)=0,"",MIN(L73,R73,X73,AD73,AJ73)) | AL73: =IF($AK73="","",IF(L73=$AK73,$G73,IF(R73=$AK73,$M73,IF(X73=$AK73,$S73,IF(AD73=$AK73,$Y73,IF(AJ73=$AK73,$AE73,"")))))) | AM73: =IF($AK73="","",$AK73/IF($E73="",1,$E73)) | AN73: =COUNT(L73,R73,X73,AD73,AJ73) | AO73: =IF(COUNT(L73,R73,X73,AD73,AJ73)=0,"",MAX(L73,R73,X73,AD73,AJ73)) | AP73: =IF(OR($AK73="",$AO73="",$AO73=0),"",($AO73-$AK73)/$AO73) | AQ73: =IF($AK73="","",IF(L73=$AK73,$K73,IF(R73=$AK73,$Q73,IF(X73=$AK73,$W73,IF(AD73=$AK73,$AC73,IF(AJ73=$AK73,$AI73,""))))))
A74: PP-VEG-CUCUMBER | B74: Vegetables | C74: Cucumber | D74: g | E74: 0.9 | F74: Salad base | L74: =IF(OR($J74="",$H74="",$H74=0),"",$J74/(1+IF(IFERROR(INDEX('03 Suppliers'!$N$5:$N$34,MATCH($G74,'03 Suppliers'!$B$5:$B$34,0)),"Excl VAT")="Incl VAT",'01 Control'!$C$6,0))/($H74*IFERROR(VLOOKUP($I74,'02 Lists'!$A$5:$B$18,2,FALSE()),1))) | R74: =IF(OR($P74="",$N74="",$N74=0),"",$P74/(1+IF(IFERROR(INDEX('03 Suppliers'!$N$5:$N$34,MATCH($M74,'03 Suppliers'!$B$5:$B$34,0)),"Excl VAT")="Incl VAT",'01 Control'!$C$6,0))/($N74*IFERROR(VLOOKUP($O74,'02 Lists'!$A$5:$B$18,2,FALSE()),1))) | X74: =IF(OR($V74="",$T74="",$T74=0),"",$V74/(1+IF(IFERROR(INDEX('03 Suppliers'!$N$5:$N$34,MATCH($S74,'03 Suppliers'!$B$5:$B$34,0)),"Excl VAT")="Incl VAT",'01 Control'!$C$6,0))/($T74*IFERROR(VLOOKUP($U74,'02 Lists'!$A$5:$B$18,2,FALSE()),1))) | AD74: =IF(OR($AB74="",$Z74="",$Z74=0),"",$AB74/(1+IF(IFERROR(INDEX('03 Suppliers'!$N$5:$N$34,MATCH($Y74,'03 Suppliers'!$B$5:$B$34,0)),"Excl VAT")="Incl VAT",'01 Control'!$C$6,0))/($Z74*IFERROR(VLOOKUP($AA74,'02 Lists'!$A$5:$B$18,2,FALSE()),1))) | AJ74: =IF(OR($AH74="",$AF74="",$AF74=0),"",$AH74/(1+IF(IFERROR(INDEX('03 Suppliers'!$N$5:$N$34,MATCH($AE74,'03 Suppliers'!$B$5:$B$34,0)),"Excl VAT")="Incl VAT",'01 Control'!$C$6,0))/($AF74*IFERROR(VLOOKUP($AG74,'02 Lists'!$A$5:$B$18,2,FALSE()),1))) | AK74: =IF(COUNT(L74,R74,X74,AD74,AJ74)=0,"",MIN(L74,R74,X74,AD74,AJ74)) | AL74: =IF($AK74="","",IF(L74=$AK74,$G74,IF(R74=$AK74,$M74,IF(X74=$AK74,$S74,IF(AD74=$AK74,$Y74,IF(AJ74=$AK74,$AE74,"")))))) | AM74: =IF($AK74="","",$AK74/IF($E74="",1,$E74)) | AN74: =COUNT(L74,R74,X74,AD74,AJ74) | AO74: =IF(COUNT(L74,R74,X74,AD74,AJ74)=0,"",MAX(L74,R74,X74,AD74,AJ74)) | AP74: =IF(OR($AK74="",$AO74="",$AO74=0),"",($AO74-$AK74)/$AO74) | AQ74: =IF($AK74="","",IF(L74=$AK74,$K74,IF(R74=$AK74,$Q74,IF(X74=$AK74,$W74,IF(AD74=$AK74,$AC74,IF(AJ74=$AK74,$AI74,""))))))
A75: PP-VEG-LEMON | B75: Vegetables | C75: Lemons | D75: g | E75: 0.45 | F75: Juice yield only | L75: =IF(OR($J75="",$H75="",$H75=0),"",$J75/(1+IF(IFERROR(INDEX('03 Suppliers'!$N$5:$N$34,MATCH($G75,'03 Suppliers'!$B$5:$B$34,0)),"Excl VAT")="Incl VAT",'01 Control'!$C$6,0))/($H75*IFERROR(VLOOKUP($I75,'02 Lists'!$A$5:$B$18,2,FALSE()),1))) | R75: =IF(OR($P75="",$N75="",$N75=0),"",$P75/(1+IF(IFERROR(INDEX('03 Suppliers'!$N$5:$N$34,MATCH($M75,'03 Suppliers'!$B$5:$B$34,0)),"Excl VAT")="Incl VAT",'01 Control'!$C$6,0))/($N75*IFERROR(VLOOKUP($O75,'02 Lists'!$A$5:$B$18,2,FALSE()),1))) | X75: =IF(OR($V75="",$T75="",$T75=0),"",$V75/(1+IF(IFERROR(INDEX('03 Suppliers'!$N$5:$N$34,MATCH($S75,'03 Suppliers'!$B$5:$B$34,0)),"Excl VAT")="Incl VAT",'01 Control'!$C$6,0))/($T75*IFERROR(VLOOKUP($U75,'02 Lists'!$A$5:$B$18,2,FALSE()),1))) | AD75: =IF(OR($AB75="",$Z75="",$Z75=0),"",$AB75/(1+IF(IFERROR(INDEX('03 Suppliers'!$N$5:$N$34,MATCH($Y75,'03 Suppliers'!$B$5:$B$34,0)),"Excl VAT")="Incl VAT",'01 Control'!$C$6,0))/($Z75*IFERROR(VLOOKUP($AA75,'02 Lists'!$A$5:$B$18,2,FALSE()),1))) | AJ75: =IF(OR($AH75="",$AF75="",$AF75=0),"",$AH75/(1+IF(IFERROR(INDEX('03 Suppliers'!$N$5:$N$34,MATCH($AE75,'03 Suppliers'!$B$5:$B$34,0)),"Excl VAT")="Incl VAT",'01 Control'!$C$6,0))/($AF75*IFERROR(VLOOKUP($AG75,'02 Lists'!$A$5:$B$18,2,FALSE()),1))) | AK75: =IF(COUNT(L75,R75,X75,AD75,AJ75)=0,"",MIN(L75,R75,X75,AD75,AJ75)) | AL75: =IF($AK75="","",IF(L75=$AK75,$G75,IF(R75=$AK75,$M75,IF(X75=$AK75,$S75,IF(AD75=$AK75,$Y75,IF(AJ75=$AK75,$AE75,"")))))) | AM75: =IF($AK75="","",$AK75/IF($E75="",1,$E75)) | AN75: =COUNT(L75,R75,X75,AD75,AJ75) | AO75: =IF(COUNT(L75,R75,X75,AD75,AJ75)=0,"",MAX(L75,R75,X75,AD75,AJ75)) | AP75: =IF(OR($AK75="",$AO75="",$AO75=0),"",($AO75-$AK75)/$AO75) | AQ75: =IF($AK75="","",IF(L75=$AK75,$K75,IF(R75=$AK75,$Q75,IF(X75=$AK75,$W75,IF(AD75=$AK75,$AC75,IF(AJ75=$AK75,$AI75,""))))))
A76: PP-VEG-ROCKET | B76: Vegetables | C76: Rocket leaves | D76: g | E76: 0.95 | F76: Pesto finish | L76: =IF(OR($J76="",$H76="",$H76=0),"",$J76/(1+IF(IFERROR(INDEX('03 Suppliers'!$N$5:$N$34,MATCH($G76,'03 Suppliers'!$B$5:$B$34,0)),"Excl VAT")="Incl VAT",'01 Control'!$C$6,0))/($H76*IFERROR(VLOOKUP($I76,'02 Lists'!$A$5:$B$18,2,FALSE()),1))) | R76: =IF(OR($P76="",$N76="",$N76=0),"",$P76/(1+IF(IFERROR(INDEX('03 Suppliers'!$N$5:$N$34,MATCH($M76,'03 Suppliers'!$B$5:$B$34,0)),"Excl VAT")="Incl VAT",'01 Control'!$C$6,0))/($N76*IFERROR(VLOOKUP($O76,'02 Lists'!$A$5:$B$18,2,FALSE()),1))) | X76: =IF(OR($V76="",$T76="",$T76=0),"",$V76/(1+IF(IFERROR(INDEX('03 Suppliers'!$N$5:$N$34,MATCH($S76,'03 Suppliers'!$B$5:$B$34,0)),"Excl VAT")="Incl VAT",'01 Control'!$C$6,0))/($T76*IFERROR(VLOOKUP($U76,'02 Lists'!$A$5:$B$18,2,FALSE()),1))) | AD76: =IF(OR($AB76="",$Z76="",$Z76=0),"",$AB76/(1+IF(IFERROR(INDEX('03 Suppliers'!$N$5:$N$34,MATCH($Y76,'03 Suppliers'!$B$5:$B$34,0)),"Excl VAT")="Incl VAT",'01 Control'!$C$6,0))/($Z76*IFERROR(VLOOKUP($AA76,'02 Lists'!$A$5:$B$18,2,FALSE()),1))) | AJ76: =IF(OR($AH76="",$AF76="",$AF76=0),"",$AH76/(1+IF(IFERROR(INDEX('03 Suppliers'!$N$5:$N$34,MATCH($AE76,'03 Suppliers'!$B$5:$B$34,0)),"Excl VAT")="Incl VAT",'01 Control'!$C$6,0))/($AF76*IFERROR(VLOOKUP($AG76,'02 Lists'!$A$5:$B$18,2,FALSE()),1))) | AK76: =IF(COUNT(L76,R76,X76,AD76,AJ76)=0,"",MIN(L76,R76,X76,AD76,AJ76)) | AL76: =IF($AK76="","",IF(L76=$AK76,$G76,IF(R76=$AK76,$M76,IF(X76=$AK76,$S76,IF(AD76=$AK76,$Y76,IF(AJ76=$AK76,$AE76,"")))))) | AM76: =IF($AK76="","",$AK76/IF($E76="",1,$E76)) | AN76: =COUNT(L76,R76,X76,AD76,AJ76) | AO76: =IF(COUNT(L76,R76,X76,AD76,AJ76)=0,"",MAX(L76,R76,X76,AD76,AJ76)) | AP76: =IF(OR($AK76="",$AO76="",$AO76=0),"",($AO76-$AK76)/$AO76) | AQ76: =IF($AK76="","",IF(L76=$AK76,$K76,IF(R76=$AK76,$Q76,IF(X76=$AK76,$W76,IF(AD76=$AK76,$AC76,IF(AJ76=$AK76,$AI76,""))))))
A77: PP-GRO-MSH-001 | B77: Mushroom (TLF) | C77: Grey oyster mushrooms | D77: g | E77: 0.95 | F77: The Local Farmer | G77: The Local Farmer | H77: 1 | I77: kg | J77: 563.14 | K77: 46251 | L77: =IF(OR($J77="",$H77="",$H77=0),"",$J77/(1+IF(IFERROR(INDEX('03 Suppliers'!$N$5:$N$34,MATCH($G77,'03 Suppliers'!$B$5:$B$34,0)),"Excl VAT")="Incl VAT",'01 Control'!$C$6,0))/($H77*IFERROR(VLOOKUP($I77,'02 Lists'!$A$5:$B$18,2,FALSE()),1))) | R77: =IF(OR($P77="",$N77="",$N77=0),"",$P77/(1+IF(IFERROR(INDEX('03 Suppliers'!$N$5:$N$34,MATCH($M77,'03 Suppliers'!$B$5:$B$34,0)),"Excl VAT")="Incl VAT",'01 Control'!$C$6,0))/($N77*IFERROR(VLOOKUP($O77,'02 Lists'!$A$5:$B$18,2,FALSE()),1))) | X77: =IF(OR($V77="",$T77="",$T77=0),"",$V77/(1+IF(IFERROR(INDEX('03 Suppliers'!$N$5:$N$34,MATCH($S77,'03 Suppliers'!$B$5:$B$34,0)),"Excl VAT")="Incl VAT",'01 Control'!$C$6,0))/($T77*IFERROR(VLOOKUP($U77,'02 Lists'!$A$5:$B$18,2,FALSE()),1))) | AD77: =IF(OR($AB77="",$Z77="",$Z77=0),"",$AB77/(1+IF(IFERROR(INDEX('03 Suppliers'!$N$5:$N$34,MATCH($Y77,'03 Suppliers'!$B$5:$B$34,0)),"Excl VAT")="Incl VAT",'01 Control'!$C$6,0))/($Z77*IFERROR(VLOOKUP($AA77,'02 Lists'!$A$5:$B$18,2,FALSE()),1))) | AJ77: =IF(OR($AH77="",$AF77="",$AF77=0),"",$AH77/(1+IF(IFERROR(INDEX('03 Suppliers'!$N$5:$N$34,MATCH($AE77,'03 Suppliers'!$B$5:$B$34,0)),"Excl VAT")="Incl VAT",'01 Control'!$C$6,0))/($AF77*IFERROR(VLOOKUP($AG77,'02 Lists'!$A$5:$B$18,2,FALSE()),1))) | AK77: =IF(COUNT(L77,R77,X77,AD77,AJ77)=0,"",MIN(L77,R77,X77,AD77,AJ77)) | AL77: =IF($AK77="","",IF(L77=$AK77,$G77,IF(R77=$AK77,$M77,IF(X77=$AK77,$S77,IF(AD77=$AK77,$Y77,IF(AJ77=$AK77,$AE77,"")))))) | AM77: =IF($AK77="","",$AK77/IF($E77="",1,$E77)) | AN77: =COUNT(L77,R77,X77,AD77,AJ77) | AO77: =IF(COUNT(L77,R77,X77,AD77,AJ77)=0,"",MAX(L77,R77,X77,AD77,AJ77)) | AP77: =IF(OR($AK77="",$AO77="",$AO77=0),"",($AO77-$AK77)/$AO77) | AQ77: =IF($AK77="","",IF(L77=$AK77,$K77,IF(R77=$AK77,$Q77,IF(X77=$AK77,$W77,IF(AD77=$AK77,$AC77,IF(AJ77=$AK77,$AI77,""))))))
A78: PP-KO-MSH-002 | B78: Mushroom (TLF) | C78: King oyster mushrooms | D78: g | E78: 0.95 | F78: The Local Farmer | G78: The Local Farmer | H78: 1 | I78: kg | J78: 563.14 | K78: 46251 | L78: =IF(OR($J78="",$H78="",$H78=0),"",$J78/(1+IF(IFERROR(INDEX('03 Suppliers'!$N$5:$N$34,MATCH($G78,'03 Suppliers'!$B$5:$B$34,0)),"Excl VAT")="Incl VAT",'01 Control'!$C$6,0))/($H78*IFERROR(VLOOKUP($I78,'02 Lists'!$A$5:$B$18,2,FALSE()),1))) | R78: =IF(OR($P78="",$N78="",$N78=0),"",$P78/(1+IF(IFERROR(INDEX('03 Suppliers'!$N$5:$N$34,MATCH($M78,'03 Suppliers'!$B$5:$B$34,0)),"Excl VAT")="Incl VAT",'01 Control'!$C$6,0))/($N78*IFERROR(VLOOKUP($O78,'02 Lists'!$A$5:$B$18,2,FALSE()),1))) | X78: =IF(OR($V78="",$T78="",$T78=0),"",$V78/(1+IF(IFERROR(INDEX('03 Suppliers'!$N$5:$N$34,MATCH($S78,'03 Suppliers'!$B$5:$B$34,0)),"Excl VAT")="Incl VAT",'01 Control'!$C$6,0))/($T78*IFERROR(VLOOKUP($U78,'02 Lists'!$A$5:$B$18,2,FALSE()),1))) | AD78: =IF(OR($AB78="",$Z78="",$Z78=0),"",$AB78/(1+IF(IFERROR(INDEX('03 Suppliers'!$N$5:$N$34,MATCH($Y78,'03 Suppliers'!$B$5:$B$34,0)),"Excl VAT")="Incl VAT",'01 Control'!$C$6,0))/($Z78*IFERROR(VLOOKUP($AA78,'02 Lists'!$A$5:$B$18,2,FALSE()),1))) | AJ78: =IF(OR($AH78="",$AF78="",$AF78=0),"",$AH78/(1+IF(IFERROR(INDEX('03 Suppliers'!$N$5:$N$34,MATCH($AE78,'03 Suppliers'!$B$5:$B$34,0)),"Excl VAT")="Incl VAT",'01 Control'!$C$6,0))/($AF78*IFERROR(VLOOKUP($AG78,'02 Lists'!$A$5:$B$18,2,FALSE()),1))) | AK78: =IF(COUNT(L78,R78,X78,AD78,AJ78)=0,"",MIN(L78,R78,X78,AD78,AJ78)) | AL78: =IF($AK78="","",IF(L78=$AK78,$G78,IF(R78=$AK78,$M78,IF(X78=$AK78,$S78,IF(AD78=$AK78,$Y78,IF(AJ78=$AK78,$AE78,"")))))) | AM78: =IF($AK78="","",$AK78/IF($E78="",1,$E78)) | AN78: =COUNT(L78,R78,X78,AD78,AJ78) | AO78: =IF(COUNT(L78,R78,X78,AD78,AJ78)=0,"",MAX(L78,R78,X78,AD78,AJ78)) | AP78: =IF(OR($AK78="",$AO78="",$AO78=0),"",($AO78-$AK78)/$AO78) | AQ78: =IF($AK78="","",IF(L78=$AK78,$K78,IF(R78=$AK78,$Q78,IF(X78=$AK78,$W78,IF(AD78=$AK78,$AC78,IF(AJ78=$AK78,$AI78,""))))))
A79: PP-BA-MIC-001 | B79: Microgreen | C79: Basil microgreens | D79: g | E79: 1 | F79: The Local Farmer | G79: The Local Farmer | H79: 1 | I79: kg | J79: 362.96 | K79: 46251 | L79: =IF(OR($J79="",$H79="",$H79=0),"",$J79/(1+IF(IFERROR(INDEX('03 Suppliers'!$N$5:$N$34,MATCH($G79,'03 Suppliers'!$B$5:$B$34,0)),"Excl VAT")="Incl VAT",'01 Control'!$C$6,0))/($H79*IFERROR(VLOOKUP($I79,'02 Lists'!$A$5:$B$18,2,FALSE()),1))) | R79: =IF(OR($P79="",$N79="",$N79=0),"",$P79/(1+IF(IFERROR(INDEX('03 Suppliers'!$N$5:$N$34,MATCH($M79,'03 Suppliers'!$B$5:$B$34,0)),"Excl VAT")="Incl VAT",'01 Control'!$C$6,0))/($N79*IFERROR(VLOOKUP($O79,'02 Lists'!$A$5:$B$18,2,FALSE()),1))) | X79: =IF(OR($V79="",$T79="",$T79=0),"",$V79/(1+IF(IFERROR(INDEX('03 Suppliers'!$N$5:$N$34,MATCH($S79,'03 Suppliers'!$B$5:$B$34,0)),"Excl VAT")="Incl VAT",'01 Control'!$C$6,0))/($T79*IFERROR(VLOOKUP($U79,'02 Lists'!$A$5:$B$18,2,FALSE()),1))) | AD79: =IF(OR($AB79="",$Z79="",$Z79=0),"",$AB79/(1+IF(IFERROR(INDEX('03 Suppliers'!$N$5:$N$34,MATCH($Y79,'03 Suppliers'!$B$5:$B$34,0)),"Excl VAT")="Incl VAT",'01 Control'!$C$6,0))/($Z79*IFERROR(VLOOKUP($AA79,'02 Lists'!$A$5:$B$18,2,FALSE()),1))) | AJ79: =IF(OR($AH79="",$AF79="",$AF79=0),"",$AH79/(1+IF(IFERROR(INDEX('03 Suppliers'!$N$5:$N$34,MATCH($AE79,'03 Suppliers'!$B$5:$B$34,0)),"Excl VAT")="Incl VAT",'01 Control'!$C$6,0))/($AF79*IFERROR(VLOOKUP($AG79,'02 Lists'!$A$5:$B$18,2,FALSE()),1))) | AK79: =IF(COUNT(L79,R79,X79,AD79,AJ79)=0,"",MIN(L79,R79,X79,AD79,AJ79)) | AL79: =IF($AK79="","",IF(L79=$AK79,$G79,IF(R79=$AK79,$M79,IF(X79=$AK79,$S79,IF(AD79=$AK79,$Y79,IF(AJ79=$AK79,$AE79,"")))))) | AM79: =IF($AK79="","",$AK79/IF($E79="",1,$E79)) | AN79: =COUNT(L79,R79,X79,AD79,AJ79) | AO79: =IF(COUNT(L79,R79,X79,AD79,AJ79)=0,"",MAX(L79,R79,X79,AD79,AJ79)) | AP79: =IF(OR($AK79="",$AO79="",$AO79=0),"",($AO79-$AK79)/$AO79) | AQ79: =IF($AK79="","",IF(L79=$AK79,$K79,IF(R79=$AK79,$Q79,IF(X79=$AK79,$W79,IF(AD79=$AK79,$AC79,IF(AJ79=$AK79,$AI79,""))))))
A80: PP-ROC-MIC-002 | B80: Microgreen | C80: Rocket microgreens | D80: g | E80: 1 | F80: The Local Farmer | G80: The Local Farmer | H80: 1 | I80: kg | J80: 287.42 | K80: 46251 | L80: =IF(OR($J80="",$H80="",$H80=0),"",$J80/(1+IF(IFERROR(INDEX('03 Suppliers'!$N$5:$N$34,MATCH($G80,'03 Suppliers'!$B$5:$B$34,0)),"Excl VAT")="Incl VAT",'01 Control'!$C$6,0))/($H80*IFERROR(VLOOKUP($I80,'02 Lists'!$A$5:$B$18,2,FALSE()),1))) | R80: =IF(OR($P80="",$N80="",$N80=0),"",$P80/(1+IF(IFERROR(INDEX('03 Suppliers'!$N$5:$N$34,MATCH($M80,'03 Suppliers'!$B$5:$B$34,0)),"Excl VAT")="Incl VAT",'01 Control'!$C$6,0))/($N80*IFERROR(VLOOKUP($O80,'02 Lists'!$A$5:$B$18,2,FALSE()),1))) | X80: =IF(OR($V80="",$T80="",$T80=0),"",$V80/(1+IF(IFERROR(INDEX('03 Suppliers'!$N$5:$N$34,MATCH($S80,'03 Suppliers'!$B$5:$B$34,0)),"Excl VAT")="Incl VAT",'01 Control'!$C$6,0))/($T80*IFERROR(VLOOKUP($U80,'02 Lists'!$A$5:$B$18,2,FALSE()),1))) | AD80: =IF(OR($AB80="",$Z80="",$Z80=0),"",$AB80/(1+IF(IFERROR(INDEX('03 Suppliers'!$N$5:$N$34,MATCH($Y80,'03 Suppliers'!$B$5:$B$34,0)),"Excl VAT")="Incl VAT",'01 Control'!$C$6,0))/($Z80*IFERROR(VLOOKUP($AA80,'02 Lists'!$A$5:$B$18,2,FALSE()),1))) | AJ80: =IF(OR($AH80="",$AF80="",$AF80=0),"",$AH80/(1+IF(IFERROR(INDEX('03 Suppliers'!$N$5:$N$34,MATCH($AE80,'03 Suppliers'!$B$5:$B$34,0)),"Excl VAT")="Incl VAT",'01 Control'!$C$6,0))/($AF80*IFERROR(VLOOKUP($AG80,'02 Lists'!$A$5:$B$18,2,FALSE()),1))) | AK80: =IF(COUNT(L80,R80,X80,AD80,AJ80)=0,"",MIN(L80,R80,X80,AD80,AJ80)) | AL80: =IF($AK80="","",IF(L80=$AK80,$G80,IF(R80=$AK80,$M80,IF(X80=$AK80,$S80,IF(AD80=$AK80,$Y80,IF(AJ80=$AK80,$AE80,"")))))) | AM80: =IF($AK80="","",$AK80/IF($E80="",1,$E80)) | AN80: =COUNT(L80,R80,X80,AD80,AJ80) | AO80: =IF(COUNT(L80,R80,X80,AD80,AJ80)=0,"",MAX(L80,R80,X80,AD80,AJ80)) | AP80: =IF(OR($AK80="",$AO80="",$AO80=0),"",($AO80-$AK80)/$AO80) | AQ80: =IF($AK80="","",IF(L80=$AK80,$K80,IF(R80=$AK80,$Q80,IF(X80=$AK80,$W80,IF(AD80=$AK80,$AC80,IF(AJ80=$AK80,$AI80,""))))))
A81: PP-RAD-MIC-003 | B81: Microgreen | C81: Radish microgreens | D81: g | E81: 1 | F81: The Local Farmer CHECK THE UNIT: the carried-over quote reads R19.06/kg, which is out of line with the rest of the list. Confirm per-kg vs pack price before this reaches a menu price. | G81: The Local Farmer | H81: 1 | I81: kg | J81: 19.06 | K81: 46251 | L81: =IF(OR($J81="",$H81="",$H81=0),"",$J81/(1+IF(IFERROR(INDEX('03 Suppliers'!$N$5:$N$34,MATCH($G81,'03 Suppliers'!$B$5:$B$34,0)),"Excl VAT")="Incl VAT",'01 Control'!$C$6,0))/($H81*IFERROR(VLOOKUP($I81,'02 Lists'!$A$5:$B$18,2,FALSE()),1))) | R81: =IF(OR($P81="",$N81="",$N81=0),"",$P81/(1+IF(IFERROR(INDEX('03 Suppliers'!$N$5:$N$34,MATCH($M81,'03 Suppliers'!$B$5:$B$34,0)),"Excl VAT")="Incl VAT",'01 Control'!$C$6,0))/($N81*IFERROR(VLOOKUP($O81,'02 Lists'!$A$5:$B$18,2,FALSE()),1))) | X81: =IF(OR($V81="",$T81="",$T81=0),"",$V81/(1+IF(IFERROR(INDEX('03 Suppliers'!$N$5:$N$34,MATCH($S81,'03 Suppliers'!$B$5:$B$34,0)),"Excl VAT")="Incl VAT",'01 Control'!$C$6,0))/($T81*IFERROR(VLOOKUP($U81,'02 Lists'!$A$5:$B$18,2,FALSE()),1))) | AD81: =IF(OR($AB81="",$Z81="",$Z81=0),"",$AB81/(1+IF(IFERROR(INDEX('03 Suppliers'!$N$5:$N$34,MATCH($Y81,'03 Suppliers'!$B$5:$B$34,0)),"Excl VAT")="Incl VAT",'01 Control'!$C$6,0))/($Z81*IFERROR(VLOOKUP($AA81,'02 Lists'!$A$5:$B$18,2,FALSE()),1))) | AJ81: =IF(OR($AH81="",$AF81="",$AF81=0),"",$AH81/(1+IF(IFERROR(INDEX('03 Suppliers'!$N$5:$N$34,MATCH($AE81,'03 Suppliers'!$B$5:$B$34,0)),"Excl VAT")="Incl VAT",'01 Control'!$C$6,0))/($AF81*IFERROR(VLOOKUP($AG81,'02 Lists'!$A$5:$B$18,2,FALSE()),1))) | AK81: =IF(COUNT(L81,R81,X81,AD81,AJ81)=0,"",MIN(L81,R81,X81,AD81,AJ81)) | AL81: =IF($AK81="","",IF(L81=$AK81,$G81,IF(R81=$AK81,$M81,IF(X81=$AK81,$S81,IF(AD81=$AK81,$Y81,IF(AJ81=$AK81,$AE81,"")))))) | AM81: =IF($AK81="","",$AK81/IF($E81="",1,$E81)) | AN81: =COUNT(L81,R81,X81,AD81,AJ81) | AO81: =IF(COUNT(L81,R81,X81,AD81,AJ81)=0,"",MAX(L81,R81,X81,AD81,AJ81)) | AP81: =IF(OR($AK81="",$AO81="",$AO81=0),"",($AO81-$AK81)/$AO81) | AQ81: =IF($AK81="","",IF(L81=$AK81,$K81,IF(R81=$AK81,$Q81,IF(X81=$AK81,$W81,IF(AD81=$AK81,$AC81,IF(AJ81=$AK81,$AI81,""))))))
A82: PP-AMR-MIC-004 | B82: Microgreen | C82: Amaranth microgreens | D82: g | E82: 1 | F82: The Local Farmer | G82: The Local Farmer | H82: 1 | I82: kg | J82: 527.14 | K82: 46251 | L82: =IF(OR($J82="",$H82="",$H82=0),"",$J82/(1+IF(IFERROR(INDEX('03 Suppliers'!$N$5:$N$34,MATCH($G82,'03 Suppliers'!$B$5:$B$34,0)),"Excl VAT")="Incl VAT",'01 Control'!$C$6,0))/($H82*IFERROR(VLOOKUP($I82,'02 Lists'!$A$5:$B$18,2,FALSE()),1))) | R82: =IF(OR($P82="",$N82="",$N82=0),"",$P82/(1+IF(IFERROR(INDEX('03 Suppliers'!$N$5:$N$34,MATCH($M82,'03 Suppliers'!$B$5:$B$34,0)),"Excl VAT")="Incl VAT",'01 Control'!$C$6,0))/($N82*IFERROR(VLOOKUP($O82,'02 Lists'!$A$5:$B$18,2,FALSE()),1))) | X82: =IF(OR($V82="",$T82="",$T82=0),"",$V82/(1+IF(IFERROR(INDEX('03 Suppliers'!$N$5:$N$34,MATCH($S82,'03 Suppliers'!$B$5:$B$34,0)),"Excl VAT")="Incl VAT",'01 Control'!$C$6,0))/($T82*IFERROR(VLOOKUP($U82,'02 Lists'!$A$5:$B$18,2,FALSE()),1))) | AD82: =IF(OR($AB82="",$Z82="",$Z82=0),"",$AB82/(1+IF(IFERROR(INDEX('03 Suppliers'!$N$5:$N$34,MATCH($Y82,'03 Suppliers'!$B$5:$B$34,0)),"Excl VAT")="Incl VAT",'01 Control'!$C$6,0))/($Z82*IFERROR(VLOOKUP($AA82,'02 Lists'!$A$5:$B$18,2,FALSE()),1))) | AJ82: =IF(OR($AH82="",$AF82="",$AF82=0),"",$AH82/(1+IF(IFERROR(INDEX('03 Suppliers'!$N$5:$N$34,MATCH($AE82,'03 Suppliers'!$B$5:$B$34,0)),"Excl VAT")="Incl VAT",'01 Control'!$C$6,0))/($AF82*IFERROR(VLOOKUP($AG82,'02 Lists'!$A$5:$B$18,2,FALSE()),1))) | AK82: =IF(COUNT(L82,R82,X82,AD82,AJ82)=0,"",MIN(L82,R82,X82,AD82,AJ82)) | AL82: =IF($AK82="","",IF(L82=$AK82,$G82,IF(R82=$AK82,$M82,IF(X82=$AK82,$S82,IF(AD82=$AK82,$Y82,IF(AJ82=$AK82,$AE82,"")))))) | AM82: =IF($AK82="","",$AK82/IF($E82="",1,$E82)) | AN82: =COUNT(L82,R82,X82,AD82,AJ82) | AO82: =IF(COUNT(L82,R82,X82,AD82,AJ82)=0,"",MAX(L82,R82,X82,AD82,AJ82)) | AP82: =IF(OR($AK82="",$AO82="",$AO82=0),"",($AO82-$AK82)/$AO82) | AQ82: =IF($AK82="","",IF(L82=$AK82,$K82,IF(R82=$AK82,$Q82,IF(X82=$AK82,$W82,IF(AD82=$AK82,$AC82,IF(AJ82=$AK82,$AI82,""))))))
A83: PP-PEA-MIC-005 | B83: Microgreen | C83: Pea shoot microgreens | D83: g | E83: 1 | F83: The Local Farmer | G83: The Local Farmer | H83: 1 | I83: kg | J83: 152.3 | K83: 46251 | L83: =IF(OR($J83="",$H83="",$H83=0),"",$J83/(1+IF(IFERROR(INDEX('03 Suppliers'!$N$5:$N$34,MATCH($G83,'03 Suppliers'!$B$5:$B$34,0)),"Excl VAT")="Incl VAT",'01 Control'!$C$6,0))/($H83*IFERROR(VLOOKUP($I83,'02 Lists'!$A$5:$B$18,2,FALSE()),1))) | R83: =IF(OR($P83="",$N83="",$N83=0),"",$P83/(1+IF(IFERROR(INDEX('03 Suppliers'!$N$5:$N$34,MATCH($M83,'03 Suppliers'!$B$5:$B$34,0)),"Excl VAT")="Incl VAT",'01 Control'!$C$6,0))/($N83*IFERROR(VLOOKUP($O83,'02 Lists'!$A$5:$B$18,2,FALSE()),1))) | X83: =IF(OR($V83="",$T83="",$T83=0),"",$V83/(1+IF(IFERROR(INDEX('03 Suppliers'!$N$5:$N$34,MATCH($S83,'03 Suppliers'!$B$5:$B$34,0)),"Excl VAT")="Incl VAT",'01 Control'!$C$6,0))/($T83*IFERROR(VLOOKUP($U83,'02 Lists'!$A$5:$B$18,2,FALSE()),1))) | AD83: =IF(OR($AB83="",$Z83="",$Z83=0),"",$AB83/(1+IF(IFERROR(INDEX('03 Suppliers'!$N$5:$N$34,MATCH($Y83,'03 Suppliers'!$B$5:$B$34,0)),"Excl VAT")="Incl VAT",'01 Control'!$C$6,0))/($Z83*IFERROR(VLOOKUP($AA83,'02 Lists'!$A$5:$B$18,2,FALSE()),1))) | AJ83: =IF(OR($AH83="",$AF83="",$AF83=0),"",$AH83/(1+IF(IFERROR(INDEX('03 Suppliers'!$N$5:$N$34,MATCH($AE83,'03 Suppliers'!$B$5:$B$34,0)),"Excl VAT")="Incl VAT",'01 Control'!$C$6,0))/($AF83*IFERROR(VLOOKUP($AG83,'02 Lists'!$A$5:$B$18,2,FALSE()),1))) | AK83: =IF(COUNT(L83,R83,X83,AD83,AJ83)=0,"",MIN(L83,R83,X83,AD83,AJ83)) | AL83: =IF($AK83="","",IF(L83=$AK83,$G83,IF(R83=$AK83,$M83,IF(X83=$AK83,$S83,IF(AD83=$AK83,$Y83,IF(AJ83=$AK83,$AE83,"")))))) | AM83: =IF($AK83="","",$AK83/IF($E83="",1,$E83)) | AN83: =COUNT(L83,R83,X83,AD83,AJ83) | AO83: =IF(COUNT(L83,R83,X83,AD83,AJ83)=0,"",MAX(L83,R83,X83,AD83,AJ83)) | AP83: =IF(OR($AK83="",$AO83="",$AO83=0),"",($AO83-$AK83)/$AO83) | AQ83: =IF($AK83="","",IF(L83=$AK83,$K83,IF(R83=$AK83,$Q83,IF(X83=$AK83,$W83,IF(AD83=$AK83,$AC83,IF(AJ83=$AK83,$AI83,""))))))
A84: PP-SUN-MIC-006 | B84: Microgreen | C84: Sunflower microgreens | D84: g | E84: 1 | F84: The Local Farmer | G84: The Local Farmer | H84: 1 | I84: kg | J84: 193.16 | K84: 46251 | L84: =IF(OR($J84="",$H84="",$H84=0),"",$J84/(1+IF(IFERROR(INDEX('03 Suppliers'!$N$5:$N$34,MATCH($G84,'03 Suppliers'!$B$5:$B$34,0)),"Excl VAT")="Incl VAT",'01 Control'!$C$6,0))/($H84*IFERROR(VLOOKUP($I84,'02 Lists'!$A$5:$B$18,2,FALSE()),1))) | R84: =IF(OR($P84="",$N84="",$N84=0),"",$P84/(1+IF(IFERROR(INDEX('03 Suppliers'!$N$5:$N$34,MATCH($M84,'03 Suppliers'!$B$5:$B$34,0)),"Excl VAT")="Incl VAT",'01 Control'!$C$6,0))/($N84*IFERROR(VLOOKUP($O84,'02 Lists'!$A$5:$B$18,2,FALSE()),1))) | X84: =IF(OR($V84="",$T84="",$T84=0),"",$V84/(1+IF(IFERROR(INDEX('03 Suppliers'!$N$5:$N$34,MATCH($S84,'03 Suppliers'!$B$5:$B$34,0)),"Excl VAT")="Incl VAT",'01 Control'!$C$6,0))/($T84*IFERROR(VLOOKUP($U84,'02 Lists'!$A$5:$B$18,2,FALSE()),1))) | AD84: =IF(OR($AB84="",$Z84="",$Z84=0),"",$AB84/(1+IF(IFERROR(INDEX('03 Suppliers'!$N$5:$N$34,MATCH($Y84,'03 Suppliers'!$B$5:$B$34,0)),"Excl VAT")="Incl VAT",'01 Control'!$C$6,0))/($Z84*IFERROR(VLOOKUP($AA84,'02 Lists'!$A$5:$B$18,2,FALSE()),1))) | AJ84: =IF(OR($AH84="",$AF84="",$AF84=0),"",$AH84/(1+IF(IFERROR(INDEX('03 Suppliers'!$N$5:$N$34,MATCH($AE84,'03 Suppliers'!$B$5:$B$34,0)),"Excl VAT")="Incl VAT",'01 Control'!$C$6,0))/($AF84*IFERROR(VLOOKUP($AG84,'02 Lists'!$A$5:$B$18,2,FALSE()),1))) | AK84: =IF(COUNT(L84,R84,X84,AD84,AJ84)=0,"",MIN(L84,R84,X84,AD84,AJ84)) | AL84: =IF($AK84="","",IF(L84=$AK84,$G84,IF(R84=$AK84,$M84,IF(X84=$AK84,$S84,IF(AD84=$AK84,$Y84,IF(AJ84=$AK84,$AE84,"")))))) | AM84: =IF($AK84="","",$AK84/IF($E84="",1,$E84)) | AN84: =COUNT(L84,R84,X84,AD84,AJ84) | AO84: =IF(COUNT(L84,R84,X84,AD84,AJ84)=0,"",MAX(L84,R84,X84,AD84,AJ84)) | AP84: =IF(OR($AK84="",$AO84="",$AO84=0),"",($AO84-$AK84)/$AO84) | AQ84: =IF($AK84="","",IF(L84=$AK84,$K84,IF(R84=$AK84,$Q84,IF(X84=$AK84,$W84,IF(AD84=$AK84,$AC84,IF(AJ84=$AK84,$AI84,""))))))
A85: PP-NUT-PINE | B85: Nuts / Seeds | C85: Pine nuts / toasted nuts (pesto) | D85: g | E85: 1 | F85: NUT ALLERGEN | L85: =IF(OR($J85="",$H85="",$H85=0),"",$J85/(1+IF(IFERROR(INDEX('03 Suppliers'!$N$5:$N$34,MATCH($G85,'03 Suppliers'!$B$5:$B$34,0)),"Excl VAT")="Incl VAT",'01 Control'!$C$6,0))/($H85*IFERROR(VLOOKUP($I85,'02 Lists'!$A$5:$B$18,2,FALSE()),1))) | R85: =IF(OR($P85="",$N85="",$N85=0),"",$P85/(1+IF(IFERROR(INDEX('03 Suppliers'!$N$5:$N$34,MATCH($M85,'03 Suppliers'!$B$5:$B$34,0)),"Excl VAT")="Incl VAT",'01 Control'!$C$6,0))/($N85*IFERROR(VLOOKUP($O85,'02 Lists'!$A$5:$B$18,2,FALSE()),1))) | X85: =IF(OR($V85="",$T85="",$T85=0),"",$V85/(1+IF(IFERROR(INDEX('03 Suppliers'!$N$5:$N$34,MATCH($S85,'03 Suppliers'!$B$5:$B$34,0)),"Excl VAT")="Incl VAT",'01 Control'!$C$6,0))/($T85*IFERROR(VLOOKUP($U85,'02 Lists'!$A$5:$B$18,2,FALSE()),1))) | AD85: =IF(OR($AB85="",$Z85="",$Z85=0),"",$AB85/(1+IF(IFERROR(INDEX('03 Suppliers'!$N$5:$N$34,MATCH($Y85,'03 Suppliers'!$B$5:$B$34,0)),"Excl VAT")="Incl VAT",'01 Control'!$C$6,0))/($Z85*IFERROR(VLOOKUP($AA85,'02 Lists'!$A$5:$B$18,2,FALSE()),1))) | AJ85: =IF(OR($AH85="",$AF85="",$AF85=0),"",$AH85/(1+IF(IFERROR(INDEX('03 Suppliers'!$N$5:$N$34,MATCH($AE85,'03 Suppliers'!$B$5:$B$34,0)),"Excl VAT")="Incl VAT",'01 Control'!$C$6,0))/($AF85*IFERROR(VLOOKUP($AG85,'02 Lists'!$A$5:$B$18,2,FALSE()),1))) | AK85: =IF(COUNT(L85,R85,X85,AD85,AJ85)=0,"",MIN(L85,R85,X85,AD85,AJ85)) | AL85: =IF($AK85="","",IF(L85=$AK85,$G85,IF(R85=$AK85,$M85,IF(X85=$AK85,$S85,IF(AD85=$AK85,$Y85,IF(AJ85=$AK85,$AE85,"")))))) | AM85: =IF($AK85="","",$AK85/IF($E85="",1,$E85)) | AN85: =COUNT(L85,R85,X85,AD85,AJ85) | AO85: =IF(COUNT(L85,R85,X85,AD85,AJ85)=0,"",MAX(L85,R85,X85,AD85,AJ85)) | AP85: =IF(OR($AK85="",$AO85="",$AO85=0),"",($AO85-$AK85)/$AO85) | AQ85: =IF($AK85="","",IF(L85=$AK85,$K85,IF(R85=$AK85,$Q85,IF(X85=$AK85,$W85,IF(AD85=$AK85,$AC85,IF(AJ85=$AK85,$AI85,""))))))
A86: PP-SEED-SUN | B86: Nuts / Seeds | C86: Sunflower seeds (nut-free pesto build) | D86: g | E86: 1 | F86: Nut-free alternative | L86: =IF(OR($J86="",$H86="",$H86=0),"",$J86/(1+IF(IFERROR(INDEX('03 Suppliers'!$N$5:$N$34,MATCH($G86,'03 Suppliers'!$B$5:$B$34,0)),"Excl VAT")="Incl VAT",'01 Control'!$C$6,0))/($H86*IFERROR(VLOOKUP($I86,'02 Lists'!$A$5:$B$18,2,FALSE()),1))) | R86: =IF(OR($P86="",$N86="",$N86=0),"",$P86/(1+IF(IFERROR(INDEX('03 Suppliers'!$N$5:$N$34,MATCH($M86,'03 Suppliers'!$B$5:$B$34,0)),"Excl VAT")="Incl VAT",'01 Control'!$C$6,0))/($N86*IFERROR(VLOOKUP($O86,'02 Lists'!$A$5:$B$18,2,FALSE()),1))) | X86: =IF(OR($V86="",$T86="",$T86=0),"",$V86/(1+IF(IFERROR(INDEX('03 Suppliers'!$N$5:$N$34,MATCH($S86,'03 Suppliers'!$B$5:$B$34,0)),"Excl VAT")="Incl VAT",'01 Control'!$C$6,0))/($T86*IFERROR(VLOOKUP($U86,'02 Lists'!$A$5:$B$18,2,FALSE()),1))) | AD86: =IF(OR($AB86="",$Z86="",$Z86=0),"",$AB86/(1+IF(IFERROR(INDEX('03 Suppliers'!$N$5:$N$34,MATCH($Y86,'03 Suppliers'!$B$5:$B$34,0)),"Excl VAT")="Incl VAT",'01 Control'!$C$6,0))/($Z86*IFERROR(VLOOKUP($AA86,'02 Lists'!$A$5:$B$18,2,FALSE()),1))) | AJ86: =IF(OR($AH86="",$AF86="",$AF86=0),"",$AH86/(1+IF(IFERROR(INDEX('03 Suppliers'!$N$5:$N$34,MATCH($AE86,'03 Suppliers'!$B$5:$B$34,0)),"Excl VAT")="Incl VAT",'01 Control'!$C$6,0))/($AF86*IFERROR(VLOOKUP($AG86,'02 Lists'!$A$5:$B$18,2,FALSE()),1))) | AK86: =IF(COUNT(L86,R86,X86,AD86,AJ86)=0,"",MIN(L86,R86,X86,AD86,AJ86)) | AL86: =IF($AK86="","",IF(L86=$AK86,$G86,IF(R86=$AK86,$M86,IF(X86=$AK86,$S86,IF(AD86=$AK86,$Y86,IF(AJ86=$AK86,$AE86,"")))))) | AM86: =IF($AK86="","",$AK86/IF($E86="",1,$E86)) | AN86: =COUNT(L86,R86,X86,AD86,AJ86) | AO86: =IF(COUNT(L86,R86,X86,AD86,AJ86)=0,"",MAX(L86,R86,X86,AD86,AJ86)) | AP86: =IF(OR($AK86="",$AO86="",$AO86=0),"",($AO86-$AK86)/$AO86) | AQ86: =IF($AK86="","",IF(L86=$AK86,$K86,IF(R86=$AK86,$Q86,IF(X86=$AK86,$W86,IF(AD86=$AK86,$AC86,IF(AJ86=$AK86,$AI86,""))))))
A87: PP-PEANUT-BUTTER | B87: Nuts / Seeds | C87: Groundnut / peanut butter | D87: g | E87: 1 | F87: PEANUT ALLERGEN - Y2 West Africa | L87: =IF(OR($J87="",$H87="",$H87=0),"",$J87/(1+IF(IFERROR(INDEX('03 Suppliers'!$N$5:$N$34,MATCH($G87,'03 Suppliers'!$B$5:$B$34,0)),"Excl VAT")="Incl VAT",'01 Control'!$C$6,0))/($H87*IFERROR(VLOOKUP($I87,'02 Lists'!$A$5:$B$18,2,FALSE()),1))) | R87: =IF(OR($P87="",$N87="",$N87=0),"",$P87/(1+IF(IFERROR(INDEX('03 Suppliers'!$N$5:$N$34,MATCH($M87,'03 Suppliers'!$B$5:$B$34,0)),"Excl VAT")="Incl VAT",'01 Control'!$C$6,0))/($N87*IFERROR(VLOOKUP($O87,'02 Lists'!$A$5:$B$18,2,FALSE()),1))) | X87: =IF(OR($V87="",$T87="",$T87=0),"",$V87/(1+IF(IFERROR(INDEX('03 Suppliers'!$N$5:$N$34,MATCH($S87,'03 Suppliers'!$B$5:$B$34,0)),"Excl VAT")="Incl VAT",'01 Control'!$C$6,0))/($T87*IFERROR(VLOOKUP($U87,'02 Lists'!$A$5:$B$18,2,FALSE()),1))) | AD87: =IF(OR($AB87="",$Z87="",$Z87=0),"",$AB87/(1+IF(IFERROR(INDEX('03 Suppliers'!$N$5:$N$34,MATCH($Y87,'03 Suppliers'!$B$5:$B$34,0)),"Excl VAT")="Incl VAT",'01 Control'!$C$6,0))/($Z87*IFERROR(VLOOKUP($AA87,'02 Lists'!$A$5:$B$18,2,FALSE()),1))) | AJ87: =IF(OR($AH87="",$AF87="",$AF87=0),"",$AH87/(1+IF(IFERROR(INDEX('03 Suppliers'!$N$5:$N$34,MATCH($AE87,'03 Suppliers'!$B$5:$B$34,0)),"Excl VAT")="Incl VAT",'01 Control'!$C$6,0))/($AF87*IFERROR(VLOOKUP($AG87,'02 Lists'!$A$5:$B$18,2,FALSE()),1))) | AK87: =IF(COUNT(L87,R87,X87,AD87,AJ87)=0,"",MIN(L87,R87,X87,AD87,AJ87)) | AL87: =IF($AK87="","",IF(L87=$AK87,$G87,IF(R87=$AK87,$M87,IF(X87=$AK87,$S87,IF(AD87=$AK87,$Y87,IF(AJ87=$AK87,$AE87,"")))))) | AM87: =IF($AK87="","",$AK87/IF($E87="",1,$E87)) | AN87: =COUNT(L87,R87,X87,AD87,AJ87) | AO87: =IF(COUNT(L87,R87,X87,AD87,AJ87)=0,"",MAX(L87,R87,X87,AD87,AJ87)) | AP87: =IF(OR($AK87="",$AO87="",$AO87=0),"",($AO87-$AK87)/$AO87) | AQ87: =IF($AK87="","",IF(L87=$AK87,$K87,IF(R87=$AK87,$Q87,IF(X87=$AK87,$W87,IF(AD87=$AK87,$AC87,IF(AJ87=$AK87,$AI87,""))))))
A88: PP-SPICE-PERIPERI | B88: Spice Blend | C88: Peri-peri spice / bird's-eye chilli blend | D88: g | E88: 1 | F88: Y1 Summer, Y2 Coast | L88: =IF(OR($J88="",$H88="",$H88=0),"",$J88/(1+IF(IFERROR(INDEX('03 Suppliers'!$N$5:$N$34,MATCH($G88,'03 Suppliers'!$B$5:$B$34,0)),"Excl VAT")="Incl VAT",'01 Control'!$C$6,0))/($H88*IFERROR(VLOOKUP($I88,'02 Lists'!$A$5:$B$18,2,FALSE()),1))) | R88: =IF(OR($P88="",$N88="",$N88=0),"",$P88/(1+IF(IFERROR(INDEX('03 Suppliers'!$N$5:$N$34,MATCH($M88,'03 Suppliers'!$B$5:$B$34,0)),"Excl VAT")="Incl VAT",'01 Control'!$C$6,0))/($N88*IFERROR(VLOOKUP($O88,'02 Lists'!$A$5:$B$18,2,FALSE()),1))) | X88: =IF(OR($V88="",$T88="",$T88=0),"",$V88/(1+IF(IFERROR(INDEX('03 Suppliers'!$N$5:$N$34,MATCH($S88,'03 Suppliers'!$B$5:$B$34,0)),"Excl VAT")="Incl VAT",'01 Control'!$C$6,0))/($T88*IFERROR(VLOOKUP($U88,'02 Lists'!$A$5:$B$18,2,FALSE()),1))) | AD88: =IF(OR($AB88="",$Z88="",$Z88=0),"",$AB88/(1+IF(IFERROR(INDEX('03 Suppliers'!$N$5:$N$34,MATCH($Y88,'03 Suppliers'!$B$5:$B$34,0)),"Excl VAT")="Incl VAT",'01 Control'!$C$6,0))/($Z88*IFERROR(VLOOKUP($AA88,'02 Lists'!$A$5:$B$18,2,FALSE()),1))) | AJ88: =IF(OR($AH88="",$AF88="",$AF88=0),"",$AH88/(1+IF(IFERROR(INDEX('03 Suppliers'!$N$5:$N$34,MATCH($AE88,'03 Suppliers'!$B$5:$B$34,0)),"Excl VAT")="Incl VAT",'01 Control'!$C$6,0))/($AF88*IFERROR(VLOOKUP($AG88,'02 Lists'!$A$5:$B$18,2,FALSE()),1))) | AK88: =IF(COUNT(L88,R88,X88,AD88,AJ88)=0,"",MIN(L88,R88,X88,AD88,AJ88)) | AL88: =IF($AK88="","",IF(L88=$AK88,$G88,IF(R88=$AK88,$M88,IF(X88=$AK88,$S88,IF(AD88=$AK88,$Y88,IF(AJ88=$AK88,$AE88,"")))))) | AM88: =IF($AK88="","",$AK88/IF($E88="",1,$E88)) | AN88: =COUNT(L88,R88,X88,AD88,AJ88) | AO88: =IF(COUNT(L88,R88,X88,AD88,AJ88)=0,"",MAX(L88,R88,X88,AD88,AJ88)) | AP88: =IF(OR($AK88="",$AO88="",$AO88=0),"",($AO88-$AK88)/$AO88) | AQ88: =IF($AK88="","",IF(L88=$AK88,$K88,IF(R88=$AK88,$Q88,IF(X88=$AK88,$W88,IF(AD88=$AK88,$AC88,IF(AJ88=$AK88,$AI88,""))))))
A89: PP-SPICE-BOEREWORS | B89: Spice Blend | C89: Boerewors spice (coriander-forward) | D89: g | E89: 1 | F89: Y1 Summer | L89: =IF(OR($J89="",$H89="",$H89=0),"",$J89/(1+IF(IFERROR(INDEX('03 Suppliers'!$N$5:$N$34,MATCH($G89,'03 Suppliers'!$B$5:$B$34,0)),"Excl VAT")="Incl VAT",'01 Control'!$C$6,0))/($H89*IFERROR(VLOOKUP($I89,'02 Lists'!$A$5:$B$18,2,FALSE()),1))) | R89: =IF(OR($P89="",$N89="",$N89=0),"",$P89/(1+IF(IFERROR(INDEX('03 Suppliers'!$N$5:$N$34,MATCH($M89,'03 Suppliers'!$B$5:$B$34,0)),"Excl VAT")="Incl VAT",'01 Control'!$C$6,0))/($N89*IFERROR(VLOOKUP($O89,'02 Lists'!$A$5:$B$18,2,FALSE()),1))) | X89: =IF(OR($V89="",$T89="",$T89=0),"",$V89/(1+IF(IFERROR(INDEX('03 Suppliers'!$N$5:$N$34,MATCH($S89,'03 Suppliers'!$B$5:$B$34,0)),"Excl VAT")="Incl VAT",'01 Control'!$C$6,0))/($T89*IFERROR(VLOOKUP($U89,'02 Lists'!$A$5:$B$18,2,FALSE()),1))) | AD89: =IF(OR($AB89="",$Z89="",$Z89=0),"",$AB89/(1+IF(IFERROR(INDEX('03 Suppliers'!$N$5:$N$34,MATCH($Y89,'03 Suppliers'!$B$5:$B$34,0)),"Excl VAT")="Incl VAT",'01 Control'!$C$6,0))/($Z89*IFERROR(VLOOKUP($AA89,'02 Lists'!$A$5:$B$18,2,FALSE()),1))) | AJ89: =IF(OR($AH89="",$AF89="",$AF89=0),"",$AH89/(1+IF(IFERROR(INDEX('03 Suppliers'!$N$5:$N$34,MATCH($AE89,'03 Suppliers'!$B$5:$B$34,0)),"Excl VAT")="Incl VAT",'01 Control'!$C$6,0))/($AF89*IFERROR(VLOOKUP($AG89,'02 Lists'!$A$5:$B$18,2,FALSE()),1))) | AK89: =IF(COUNT(L89,R89,X89,AD89,AJ89)=0,"",MIN(L89,R89,X89,AD89,AJ89)) | AL89: =IF($AK89="","",IF(L89=$AK89,$G89,IF(R89=$AK89,$M89,IF(X89=$AK89,$S89,IF(AD89=$AK89,$Y89,IF(AJ89=$AK89,$AE89,"")))))) | AM89: =IF($AK89="","",$AK89/IF($E89="",1,$E89)) | AN89: =COUNT(L89,R89,X89,AD89,AJ89) | AO89: =IF(COUNT(L89,R89,X89,AD89,AJ89)=0,"",MAX(L89,R89,X89,AD89,AJ89)) | AP89: =IF(OR($AK89="",$AO89="",$AO89=0),"",($AO89-$AK89)/$AO89) | AQ89: =IF($AK89="","",IF(L89=$AK89,$K89,IF(R89=$AK89,$Q89,IF(X89=$AK89,$W89,IF(AD89=$AK89,$AC89,IF(AJ89=$AK89,$AI89,""))))))
A90: PP-SPICE-DURBAN | B90: Spice Blend | C90: Durban masala (mother-in-law) | D90: g | E90: 1 | F90: Y1 Winter, Y3 bring-back | L90: =IF(OR($J90="",$H90="",$H90=0),"",$J90/(1+IF(IFERROR(INDEX('03 Suppliers'!$N$5:$N$34,MATCH($G90,'03 Suppliers'!$B$5:$B$34,0)),"Excl VAT")="Incl VAT",'01 Control'!$C$6,0))/($H90*IFERROR(VLOOKUP($I90,'02 Lists'!$A$5:$B$18,2,FALSE()),1))) | R90: =IF(OR($P90="",$N90="",$N90=0),"",$P90/(1+IF(IFERROR(INDEX('03 Suppliers'!$N$5:$N$34,MATCH($M90,'03 Suppliers'!$B$5:$B$34,0)),"Excl VAT")="Incl VAT",'01 Control'!$C$6,0))/($N90*IFERROR(VLOOKUP($O90,'02 Lists'!$A$5:$B$18,2,FALSE()),1))) | X90: =IF(OR($V90="",$T90="",$T90=0),"",$V90/(1+IF(IFERROR(INDEX('03 Suppliers'!$N$5:$N$34,MATCH($S90,'03 Suppliers'!$B$5:$B$34,0)),"Excl VAT")="Incl VAT",'01 Control'!$C$6,0))/($T90*IFERROR(VLOOKUP($U90,'02 Lists'!$A$5:$B$18,2,FALSE()),1))) | AD90: =IF(OR($AB90="",$Z90="",$Z90=0),"",$AB90/(1+IF(IFERROR(INDEX('03 Suppliers'!$N$5:$N$34,MATCH($Y90,'03 Suppliers'!$B$5:$B$34,0)),"Excl VAT")="Incl VAT",'01 Control'!$C$6,0))/($Z90*IFERROR(VLOOKUP($AA90,'02 Lists'!$A$5:$B$18,2,FALSE()),1))) | AJ90: =IF(OR($AH90="",$AF90="",$AF90=0),"",$AH90/(1+IF(IFERROR(INDEX('03 Suppliers'!$N$5:$N$34,MATCH($AE90,'03 Suppliers'!$B$5:$B$34,0)),"Excl VAT")="Incl VAT",'01 Control'!$C$6,0))/($AF90*IFERROR(VLOOKUP($AG90,'02 Lists'!$A$5:$B$18,2,FALSE()),1))) | AK90: =IF(COUNT(L90,R90,X90,AD90,AJ90)=0,"",MIN(L90,R90,X90,AD90,AJ90)) | AL90: =IF($AK90="","",IF(L90=$AK90,$G90,IF(R90=$AK90,$M90,IF(X90=$AK90,$S90,IF(AD90=$AK90,$Y90,IF(AJ90=$AK90,$AE90,"")))))) | AM90: =IF($AK90="","",$AK90/IF($E90="",1,$E90)) | AN90: =COUNT(L90,R90,X90,AD90,AJ90) | AO90: =IF(COUNT(L90,R90,X90,AD90,AJ90)=0,"",MAX(L90,R90,X90,AD90,AJ90)) | AP90: =IF(OR($AK90="",$AO90="",$AO90=0),"",($AO90-$AK90)/$AO90) | AQ90: =IF($AK90="","",IF(L90=$AK90,$K90,IF(R90=$AK90,$Q90,IF(X90=$AK90,$W90,IF(AD90=$AK90,$AC90,IF(AJ90=$AK90,$AI90,""))))))
A91: PP-SPICE-CHAKALAKA | B91: Spice Blend | C91: Chakalaka spice / relish base | D91: g | E91: 1 | F91: Y1 Spring | L91: =IF(OR($J91="",$H91="",$H91=0),"",$J91/(1+IF(IFERROR(INDEX('03 Suppliers'!$N$5:$N$34,MATCH($G91,'03 Suppliers'!$B$5:$B$34,0)),"Excl VAT")="Incl VAT",'01 Control'!$C$6,0))/($H91*IFERROR(VLOOKUP($I91,'02 Lists'!$A$5:$B$18,2,FALSE()),1))) | R91: =IF(OR($P91="",$N91="",$N91=0),"",$P91/(1+IF(IFERROR(INDEX('03 Suppliers'!$N$5:$N$34,MATCH($M91,'03 Suppliers'!$B$5:$B$34,0)),"Excl VAT")="Incl VAT",'01 Control'!$C$6,0))/($N91*IFERROR(VLOOKUP($O91,'02 Lists'!$A$5:$B$18,2,FALSE()),1))) | X91: =IF(OR($V91="",$T91="",$T91=0),"",$V91/(1+IF(IFERROR(INDEX('03 Suppliers'!$N$5:$N$34,MATCH($S91,'03 Suppliers'!$B$5:$B$34,0)),"Excl VAT")="Incl VAT",'01 Control'!$C$6,0))/($T91*IFERROR(VLOOKUP($U91,'02 Lists'!$A$5:$B$18,2,FALSE()),1))) | AD91: =IF(OR($AB91="",$Z91="",$Z91=0),"",$AB91/(1+IF(IFERROR(INDEX('03 Suppliers'!$N$5:$N$34,MATCH($Y91,'03 Suppliers'!$B$5:$B$34,0)),"Excl VAT")="Incl VAT",'01 Control'!$C$6,0))/($Z91*IFERROR(VLOOKUP($AA91,'02 Lists'!$A$5:$B$18,2,FALSE()),1))) | AJ91: =IF(OR($AH91="",$AF91="",$AF91=0),"",$AH91/(1+IF(IFERROR(INDEX('03 Suppliers'!$N$5:$N$34,MATCH($AE91,'03 Suppliers'!$B$5:$B$34,0)),"Excl VAT")="Incl VAT",'01 Control'!$C$6,0))/($AF91*IFERROR(VLOOKUP($AG91,'02 Lists'!$A$5:$B$18,2,FALSE()),1))) | AK91: =IF(COUNT(L91,R91,X91,AD91,AJ91)=0,"",MIN(L91,R91,X91,AD91,AJ91)) | AL91: =IF($AK91="","",IF(L91=$AK91,$G91,IF(R91=$AK91,$M91,IF(X91=$AK91,$S91,IF(AD91=$AK91,$Y91,IF(AJ91=$AK91,$AE91,"")))))) | AM91: =IF($AK91="","",$AK91/IF($E91="",1,$E91)) | AN91: =COUNT(L91,R91,X91,AD91,AJ91) | AO91: =IF(COUNT(L91,R91,X91,AD91,AJ91)=0,"",MAX(L91,R91,X91,AD91,AJ91)) | AP91: =IF(OR($AK91="",$AO91="",$AO91=0),"",($AO91-$AK91)/$AO91) | AQ91: =IF($AK91="","",IF(L91=$AK91,$K91,IF(R91=$AK91,$Q91,IF(X91=$AK91,$W91,IF(AD91=$AK91,$AC91,IF(AJ91=$AK91,$AI91,""))))))
A92: PP-SPICE-CAPEMALAY | B92: Spice Blend | C92: Cape Malay masala | D92: g | E92: 1 | F92: Y2 Autumn | L92: =IF(OR($J92="",$H92="",$H92=0),"",$J92/(1+IF(IFERROR(INDEX('03 Suppliers'!$N$5:$N$34,MATCH($G92,'03 Suppliers'!$B$5:$B$34,0)),"Excl VAT")="Incl VAT",'01 Control'!$C$6,0))/($H92*IFERROR(VLOOKUP($I92,'02 Lists'!$A$5:$B$18,2,FALSE()),1))) | R92: =IF(OR($P92="",$N92="",$N92=0),"",$P92/(1+IF(IFERROR(INDEX('03 Suppliers'!$N$5:$N$34,MATCH($M92,'03 Suppliers'!$B$5:$B$34,0)),"Excl VAT")="Incl VAT",'01 Control'!$C$6,0))/($N92*IFERROR(VLOOKUP($O92,'02 Lists'!$A$5:$B$18,2,FALSE()),1))) | X92: =IF(OR($V92="",$T92="",$T92=0),"",$V92/(1+IF(IFERROR(INDEX('03 Suppliers'!$N$5:$N$34,MATCH($S92,'03 Suppliers'!$B$5:$B$34,0)),"Excl VAT")="Incl VAT",'01 Control'!$C$6,0))/($T92*IFERROR(VLOOKUP($U92,'02 Lists'!$A$5:$B$18,2,FALSE()),1))) | AD92: =IF(OR($AB92="",$Z92="",$Z92=0),"",$AB92/(1+IF(IFERROR(INDEX('03 Suppliers'!$N$5:$N$34,MATCH($Y92,'03 Suppliers'!$B$5:$B$34,0)),"Excl VAT")="Incl VAT",'01 Control'!$C$6,0))/($Z92*IFERROR(VLOOKUP($AA92,'02 Lists'!$A$5:$B$18,2,FALSE()),1))) | AJ92: =IF(OR($AH92="",$AF92="",$AF92=0),"",$AH92/(1+IF(IFERROR(INDEX('03 Suppliers'!$N$5:$N$34,MATCH($AE92,'03 Suppliers'!$B$5:$B$34,0)),"Excl VAT")="Incl VAT",'01 Control'!$C$6,0))/($AF92*IFERROR(VLOOKUP($AG92,'02 Lists'!$A$5:$B$18,2,FALSE()),1))) | AK92: =IF(COUNT(L92,R92,X92,AD92,AJ92)=0,"",MIN(L92,R92,X92,AD92,AJ92)) | AL92: =IF($AK92="","",IF(L92=$AK92,$G92,IF(R92=$AK92,$M92,IF(X92=$AK92,$S92,IF(AD92=$AK92,$Y92,IF(AJ92=$AK92,$AE92,"")))))) | AM92: =IF($AK92="","",$AK92/IF($E92="",1,$E92)) | AN92: =COUNT(L92,R92,X92,AD92,AJ92) | AO92: =IF(COUNT(L92,R92,X92,AD92,AJ92)=0,"",MAX(L92,R92,X92,AD92,AJ92)) | AP92: =IF(OR($AK92="",$AO92="",$AO92=0),"",($AO92-$AK92)/$AO92) | AQ92: =IF($AK92="","",IF(L92=$AK92,$K92,IF(R92=$AK92,$Q92,IF(X92=$AK92,$W92,IF(AD92=$AK92,$AC92,IF(AJ92=$AK92,$AI92,""))))))
A93: PP-SPICE-HARISSA | B93: Spice Blend | C93: Harissa paste | D93: g | E93: 1 | F93: Y2 Winter | L93: =IF(OR($J93="",$H93="",$H93=0),"",$J93/(1+IF(IFERROR(INDEX('03 Suppliers'!$N$5:$N$34,MATCH($G93,'03 Suppliers'!$B$5:$B$34,0)),"Excl VAT")="Incl VAT",'01 Control'!$C$6,0))/($H93*IFERROR(VLOOKUP($I93,'02 Lists'!$A$5:$B$18,2,FALSE()),1))) | R93: =IF(OR($P93="",$N93="",$N93=0),"",$P93/(1+IF(IFERROR(INDEX('03 Suppliers'!$N$5:$N$34,MATCH($M93,'03 Suppliers'!$B$5:$B$34,0)),"Excl VAT")="Incl VAT",'01 Control'!$C$6,0))/($N93*IFERROR(VLOOKUP($O93,'02 Lists'!$A$5:$B$18,2,FALSE()),1))) | X93: =IF(OR($V93="",$T93="",$T93=0),"",$V93/(1+IF(IFERROR(INDEX('03 Suppliers'!$N$5:$N$34,MATCH($S93,'03 Suppliers'!$B$5:$B$34,0)),"Excl VAT")="Incl VAT",'01 Control'!$C$6,0))/($T93*IFERROR(VLOOKUP($U93,'02 Lists'!$A$5:$B$18,2,FALSE()),1))) | AD93: =IF(OR($AB93="",$Z93="",$Z93=0),"",$AB93/(1+IF(IFERROR(INDEX('03 Suppliers'!$N$5:$N$34,MATCH($Y93,'03 Suppliers'!$B$5:$B$34,0)),"Excl VAT")="Incl VAT",'01 Control'!$C$6,0))/($Z93*IFERROR(VLOOKUP($AA93,'02 Lists'!$A$5:$B$18,2,FALSE()),1))) | AJ93: =IF(OR($AH93="",$AF93="",$AF93=0),"",$AH93/(1+IF(IFERROR(INDEX('03 Suppliers'!$N$5:$N$34,MATCH($AE93,'03 Suppliers'!$B$5:$B$34,0)),"Excl VAT")="Incl VAT",'01 Control'!$C$6,0))/($AF93*IFERROR(VLOOKUP($AG93,'02 Lists'!$A$5:$B$18,2,FALSE()),1))) | AK93: =IF(COUNT(L93,R93,X93,AD93,AJ93)=0,"",MIN(L93,R93,X93,AD93,AJ93)) | AL93: =IF($AK93="","",IF(L93=$AK93,$G93,IF(R93=$AK93,$M93,IF(X93=$AK93,$S93,IF(AD93=$AK93,$Y93,IF(AJ93=$AK93,$AE93,"")))))) | AM93: =IF($AK93="","",$AK93/IF($E93="",1,$E93)) | AN93: =COUNT(L93,R93,X93,AD93,AJ93) | AO93: =IF(COUNT(L93,R93,X93,AD93,AJ93)=0,"",MAX(L93,R93,X93,AD93,AJ93)) | AP93: =IF(OR($AK93="",$AO93="",$AO93=0),"",($AO93-$AK93)/$AO93) | AQ93: =IF($AK93="","",IF(L93=$AK93,$K93,IF(R93=$AK93,$Q93,IF(X93=$AK93,$W93,IF(AD93=$AK93,$AC93,IF(AJ93=$AK93,$AI93,""))))))
A94: PP-SPICE-BERBERE | B94: Spice Blend | C94: Berbere spice (Ethiopian) | D94: g | E94: 1 | F94: Y2 Winter | L94: =IF(OR($J94="",$H94="",$H94=0),"",$J94/(1+IF(IFERROR(INDEX('03 Suppliers'!$N$5:$N$34,MATCH($G94,'03 Suppliers'!$B$5:$B$34,0)),"Excl VAT")="Incl VAT",'01 Control'!$C$6,0))/($H94*IFERROR(VLOOKUP($I94,'02 Lists'!$A$5:$B$18,2,FALSE()),1))) | R94: =IF(OR($P94="",$N94="",$N94=0),"",$P94/(1+IF(IFERROR(INDEX('03 Suppliers'!$N$5:$N$34,MATCH($M94,'03 Suppliers'!$B$5:$B$34,0)),"Excl VAT")="Incl VAT",'01 Control'!$C$6,0))/($N94*IFERROR(VLOOKUP($O94,'02 Lists'!$A$5:$B$18,2,FALSE()),1))) | X94: =IF(OR($V94="",$T94="",$T94=0),"",$V94/(1+IF(IFERROR(INDEX('03 Suppliers'!$N$5:$N$34,MATCH($S94,'03 Suppliers'!$B$5:$B$34,0)),"Excl VAT")="Incl VAT",'01 Control'!$C$6,0))/($T94*IFERROR(VLOOKUP($U94,'02 Lists'!$A$5:$B$18,2,FALSE()),1))) | AD94: =IF(OR($AB94="",$Z94="",$Z94=0),"",$AB94/(1+IF(IFERROR(INDEX('03 Suppliers'!$N$5:$N$34,MATCH($Y94,'03 Suppliers'!$B$5:$B$34,0)),"Excl VAT")="Incl VAT",'01 Control'!$C$6,0))/($Z94*IFERROR(VLOOKUP($AA94,'02 Lists'!$A$5:$B$18,2,FALSE()),1))) | AJ94: =IF(OR($AH94="",$AF94="",$AF94=0),"",$AH94/(1+IF(IFERROR(INDEX('03 Suppliers'!$N$5:$N$34,MATCH($AE94,'03 Suppliers'!$B$5:$B$34,0)),"Excl VAT")="Incl VAT",'01 Control'!$C$6,0))/($AF94*IFERROR(VLOOKUP($AG94,'02 Lists'!$A$5:$B$18,2,FALSE()),1))) | AK94: =IF(COUNT(L94,R94,X94,AD94,AJ94)=0,"",MIN(L94,R94,X94,AD94,AJ94)) | AL94: =IF($AK94="","",IF(L94=$AK94,$G94,IF(R94=$AK94,$M94,IF(X94=$AK94,$S94,IF(AD94=$AK94,$Y94,IF(AJ94=$AK94,$AE94,"")))))) | AM94: =IF($AK94="","",$AK94/IF($E94="",1,$E94)) | AN94: =COUNT(L94,R94,X94,AD94,AJ94) | AO94: =IF(COUNT(L94,R94,X94,AD94,AJ94)=0,"",MAX(L94,R94,X94,AD94,AJ94)) | AP94: =IF(OR($AK94="",$AO94="",$AO94=0),"",($AO94-$AK94)/$AO94) | AQ94: =IF($AK94="","",IF(L94=$AK94,$K94,IF(R94=$AK94,$Q94,IF(X94=$AK94,$W94,IF(AD94=$AK94,$AC94,IF(AJ94=$AK94,$AI94,""))))))
A95: PP-SPICE-CHERMOULA | B95: Spice Blend | C95: Chermoula blend (coriander, cumin, lemon) | D95: g | E95: 1 | F95: Y2 Winter | L95: =IF(OR($J95="",$H95="",$H95=0),"",$J95/(1+IF(IFERROR(INDEX('03 Suppliers'!$N$5:$N$34,MATCH($G95,'03 Suppliers'!$B$5:$B$34,0)),"Excl VAT")="Incl VAT",'01 Control'!$C$6,0))/($H95*IFERROR(VLOOKUP($I95,'02 Lists'!$A$5:$B$18,2,FALSE()),1))) | R95: =IF(OR($P95="",$N95="",$N95=0),"",$P95/(1+IF(IFERROR(INDEX('03 Suppliers'!$N$5:$N$34,MATCH($M95,'03 Suppliers'!$B$5:$B$34,0)),"Excl VAT")="Incl VAT",'01 Control'!$C$6,0))/($N95*IFERROR(VLOOKUP($O95,'02 Lists'!$A$5:$B$18,2,FALSE()),1))) | X95: =IF(OR($V95="",$T95="",$T95=0),"",$V95/(1+IF(IFERROR(INDEX('03 Suppliers'!$N$5:$N$34,MATCH($S95,'03 Suppliers'!$B$5:$B$34,0)),"Excl VAT")="Incl VAT",'01 Control'!$C$6,0))/($T95*IFERROR(VLOOKUP($U95,'02 Lists'!$A$5:$B$18,2,FALSE()),1))) | AD95: =IF(OR($AB95="",$Z95="",$Z95=0),"",$AB95/(1+IF(IFERROR(INDEX('03 Suppliers'!$N$5:$N$34,MATCH($Y95,'03 Suppliers'!$B$5:$B$34,0)),"Excl VAT")="Incl VAT",'01 Control'!$C$6,0))/($Z95*IFERROR(VLOOKUP($AA95,'02 Lists'!$A$5:$B$18,2,FALSE()),1))) | AJ95: =IF(OR($AH95="",$AF95="",$AF95=0),"",$AH95/(1+IF(IFERROR(INDEX('03 Suppliers'!$N$5:$N$34,MATCH($AE95,'03 Suppliers'!$B$5:$B$34,0)),"Excl VAT")="Incl VAT",'01 Control'!$C$6,0))/($AF95*IFERROR(VLOOKUP($AG95,'02 Lists'!$A$5:$B$18,2,FALSE()),1))) | AK95: =IF(COUNT(L95,R95,X95,AD95,AJ95)=0,"",MIN(L95,R95,X95,AD95,AJ95)) | AL95: =IF($AK95="","",IF(L95=$AK95,$G95,IF(R95=$AK95,$M95,IF(X95=$AK95,$S95,IF(AD95=$AK95,$Y95,IF(AJ95=$AK95,$AE95,"")))))) | AM95: =IF($AK95="","",$AK95/IF($E95="",1,$E95)) | AN95: =COUNT(L95,R95,X95,AD95,AJ95) | AO95: =IF(COUNT(L95,R95,X95,AD95,AJ95)=0,"",MAX(L95,R95,X95,AD95,AJ95)) | AP95: =IF(OR($AK95="",$AO95="",$AO95=0),"",($AO95-$AK95)/$AO95) | AQ95: =IF($AK95="","",IF(L95=$AK95,$K95,IF(R95=$AK95,$Q95,IF(X95=$AK95,$W95,IF(AD95=$AK95,$AC95,IF(AJ95=$AK95,$AI95,""))))))
A96: PP-SPICE-JOLLOF | B96: Spice Blend | C96: Jollof spice | D96: g | E96: 1 | F96: Y2 Spring | L96: =IF(OR($J96="",$H96="",$H96=0),"",$J96/(1+IF(IFERROR(INDEX('03 Suppliers'!$N$5:$N$34,MATCH($G96,'03 Suppliers'!$B$5:$B$34,0)),"Excl VAT")="Incl VAT",'01 Control'!$C$6,0))/($H96*IFERROR(VLOOKUP($I96,'02 Lists'!$A$5:$B$18,2,FALSE()),1))) | R96: =IF(OR($P96="",$N96="",$N96=0),"",$P96/(1+IF(IFERROR(INDEX('03 Suppliers'!$N$5:$N$34,MATCH($M96,'03 Suppliers'!$B$5:$B$34,0)),"Excl VAT")="Incl VAT",'01 Control'!$C$6,0))/($N96*IFERROR(VLOOKUP($O96,'02 Lists'!$A$5:$B$18,2,FALSE()),1))) | X96: =IF(OR($V96="",$T96="",$T96=0),"",$V96/(1+IF(IFERROR(INDEX('03 Suppliers'!$N$5:$N$34,MATCH($S96,'03 Suppliers'!$B$5:$B$34,0)),"Excl VAT")="Incl VAT",'01 Control'!$C$6,0))/($T96*IFERROR(VLOOKUP($U96,'02 Lists'!$A$5:$B$18,2,FALSE()),1))) | AD96: =IF(OR($AB96="",$Z96="",$Z96=0),"",$AB96/(1+IF(IFERROR(INDEX('03 Suppliers'!$N$5:$N$34,MATCH($Y96,'03 Suppliers'!$B$5:$B$34,0)),"Excl VAT")="Incl VAT",'01 Control'!$C$6,0))/($Z96*IFERROR(VLOOKUP($AA96,'02 Lists'!$A$5:$B$18,2,FALSE()),1))) | AJ96: =IF(OR($AH96="",$AF96="",$AF96=0),"",$AH96/(1+IF(IFERROR(INDEX('03 Suppliers'!$N$5:$N$34,MATCH($AE96,'03 Suppliers'!$B$5:$B$34,0)),"Excl VAT")="Incl VAT",'01 Control'!$C$6,0))/($AF96*IFERROR(VLOOKUP($AG96,'02 Lists'!$A$5:$B$18,2,FALSE()),1))) | AK96: =IF(COUNT(L96,R96,X96,AD96,AJ96)=0,"",MIN(L96,R96,X96,AD96,AJ96)) | AL96: =IF($AK96="","",IF(L96=$AK96,$G96,IF(R96=$AK96,$M96,IF(X96=$AK96,$S96,IF(AD96=$AK96,$Y96,IF(AJ96=$AK96,$AE96,"")))))) | AM96: =IF($AK96="","",$AK96/IF($E96="",1,$E96)) | AN96: =COUNT(L96,R96,X96,AD96,AJ96) | AO96: =IF(COUNT(L96,R96,X96,AD96,AJ96)=0,"",MAX(L96,R96,X96,AD96,AJ96)) | AP96: =IF(OR($AK96="",$AO96="",$AO96=0),"",($AO96-$AK96)/$AO96) | AQ96: =IF($AK96="","",IF(L96=$AK96,$K96,IF(R96=$AK96,$Q96,IF(X96=$AK96,$W96,IF(AD96=$AK96,$AC96,IF(AJ96=$AK96,$AI96,""))))))
... A106: PP-BEV-SYR-ROOIBOS | B106: Beverage | C106: Rooibos slushee concentrate | D106: ml | E106: 1 | F106: The anchor slushee flavour | L106: =IF(OR($J106="",$H106="",$H106=0),"",$J106/(1+IF(IFERROR(INDEX('03 Suppliers'!$N$5:$N$34,MATCH($G106,'03 Suppliers'!$B$5:$B$34,0)),"Excl VAT")="Incl VAT",'01 Control'!$C$6,0))/($H106*IFERROR(VLOOKUP($I106,'02 Lists'!$A$5:$B$18,2,FALSE()),1))) | R106: =IF(OR($P106="",$N106="",$N106=0),"",$P106/(1+IF(IFERROR(INDEX('03 Suppliers'!$N$5:$N$34,MATCH($M106,'03 Suppliers'!$B$5:$B$34,0)),"Excl VAT")="Incl VAT",'01 Control'!$C$6,0))/($N106*IFERROR(VLOOKUP($O106,'02 Lists'!$A$5:$B$18,2,FALSE()),1))) | X106: =IF(OR($V106="",$T106="",$T106=0),"",$V106/(1+IF(IFERROR(INDEX('03 Suppliers'!$N$5:$N$34,MATCH($S106,'03 Suppliers'!$B$5:$B$34,0)),"Excl VAT")="Incl VAT",'01 Control'!$C$6,0))/($T106*IFERROR(VLOOKUP($U106,'02 Lists'!$A$5:$B$18,2,FALSE()),1))) | AD106: =IF(OR($AB106="",$Z106="",$Z106=0),"",$AB106/(1+IF(IFERROR(INDEX('03 Suppliers'!$N$5:$N$34,MATCH($Y106,'03 Suppliers'!$B$5:$B$34,0)),"Excl VAT")="Incl VAT",'01 Control'!$C$6,0))/($Z106*IFERROR(VLOOKUP($AA106,'02 Lists'!$A$5:$B$18,2,FALSE()),1))) | AJ106: =IF(OR($AH106="",$AF106="",$AF106=0),"",$AH106/(1+IF(IFERROR(INDEX('03 Suppliers'!$N$5:$N$34,MATCH($AE106,'03 Suppliers'!$B$5:$B$34,0)),"Excl VAT")="Incl VAT",'01 Control'!$C$6,0))/($AF106*IFERROR(VLOOKUP($AG106,'02 Lists'!$A$5:$B$18,2,FALSE()),1))) | AK106: =IF(COUNT(L106,R106,X106,AD106,AJ106)=0,"",MIN(L106,R106,X106,AD106,AJ106)) | AL106: =IF($AK106="","",IF(L106=$AK106,$G106,IF(R106=$AK106,$M106,IF(X106=$AK106,$S106,IF(AD106=$AK106,$Y106,IF(AJ106=$AK106,$AE106,"")))))) | AM106: =IF($AK106="","",$AK106/IF($E106="",1,$E106)) | AN106: =COUNT(L106,R106,X106,AD106,AJ106) | AO106: =IF(COUNT(L106,R106,X106,AD106,AJ106)=0,"",MAX(L106,R106,X106,AD106,AJ106)) | AP106: =IF(OR($AK106="",$AO106="",$AO106=0),"",($AO106-$AK106)/$AO106) | AQ106: =IF($AK106="","",IF(L106=$AK106,$K106,IF(R106=$AK106,$Q106,IF(X106=$AK106,$W106,IF(AD106=$AK106,$AC106,IF(AJ106=$AK106,$AI106,""))))))
A107: PP-BEV-SYR-LEMON | B107: Beverage | C107: Lemonade slushee concentrate | D107: ml | E107: 1 | L107: =IF(OR($J107="",$H107="",$H107=0),"",$J107/(1+IF(IFERROR(INDEX('03 Suppliers'!$N$5:$N$34,MATCH($G107,'03 Suppliers'!$B$5:$B$34,0)),"Excl VAT")="Incl VAT",'01 Control'!$C$6,0))/($H107*IFERROR(VLOOKUP($I107,'02 Lists'!$A$5:$B$18,2,FALSE()),1))) | R107: =IF(OR($P107="",$N107="",$N107=0),"",$P107/(1+IF(IFERROR(INDEX('03 Suppliers'!$N$5:$N$34,MATCH($M107,'03 Suppliers'!$B$5:$B$34,0)),"Excl VAT")="Incl VAT",'01 Control'!$C$6,0))/($N107*IFERROR(VLOOKUP($O107,'02 Lists'!$A$5:$B$18,2,FALSE()),1))) | X107: =IF(OR($V107="",$T107="",$T107=0),"",$V107/(1+IF(IFERROR(INDEX('03 Suppliers'!$N$5:$N$34,MATCH($S107,'03 Suppliers'!$B$5:$B$34,0)),"Excl VAT")="Incl VAT",'01 Control'!$C$6,0))/($T107*IFERROR(VLOOKUP($U107,'02 Lists'!$A$5:$B$18,2,FALSE()),1))) | AD107: =IF(OR($AB107="",$Z107="",$Z107=0),"",$AB107/(1+IF(IFERROR(INDEX('03 Suppliers'!$N$5:$N$34,MATCH($Y107,'03 Suppliers'!$B$5:$B$34,0)),"Excl VAT")="Incl VAT",'01 Control'!$C$6,0))/($Z107*IFERROR(VLOOKUP($AA107,'02 Lists'!$A$5:$B$18,2,FALSE()),1))) | AJ107: =IF(OR($AH107="",$AF107="",$AF107=0),"",$AH107/(1+IF(IFERROR(INDEX('03 Suppliers'!$N$5:$N$34,MATCH($AE107,'03 Suppliers'!$B$5:$B$34,0)),"Excl VAT")="Incl VAT",'01 Control'!$C$6,0))/($AF107*IFERROR(VLOOKUP($AG107,'02 Lists'!$A$5:$B$18,2,FALSE()),1))) | AK107: =IF(COUNT(L107,R107,X107,AD107,AJ107)=0,"",MIN(L107,R107,X107,AD107,AJ107)) | AL107: =IF($AK107="","",IF(L107=$AK107,$G107,IF(R107=$AK107,$M107,IF(X107=$AK107,$S107,IF(AD107=$AK107,$Y107,IF(AJ107=$AK107,$AE107,"")))))) | AM107: =IF($AK107="","",$AK107/IF($E107="",1,$E107)) | AN107: =COUNT(L107,R107,X107,AD107,AJ107) | AO107: =IF(COUNT(L107,R107,X107,AD107,AJ107)=0,"",MAX(L107,R107,X107,AD107,AJ107)) | AP107: =IF(OR($AK107="",$AO107="",$AO107=0),"",($AO107-$AK107)/$AO107) | AQ107: =IF($AK107="","",IF(L107=$AK107,$K107,IF(R107=$AK107,$Q107,IF(X107=$AK107,$W107,IF(AD107=$AK107,$AC107,IF(AJ107=$AK107,$AI107,""))))))
A108: PP-BEV-SYR-CREAM | B108: Beverage | C108: Cream soda slushee concentrate | D108: ml | E108: 1 | L108: =IF(OR($J108="",$H108="",$H108=0),"",$J108/(1+IF(IFERROR(INDEX('03 Suppliers'!$N$5:$N$34,MATCH($G108,'03 Suppliers'!$B$5:$B$34,0)),"Excl VAT")="Incl VAT",'01 Control'!$C$6,0))/($H108*IFERROR(VLOOKUP($I108,'02 Lists'!$A$5:$B$18,2,FALSE()),1))) | R108: =IF(OR($P108="",$N108="",$N108=0),"",$P108/(1+IF(IFERROR(INDEX('03 Suppliers'!$N$5:$N$34,MATCH($M108,'03 Suppliers'!$B$5:$B$34,0)),"Excl VAT")="Incl VAT",'01 Control'!$C$6,0))/($N108*IFERROR(VLOOKUP($O108,'02 Lists'!$A$5:$B$18,2,FALSE()),1))) | X108: =IF(OR($V108="",$T108="",$T108=0),"",$V108/(1+IF(IFERROR(INDEX('03 Suppliers'!$N$5:$N$34,MATCH($S108,'03 Suppliers'!$B$5:$B$34,0)),"Excl VAT")="Incl VAT",'01 Control'!$C$6,0))/($T108*IFERROR(VLOOKUP($U108,'02 Lists'!$A$5:$B$18,2,FALSE()),1))) | AD108: =IF(OR($AB108="",$Z108="",$Z108=0),"",$AB108/(1+IF(IFERROR(INDEX('03 Suppliers'!$N$5:$N$34,MATCH($Y108,'03 Suppliers'!$B$5:$B$34,0)),"Excl VAT")="Incl VAT",'01 Control'!$C$6,0))/($Z108*IFERROR(VLOOKUP($AA108,'02 Lists'!$A$5:$B$18,2,FALSE()),1))) | AJ108: =IF(OR($AH108="",$AF108="",$AF108=0),"",$AH108/(1+IF(IFERROR(INDEX('03 Suppliers'!$N$5:$N$34,MATCH($AE108,'03 Suppliers'!$B$5:$B$34,0)),"Excl VAT")="Incl VAT",'01 Control'!$C$6,0))/($AF108*IFERROR(VLOOKUP($AG108,'02 Lists'!$A$5:$B$18,2,FALSE()),1))) | AK108: =IF(COUNT(L108,R108,X108,AD108,AJ108)=0,"",MIN(L108,R108,X108,AD108,AJ108)) | AL108: =IF($AK108="","",IF(L108=$AK108,$G108,IF(R108=$AK108,$M108,IF(X108=$AK108,$S108,IF(AD108=$AK108,$Y108,IF(AJ108=$AK108,$AE108,"")))))) | AM108: =IF($AK108="","",$AK108/IF($E108="",1,$E108)) | AN108: =COUNT(L108,R108,X108,AD108,AJ108) | AO108: =IF(COUNT(L108,R108,X108,AD108,AJ108)=0,"",MAX(L108,R108,X108,AD108,AJ108)) | AP108: =IF(OR($AK108="",$AO108="",$AO108=0),"",($AO108-$AK108)/$AO108) | AQ108: =IF($AK108="","",IF(L108=$AK108,$K108,IF(R108=$AK108,$Q108,IF(X108=$AK108,$W108,IF(AD108=$AK108,$AC108,IF(AJ108=$AK108,$AI108,""))))))
A109: PP-BEV-SYR-ROTATING | B109: Beverage | C109: Rotating slushee concentrate (seasonal) | D109: ml | E109: 1 | F109: 2 flavours live at a time | L109: =IF(OR($J109="",$H109="",$H109=0),"",$J109/(1+IF(IFERROR(INDEX('03 Suppliers'!$N$5:$N$34,MATCH($G109,'03 Suppliers'!$B$5:$B$34,0)),"Excl VAT")="Incl VAT",'01 Control'!$C$6,0))/($H109*IFERROR(VLOOKUP($I109,'02 Lists'!$A$5:$B$18,2,FALSE()),1))) | R109: =IF(OR($P109="",$N109="",$N109=0),"",$P109/(1+IF(IFERROR(INDEX('03 Suppliers'!$N$5:$N$34,MATCH($M109,'03 Suppliers'!$B$5:$B$34,0)),"Excl VAT")="Incl VAT",'01 Control'!$C$6,0))/($N109*IFERROR(VLOOKUP($O109,'02 Lists'!$A$5:$B$18,2,FALSE()),1))) | X109: =IF(OR($V109="",$T109="",$T109=0),"",$V109/(1+IF(IFERROR(INDEX('03 Suppliers'!$N$5:$N$34,MATCH($S109,'03 Suppliers'!$B$5:$B$34,0)),"Excl VAT")="Incl VAT",'01 Control'!$C$6,0))/($T109*IFERROR(VLOOKUP($U109,'02 Lists'!$A$5:$B$18,2,FALSE()),1))) | AD109: =IF(OR($AB109="",$Z109="",$Z109=0),"",$AB109/(1+IF(IFERROR(INDEX('03 Suppliers'!$N$5:$N$34,MATCH($Y109,'03 Suppliers'!$B$5:$B$34,0)),"Excl VAT")="Incl VAT",'01 Control'!$C$6,0))/($Z109*IFERROR(VLOOKUP($AA109,'02 Lists'!$A$5:$B$18,2,FALSE()),1))) | AJ109: =IF(OR($AH109="",$AF109="",$AF109=0),"",$AH109/(1+IF(IFERROR(INDEX('03 Suppliers'!$N$5:$N$34,MATCH($AE109,'03 Suppliers'!$B$5:$B$34,0)),"Excl VAT")="Incl VAT",'01 Control'!$C$6,0))/($AF109*IFERROR(VLOOKUP($AG109,'02 Lists'!$A$5:$B$18,2,FALSE()),1))) | AK109: =IF(COUNT(L109,R109,X109,AD109,AJ109)=0,"",MIN(L109,R109,X109,AD109,AJ109)) | AL109: =IF($AK109="","",IF(L109=$AK109,$G109,IF(R109=$AK109,$M109,IF(X109=$AK109,$S109,IF(AD109=$AK109,$Y109,IF(AJ109=$AK109,$AE109,"")))))) | AM109: =IF($AK109="","",$AK109/IF($E109="",1,$E109)) | AN109: =COUNT(L109,R109,X109,AD109,AJ109) | AO109: =IF(COUNT(L109,R109,X109,AD109,AJ109)=0,"",MAX(L109,R109,X109,AD109,AJ109)) | AP109: =IF(OR($AK109="",$AO109="",$AO109=0),"",($AO109-$AK109)/$AO109) | AQ109: =IF($AK109="","",IF(L109=$AK109,$K109,IF(R109=$AK109,$Q109,IF(X109=$AK109,$W109,IF(AD109=$AK109,$AC109,IF(AJ109=$AK109,$AI109,""))))))
A110: PP-BEV-SYR-NAARTJIE | B110: Beverage | C110: Naartjie slushee concentrate | D110: ml | E110: 1 | F110: SA citrus anchor - the local hero flavour | L110: =IF(OR($J110="",$H110="",$H110=0),"",$J110/(1+IF(IFERROR(INDEX('03 Suppliers'!$N$5:$N$34,MATCH($G110,'03 Suppliers'!$B$5:$B$34,0)),"Excl VAT")="Incl VAT",'01 Control'!$C$6,0))/($H110*IFERROR(VLOOKUP($I110,'02 Lists'!$A$5:$B$18,2,FALSE()),1))) | R110: =IF(OR($P110="",$N110="",$N110=0),"",$P110/(1+IF(IFERROR(INDEX('03 Suppliers'!$N$5:$N$34,MATCH($M110,'03 Suppliers'!$B$5:$B$34,0)),"Excl VAT")="Incl VAT",'01 Control'!$C$6,0))/($N110*IFERROR(VLOOKUP($O110,'02 Lists'!$A$5:$B$18,2,FALSE()),1))) | X110: =IF(OR($V110="",$T110="",$T110=0),"",$V110/(1+IF(IFERROR(INDEX('03 Suppliers'!$N$5:$N$34,MATCH($S110,'03 Suppliers'!$B$5:$B$34,0)),"Excl VAT")="Incl VAT",'01 Control'!$C$6,0))/($T110*IFERROR(VLOOKUP($U110,'02 Lists'!$A$5:$B$18,2,FALSE()),1))) | AD110: =IF(OR($AB110="",$Z110="",$Z110=0),"",$AB110/(1+IF(IFERROR(INDEX('03 Suppliers'!$N$5:$N$34,MATCH($Y110,'03 Suppliers'!$B$5:$B$34,0)),"Excl VAT")="Incl VAT",'01 Control'!$C$6,0))/($Z110*IFERROR(VLOOKUP($AA110,'02 Lists'!$A$5:$B$18,2,FALSE()),1))) | AJ110: =IF(OR($AH110="",$AF110="",$AF110=0),"",$AH110/(1+IF(IFERROR(INDEX('03 Suppliers'!$N$5:$N$34,MATCH($AE110,'03 Suppliers'!$B$5:$B$34,0)),"Excl VAT")="Incl VAT",'01 Control'!$C$6,0))/($AF110*IFERROR(VLOOKUP($AG110,'02 Lists'!$A$5:$B$18,2,FALSE()),1))) | AK110: =IF(COUNT(L110,R110,X110,AD110,AJ110)=0,"",MIN(L110,R110,X110,AD110,AJ110)) | AL110: =IF($AK110="","",IF(L110=$AK110,$G110,IF(R110=$AK110,$M110,IF(X110=$AK110,$S110,IF(AD110=$AK110,$Y110,IF(AJ110=$AK110,$AE110,"")))))) | AM110: =IF($AK110="","",$AK110/IF($E110="",1,$E110)) | AN110: =COUNT(L110,R110,X110,AD110,AJ110) | AO110: =IF(COUNT(L110,R110,X110,AD110,AJ110)=0,"",MAX(L110,R110,X110,AD110,AJ110)) | AP110: =IF(OR($AK110="",$AO110="",$AO110=0),"",($AO110-$AK110)/$AO110) | AQ110: =IF($AK110="","",IF(L110=$AK110,$K110,IF(R110=$AK110,$Q110,IF(X110=$AK110,$W110,IF(AD110=$AK110,$AC110,IF(AJ110=$AK110,$AI110,""))))))
A111: PP-BEV-SYR-GRANADILLA | B111: Beverage | C111: Granadilla slushee concentrate | D111: ml | E111: 1 | F111: Granadilla reads premium and is unmistakably SA | L111: =IF(OR($J111="",$H111="",$H111=0),"",$J111/(1+IF(IFERROR(INDEX('03 Suppliers'!$N$5:$N$34,MATCH($G111,'03 Suppliers'!$B$5:$B$34,0)),"Excl VAT")="Incl VAT",'01 Control'!$C$6,0))/($H111*IFERROR(VLOOKUP($I111,'02 Lists'!$A$5:$B$18,2,FALSE()),1))) | R111: =IF(OR($P111="",$N111="",$N111=0),"",$P111/(1+IF(IFERROR(INDEX('03 Suppliers'!$N$5:$N$34,MATCH($M111,'03 Suppliers'!$B$5:$B$34,0)),"Excl VAT")="Incl VAT",'01 Control'!$C$6,0))/($N111*IFERROR(VLOOKUP($O111,'02 Lists'!$A$5:$B$18,2,FALSE()),1))) | X111: =IF(OR($V111="",$T111="",$T111=0),"",$V111/(1+IF(IFERROR(INDEX('03 Suppliers'!$N$5:$N$34,MATCH($S111,'03 Suppliers'!$B$5:$B$34,0)),"Excl VAT")="Incl VAT",'01 Control'!$C$6,0))/($T111*IFERROR(VLOOKUP($U111,'02 Lists'!$A$5:$B$18,2,FALSE()),1))) | AD111: =IF(OR($AB111="",$Z111="",$Z111=0),"",$AB111/(1+IF(IFERROR(INDEX('03 Suppliers'!$N$5:$N$34,MATCH($Y111,'03 Suppliers'!$B$5:$B$34,0)),"Excl VAT")="Incl VAT",'01 Control'!$C$6,0))/($Z111*IFERROR(VLOOKUP($AA111,'02 Lists'!$A$5:$B$18,2,FALSE()),1))) | AJ111: =IF(OR($AH111="",$AF111="",$AF111=0),"",$AH111/(1+IF(IFERROR(INDEX('03 Suppliers'!$N$5:$N$34,MATCH($AE111,'03 Suppliers'!$B$5:$B$34,0)),"Excl VAT")="Incl VAT",'01 Control'!$C$6,0))/($AF111*IFERROR(VLOOKUP($AG111,'02 Lists'!$A$5:$B$18,2,FALSE()),1))) | AK111: =IF(COUNT(L111,R111,X111,AD111,AJ111)=0,"",MIN(L111,R111,X111,AD111,AJ111)) | AL111: =IF($AK111="","",IF(L111=$AK111,$G111,IF(R111=$AK111,$M111,IF(X111=$AK111,$S111,IF(AD111=$AK111,$Y111,IF(AJ111=$AK111,$AE111,"")))))) | AM111: =IF($AK111="","",$AK111/IF($E111="",1,$E111)) | AN111: =COUNT(L111,R111,X111,AD111,AJ111) | AO111: =IF(COUNT(L111,R111,X111,AD111,AJ111)=0,"",MAX(L111,R111,X111,AD111,AJ111)) | AP111: =IF(OR($AK111="",$AO111="",$AO111=0),"",($AO111-$AK111)/$AO111) | AQ111: =IF($AK111="","",IF(L111=$AK111,$K111,IF(R111=$AK111,$Q111,IF(X111=$AK111,$W111,IF(AD111=$AK111,$AC111,IF(AJ111=$AK111,$AI111,""))))))
A112: PP-BEV-SYR-STRAWBERRY | B112: Beverage | C112: Strawberry slushee concentrate | D112: ml | E112: 1 | F112: Universal safe pick - highest volume flavour in every slush bar | L112: =IF(OR($J112="",$H112="",$H112=0),"",$J112/(1+IF(IFERROR(INDEX('03 Suppliers'!$N$5:$N$34,MATCH($G112,'03 Suppliers'!$B$5:$B$34,0)),"Excl VAT")="Incl VAT",'01 Control'!$C$6,0))/($H112*IFERROR(VLOOKUP($I112,'02 Lists'!$A$5:$B$18,2,FALSE()),1))) | R112: =IF(OR($P112="",$N112="",$N112=0),"",$P112/(1+IF(IFERROR(INDEX('03 Suppliers'!$N$5:$N$34,MATCH($M112,'03 Suppliers'!$B$5:$B$34,0)),"Excl VAT")="Incl VAT",'01 Control'!$C$6,0))/($N112*IFERROR(VLOOKUP($O112,'02 Lists'!$A$5:$B$18,2,FALSE()),1))) | X112: =IF(OR($V112="",$T112="",$T112=0),"",$V112/(1+IF(IFERROR(INDEX('03 Suppliers'!$N$5:$N$34,MATCH($S112,'03 Suppliers'!$B$5:$B$34,0)),"Excl VAT")="Incl VAT",'01 Control'!$C$6,0))/($T112*IFERROR(VLOOKUP($U112,'02 Lists'!$A$5:$B$18,2,FALSE()),1))) | AD112: =IF(OR($AB112="",$Z112="",$Z112=0),"",$AB112/(1+IF(IFERROR(INDEX('03 Suppliers'!$N$5:$N$34,MATCH($Y112,'03 Suppliers'!$B$5:$B$34,0)),"Excl VAT")="Incl VAT",'01 Control'!$C$6,0))/($Z112*IFERROR(VLOOKUP($AA112,'02 Lists'!$A$5:$B$18,2,FALSE()),1))) | AJ112: =IF(OR($AH112="",$AF112="",$AF112=0),"",$AH112/(1+IF(IFERROR(INDEX('03 Suppliers'!$N$5:$N$34,MATCH($AE112,'03 Suppliers'!$B$5:$B$34,0)),"Excl VAT")="Incl VAT",'01 Control'!$C$6,0))/($AF112*IFERROR(VLOOKUP($AG112,'02 Lists'!$A$5:$B$18,2,FALSE()),1))) | AK112: =IF(COUNT(L112,R112,X112,AD112,AJ112)=0,"",MIN(L112,R112,X112,AD112,AJ112)) | AL112: =IF($AK112="","",IF(L112=$AK112,$G112,IF(R112=$AK112,$M112,IF(X112=$AK112,$S112,IF(AD112=$AK112,$Y112,IF(AJ112=$AK112,$AE112,"")))))) | AM112: =IF($AK112="","",$AK112/IF($E112="",1,$E112)) | AN112: =COUNT(L112,R112,X112,AD112,AJ112) | AO112: =IF(COUNT(L112,R112,X112,AD112,AJ112)=0,"",MAX(L112,R112,X112,AD112,AJ112)) | AP112: =IF(OR($AK112="",$AO112="",$AO112=0),"",($AO112-$AK112)/$AO112) | AQ112: =IF($AK112="","",IF(L112=$AK112,$K112,IF(R112=$AK112,$Q112,IF(X112=$AK112,$W112,IF(AD112=$AK112,$AC112,IF(AJ112=$AK112,$AI112,""))))))
